Workbook

Sheet Variables
A1: Department: | B1: Interested | C1: Cleared
A2: Production Specialist 1 - Mechanical Assembly - A&C Shift
A3: Production Specialist 1 - Mechanical Assembly - B&D shift
A21: Total

Sheet Dashboard For Flex
A1: Applications | C1: Phone Screens | E1: Interviews | G1: Resume Subs
A2: Goal | B2: Attn | C2: Goal | D2: Attn | E2: Interviews Scheduled for today | F2: Interviews Scheduled for tomorrow | G2: Goal | H2: Attn | I2: Offers accepted | J2: Total in Pipeline | K2: Production Specialist 1 - Mechanical Assembly - A&C Shift | L2: Production Specialist 1 - Mechanical Assembly - A&C Shift Background cleared | M2: Production Specialist 1 - Mechanical Assembly - B&D shift | N2: Production Specialist 1 - Mechanical Assembly - B&D shift Background cleared | O2: Production Specialist 1 - Materials - A&C shift | P2: Production Specialist 1 - Materials - A&C shift Background cleared | Q2: Production Specialist 1 - Materials - B&D shift | R2: Production Specialist 1 - Materials - B&D shiftBackground cleared | S2: Production Specialist 1 - Rack Level Assembly - A&C shift | T2: Production Specialist 1 - Rack Level Assembly - A&C shift Background cleared | U2: Production Specialist 1 - Rack Level Assembly - B&D shift | V2: Production Specialist 1 - Rack Level Assembly - B&D shift Background cleared | W2: IT Support Technician - 1st Shift | X2: IT Support Technician - 1st Shift - Background cleared | Y2: Delivery Business Systems Analyst - 1st Shift | Z2: Delivery Business Systems Analyst - 1st Shift - Background cleared | AA2: Production Specialist 1 -Quality - B&D shift | AB2: Production Specialist 1 - Quality - B&D shift - Background cleared | AC2: Production Specialist 1 -Test Opertor - A&Cshift | AD2: Production Specialist 1 - Test Opertor - A&C shift - Background cleared | AE2: Production Specialist 1 - Mechanical Assy Debug - A&C shift | AF2: Production Specialist 1 - Mechanical Assy Debug - A&C shift - Background cleared | AG2: Debug Tech 4 - B&D shift | AH2: Debug Tech 4 - B&D shift - Background cleared | AI2: HR Generalist - 1st Shift | AJ2: Recruiter 1st Shift | AK2: Production Specialist 1 -Test Opertor - 1st shift | AL2: Production Specialist 1 - Test Opertor - 1st shift - Background cleared | AM2: Production Specialist 1 - Mechanical Assy Debug - 1st shift | AN2: Production Specialist 1 - Mechanical Assy Debug - 1st shift - Background cleared | AO2: Debug Tech 4 - 2nd shift | AP2: Debug Tech 4 - 2nd shift - Background cleared | AQ2: HR Generalist - 1st Shift | AR2: Recruiter 1st Shift

Sheet Dashboard
A1: Department: | B1: Interested | C1: Cleared
A2: Production Specialist 1 - Mechanical Assembly - 1st shift | B2: =COUNTIFS(PrepList!E:E,Dashboard!A2,PrepList'!M:M,"No") | C2: =COUNTIFS(PrepList!#REF!,Dashboard!A2,PrepList!#REF!,"Yes") -> #REF!
A3: Production Specialist 1 - Mechanical Assembly - 2nd shift | B3: =COUNTIFS(PrepList!H:H,Dashboard!A3,PrepList!#REF!,"No") -> #REF! | C3: =COUNTIFS(PrepList!#REF!,Dashboard!A3,PrepList!#REF!,"Yes") -> #REF!
A4: Production Specialist 1 - Materials - 1st shift | B4: =COUNTIFS(PrepList!H:H,Dashboard!A4,PrepList!#REF!,"No") -> #REF! | C4: =COUNTIFS(PrepList!#REF!,Dashboard!A4,PrepList!#REF!,"Yes") -> #REF!
A5: Production Specialist 1 - Materials - 2nd shift | B5: =COUNTIFS(PrepList!H:H,Dashboard!A5,PrepList!#REF!,"No") -> #REF! | C5: =COUNTIFS(PrepList!#REF!,Dashboard!A5,PrepList!#REF!,"Yes") -> #REF!
A6: Production Specialist 1 - Materials - 3rd shift | B6: =COUNTIFS(PrepList!H:H,Dashboard!A6,PrepList!#REF!,"No") -> #REF! | C6: =COUNTIFS(PrepList!#REF!,Dashboard!A6,PrepList!#REF!,"Yes") -> #REF!
A7: Production Specialist 1 - Mechanical Assembly - 3rd shift | B7: =COUNTIFS(PrepList!H:H,Dashboard!A7,PrepList!#REF!,"No") -> #REF! | C7: =COUNTIFS(PrepList!#REF!,Dashboard!A7,PrepList!#REF!,"Yes") -> #REF!
A8: Production Specialist 1 - Rack Level Assembly - 3rd shift | B8: =COUNTIFS(PrepList!H:H,Dashboard!A8,PrepList!#REF!,"No") -> #REF! | C8: =COUNTIFS(PrepList!#REF!,Dashboard!A8,PrepList!#REF!,"Yes") -> #REF!
A9: Production Specialist 1 - Packout - 3rd shift | B9: =COUNTIFS(PrepList!H:H,Dashboard!A9,PrepList!#REF!,"No") -> #REF! | C9: =COUNTIFS(PrepList!#REF!,Dashboard!A9,PrepList!#REF!,"Yes") -> #REF!
A10: Production Specialist 1 - Rack Level Assembly - 3rd shift | B10: =COUNTIFS(PrepList!H:H,Dashboard!A10,PrepList!#REF!,"No") -> #REF! | C10: =COUNTIFS(PrepList!#REF!,Dashboard!A10,PrepList!#REF!,"Yes") -> #REF!
A11: Production Specialist 1 - Rack Level Assembly -1st shift | B11: =COUNTIFS(PrepList!H:H,Dashboard!A11,PrepList!#REF!,"No") -> #REF! | C11: =COUNTIFS(PrepList!#REF!,Dashboard!A11,PrepList!#REF!,"Yes") -> #REF!
A12: Production Specialist 1 - Rack Level Assembly -2nd shift | B12: =COUNTIFS(PrepList!H:H,Dashboard!A12,PrepList!#REF!,"No") -> #REF! | C12: =COUNTIFS(PrepList!#REF!,Dashboard!A12,PrepList!#REF!,"Yes") -> #REF!
A13: IT Support Technician - 1st Shift | B13: =COUNTIFS(PrepList!H:H,Dashboard!A13,PrepList!#REF!,"No") -> #REF! | C13: =COUNTIFS(PrepList!#REF!,Dashboard!A13,PrepList!#REF!,"Yes") -> #REF!
A14: Delivery Business Systems Analyst - 1st Shift | B14: =COUNTIFS(PrepList!H:H,Dashboard!A14,PrepList!#REF!,"No") -> #REF! | C14: =COUNTIFS(PrepList!#REF!,Dashboard!A14,PrepList!#REF!,"Yes") -> #REF!
... A20: Recruiter 1st Shift | B20: =COUNTIFS(PrepList!H:H,Dashboard!A20,PrepList!#REF!,"No") -> #REF! | C20: =COUNTIFS(PrepList!#REF!,Dashboard!A20,PrepList!#REF!,"Yes") -> #REF!
A21: Total | B21: =SUM(B2:B20) -> #REF! | C21: =SUM(C2:C20) -> #REF!

Sheet Office Goals
A1: 2.24 - 2.28 | D1: as of 2.26
A2: Office | B2: Goal | C2: Actual
A3: NSL | B3: 10 | C3: 16
A4: WVC | B4: 20 | C4: 45
A5: WJ | B5: 20 | C5: 23
A6: Total | B6: =SUM(B3:B5) -> 50 | C6: =SUM(C3:C5) -> 84
A8: 3.03 - 3.07
A9: Office | B9: Goal | C9: Actual
A10: NSL | B10: 10
A11: WVC | B11: 20
A12: WJ | B12: 20
A13: Total | B13: =SUM(B10:B12) -> 50 | C13: =SUM(C10:C12) -> 0

Sheet MGR&Shifts
A1: Work Location | B1: Shift_Time | C1: Manager
A2: SLC-WH-RECIEVING & SHIPPING | B2: 0700a-0400p M-F some Saturday's | C2: Adam Coghlan (1034757)
A3: SLC-RACK ASSY- SUPERVISOR ASSY | B3: 8:30am to 5:00pm | C3: Alex Martinez
A4: SLC-RACK ASSY-IQA INSPECTION | B4: Salt Lake City- C 1st Shift 0630a-0300p Mon-Fri | C4: Alondra Landin (1152847)
A5: SLC-MECH ASSY- SUPERVISOR ASSY | B5: Salt Lake City - 12 - 0300p-1130p M-F | C5: Avigail Zamora
A6: SLC-MECH ASSY-ASSEMBLY | B6: 0800a-0500p M 1000a-0700p T-F | C6: Barbara Garcia (1137177)
A7: SLC-MECH ASSY-REWORK | B7: Salt Lake City- F 2nd Shift 0200p-1230a Mon-Th (15% Diff) | C7: Britton Hanna (1154396)
A8: SLC-RACK ASSY- SHIPPING | B8: Salt Lake City- Wknd Shift 0230p-0230a F-Sun (15% Diff) | C8: Castalia Marino
A9: SLC-WH-LEAD | B9: 0230p-1100p M-F some Saturday's | C9: Cristian Vega (1135987)
A10: SLC-MECH ASSY- WATER SPIDER | B10: Salt Lake City- D 1st Shift 0700a-0330p Mon-Fri | C10: Dallas Driggers (1156397)
A11: SLC-MECH ASSY-KITTING | B11: 0400p-0100a M-F some Saturday's | C11: Danilo Vieira De Souza Alves (60729)
A12: SLC-MECH ASSY-DETRASH | B12: 0330p-1200a M-F some Saturday's | C12: David Hiestand (1138434)
... A41: SLC-RACK ASSY-WATERSPIDER | B41: Salt Lake City - L - 10:00 PM - 6:30 AM (Sun-Thurs) | C41: Zee Fruechting (1167899)

Sheet Completed Orientation
A1: Employee Name | B1: Phone # | C1: Preferred Schedule | D1: Shift Requirement | E1: Position
A2: Ivonne Galban | B2: 801-500-3133 | C2: A/C (Day) | E2: =ROW() - ROW(Table52[[#Headers],[Position]]) -> 1
A3: Yulimar M Nazarin | B3: 313-523-3391 | C3: A/C (Day) | E3: =ROW() - ROW(Table52[[#Headers],[Position]]) -> 2
A4: Sindy Viviana Guillen Taborda | B4: 385-343-2625 | C4: A/C (Day) | E4: =ROW() - ROW(Table52[[#Headers],[Position]]) -> 3
A5: Abel Elias Huaman Huachopoma | B5: 385-421-1590 | C5: A/C (Day) | E5: =ROW() - ROW(Table52[[#Headers],[Position]]) -> 4
A6: David C Huaman Julian | B6: 801-946-9851 | C6: A/C (Day) | E6: =ROW() - ROW(Table52[[#Headers],[Position]]) -> 5
A7: Stivaliz Chirino | B7: 385-267-0910 | C7: A/C (Day) | E7: =ROW() - ROW(Table52[[#Headers],[Position]]) -> 6
A8: Cruzmar Danielo Azuaje Briceno | B8: 801-895-1504 | C8: A/C (Day) | E8: =ROW() - ROW(Table52[[#Headers],[Position]]) -> 7
A9: Gloria N Navarro | B9: 385-302-2818 | C9: A/C (Day) | E9: =ROW() - ROW(Table52[[#Headers],[Position]]) -> 8
A10: Maria Duram | B10: 689-204-4662 | C10: A/C (Day) | E10: =ROW() - ROW(Table52[[#Headers],[Position]]) -> 9
A11: Ginelda Palmar | B11: 385-343-9591 | C11: A/C (Day) | E11: =ROW() - ROW(Table52[[#Headers],[Position]]) -> 10
A12: Juan Acero Diaz | B12: 813-521-3185 | C12: A/C (Day) | E12: =ROW() - ROW(Table52[[#Headers],[Position]]) -> 11
A13: Maria Mercedes Ibarra | B13: 801-584-9577 | C13: A/C (Day) | E13: =ROW() - ROW(Table52[[#Headers],[Position]]) -> 12
... A15: Juan Nova | B15: 385-576-3439 | C15: A/C (Day) | E15: =ROW() - ROW(Table52[[#Headers],[Position]]) -> 14
A16: Jesse Gonzalez | C16: A/C (Day) | E16: =ROW() - ROW(Table52[[#Headers],[Position]]) -> 15
A17: Christian Crush | C17: A/C (Day) | E17: =ROW() - ROW(Table52[[#Headers],[Position]]) -> 16
A18: Gabriela Molina | B18: 385-267-9020 | C18: A/C (Day) | D18: Luzmila Ballesteros | E18: =ROW() - ROW(Table52[[#Headers],[Position]]) -> 17
A19: Jesse Gonzalez | B19: 801-809-7918 | C19: A/C (Day) | E19: =ROW() - ROW(Table52[[#Headers],[Position]]) -> 18
A20: Christian Crush | B20: 409-730-6234 | C20: A/C (Day) | E20: =ROW() - ROW(Table52[[#Headers],[Position]]) -> 19
A21: Gisell Carmona | B21: 385-441-2390 | C21: A/C (Day) | D21: Catherine Rodriguez | E21: =ROW() - ROW(Table52[[#Headers],[Position]]) -> 20
A22: Catherine Rodriguez | B22: (801) 330-2018 | C22: A/C (Day) | D22: Gisell Carmona | E22: =ROW() - ROW(Table52[[#Headers],[Position]]) -> 21
A23: Mariely Gonzalez | B23: 801-674-5096 | C23: A/C (Day) | E23: =ROW() - ROW(Table52[[#Headers],[Position]]) -> 22
A24: Craig Allen Foster | B24: 406-381-3640 | C24: A/C (Day) | E24: =ROW() - ROW(Table52[[#Headers],[Position]]) -> 23
A25: Lizbeth Zavala | B25: 801-708-9014 | C25: A/C (Day) | E25: =ROW() - ROW(Table52[[#Headers],[Position]]) -> 24
A26: Syreefa Yazzie | B26: 385-887-1774 | C26: A/C (Day) | D26: Timothy Alires | E26: =ROW() - ROW(Table52[[#Headers],[Position]]) -> 25
A27: Jerja Chatterton | B27: 435-755-0810 | C27: A/C (Day) | E27: =ROW() - ROW(Table52[[#Headers],[Position]]) -> 26
A28: Jennifer Lee | B28: 385-258-9659 | C28: A/C (Day) | E28: =ROW() - ROW(Table52[[#Headers],[Position]]) -> 27
A29: Sabha Abrena | B29: 385-299-1604 | C29: A/C (Day) | E29: =ROW() - ROW(Table52[[#Headers],[Position]]) -> 28
A30: Taylor W Lawer | B30: 707-378-3290 | C30: A/C (Day) | E30: =ROW() - ROW(Table52[[#Headers],[Position]]) -> 29
A31: Sophie Wesseh | B31: 385-520-3599 | C31: A/C (Day) | E31: =ROW() - ROW(Table52[[#Headers],[Position]]) -> 30
A32: Norris John | B32: 949-393-8177 | C32: A/C (Day) | D32: 385-401-3966 | E32: =ROW() - ROW(Table52[[#Headers],[Position]]) -> 31
A33: Lotomaci BJ Uluset? | B33: 385-566-7922 | C33: A/C (Day) | D33: Robert Tiana | E33: =ROW() - ROW(Table52[[#Headers],[Position]]) -> 32
A34: Rober Tiana | B34: 385-566-7922 | C34: A/C (Day) | D34: BJ | E34: =ROW() - ROW(Table52[[#Headers],[Position]]) -> 33
A35: Arely Cardenas | B35: 801-824-7474 | C35: A/C (Day) | D35: C | E35: =ROW() - ROW(Table52[[#Headers],[Position]]) -> 34
A36: Ulises Anzaldo | B36: 385-770-9129 | C36: A/C (Day) | E36: =ROW() - ROW(Table52[[#Headers],[Position]]) -> 35
A37: Hawa Enow | B37: 801-618-5641 | C37: A/C (Day) | E37: =ROW() - ROW(Table52[[#Headers],[Position]]) -> 36
A38: Jhony Mauricio | B38: 385-900-6827 | C38: A/C (Day) | E38: =ROW() - ROW(Table52[[#Headers],[Position]]) -> 37
A39: Mary Cruz Parra | B39: 385-461-2852 | C39: A/C (Day) | E39: =ROW() - ROW(Table52[[#Headers],[Position]]) -> 38
A40: Yendri Merentes | B40: 801-430-4477 | C40: A/C (Day) | E40: =ROW() - ROW(Table52[[#Headers],[Position]]) -> 39
A41: Angel Enrique Chacin Romero | B41: 801-414-0925 | C41: A/C (Day) | E41: =ROW() - ROW(Table52[[#Headers],[Position]]) -> 40
A42: Melfis Jair Herrera | B42: 385-354-0347 | C42: A/C (Day) | E42: =ROW() - ROW(Table52[[#Headers],[Position]]) -> 41
A43: Vianca Sifonto? | B43: 801-680-4038 | C43: A/C (Day) | E43: =ROW() - ROW(Table52[[#Headers],[Position]]) -> 42
A44: Weena Chavez | B44: 561-719-8206 | C44: A/C (Day) | E44: =ROW() - ROW(Table52[[#Headers],[Position]]) -> 43
A45: Noah Parker | B45: 801-779-1369 | C45: A/C (Day) | E45: =ROW() - ROW(Table52[[#Headers],[Position]]) -> 44
A46: Alison Polite | B46: 385-777-7476 | C46: A/C (Day) | E46: =ROW() - ROW(Table52[[#Headers],[Position]]) -> 45
A47: Claudia Jaime | B47: 208-771-6268 | C47: A/C (Day) | E47: =ROW() - ROW(Table52[[#Headers],[Position]]) -> 46
A48: Deborah Sampson | B48: 385-318-5754 | C48: A/C (Day) | E48: =ROW() - ROW(Table52[[#Headers],[Position]]) -> 47
A49: Anpi Pina Trujillo | C49: A/C (Day) | E49: =ROW() - ROW(Table52[[#Headers],[Position]]) -> 48
A50: Marisol Zambrano Flores | B50: 801-706-9368 | C50: A/C (Day) | E50: =ROW() - ROW(Table52[[#Headers],[Position]]) -> 49
A51: Paul Gonzalez | B51: 385-370-7295 | C51: A/C (Day) | E51: =ROW() - ROW(Table52[[#Headers],[Position]]) -> 50
A52: Yaseisi Munoz | B52: 385-556-9399 | C52: A/C (Day) | E52: =ROW() - ROW(Table52[[#Headers],[Position]]) -> 51
A53: Josmary Perdomo | B53: 469-924-9288 | C53: A/C (Day) | E53: =ROW() - ROW(Table52[[#Headers],[Position]]) -> 52
A54: Worbelto Bracho | B54: 623-306-0592 | C54: A/C (Day) | E54: =ROW() - ROW(Table52[[#Headers],[Position]]) -> 53
A55: Yraldis Bracho Castillo | B55: 602-772-1754 | C55: A/C (Day) | E55: =ROW() - ROW(Table52[[#Headers],[Position]]) -> 54
A56: Linethe Fernandez | B56: 865-321-3242 | C56: A/C (Day) | E56: =ROW() - ROW(Table52[[#Headers],[Position]]) -> 55
A57: Fully Mosquera | B57: 385-436-7750 | C57: A/C (Day) | E57: =ROW() - ROW(Table52[[#Headers],[Position]]) -> 56
A58: Talia Catamo | B58: 801-548-0427 | C58: A/C (Day) | E58: =ROW() - ROW(Table52[[#Headers],[Position]]) -> 57
A59: Vivian Olivieri | B59: 609-854-1397 | C59: A/C (Day) | E59: =ROW() - ROW(Table52[[#Headers],[Position]]) -> 58
A60: Krysbel Azvaje | B60: 407-989-8442 | C60: A/C (Day) | E60: =ROW() - ROW(Table52[[#Headers],[Position]]) -> 59
A61: Suscina Curilo | B61: 801-403-8650 | C61: A/C (Day) | E61: =ROW() - ROW(Table52[[#Headers],[Position]]) -> 60
... A64: Djuma Mito | B64: 801-674-5410 | C64: A/C (Day) | E64: =ROW() - ROW(Table52[[#Headers],[Position]]) -> 63
A65: Andrew Heineman | B65: 8019009858 | C65: A/C (Day) | E65: 71
A66: Asukulu Mwarabu | B66: 3254361994 | C66: A/C (Day) | E66: 72
A67: Djuma Mto | B67: 8016745410 | C67: A/C (Day) | E67: 73
A68: Mikyla Dance | B68: 801-648-2594 | C68: Either
A69: Merita Phillip | B69: 385-430-7464 | C69: B/D (Night) | D69: Hemritha | E69: 1
A70: Victoria Filo | B70: 801-502-7667 | C70: B/D (Night) | E70: 2
A71: Anita Tootoo | B71: 385-484-2150 | C71: B/D (Night) | E71: 3
A72: Damian Hernandez | B72: 801-502-3689 | C72: B/D (Night) | E72: 4
A73: Eugene Aveyrua | B73: 801-674-4701 | C73: B/D (Night) | E73: 5
A74: Giam Carlo Flores Pahma | B74: 435-565-9730 | C74: B/D (Night) | E74: 6
A75: David Charles | B75: 504-942-6624 | C75: B/D (Night) | E75: 7
A76: Hiana Chibangu | B76: 801-608-0048 | C76: B/D (Night) | D76: Mutombo Kanyeba | E76: 8
A77: Thelma Amaama | B77: 385-881-7971 | C77: B/D (Night) | E77: 9
A78: Jasmin Guzman | B78: 801-635-4778 | C78: B/D (Night) | E78: 10
A79: Farrell Palmer | B79: 505-613-1287 | C79: B/D (Night) | E79: 11
A80: Janet Domnick | B80: 303-525-3631 | C80: B/D (Night) | E80: 12
A81: Patrick Tuyishime | B81: 385-423-8461 | C81: B/D (Night) | E81: 13
A82: Mutombo Kanyeba | B82: 801-326-9701 | C82: B/D (Night) | D82: Chibanyu Ahina | E82: 14
A83: Nicholas Hight | B83: 801-414-0952 | C83: B/D (Night) | E83: 15
A84: Richard Vakapuna | B84: 801-425-5968 | C84: B/D (Night) | E84: 16
A85: Jose Ocanto Lunna | B85: 385-219-6644 | C85: B/D (Night) | D85: D | E85: 17
A86: Melemafi Laylani Tupola | B86: 3857872212 | C86: B/D (Night) | E86: 18
A87: Jancarlo Guerrero | B87: 3854479343 | C87: B/D (Night) | E87: 19
A88: Angel Peni | B88: 2532409813 | C88: B/D (Night) | E88: 20
A89: Angie Peni | B89: 8013008032 | C89: B/D (Night) | E89: 21
A90: Amelia Mokofisi | B90: 650-942-1117 | C90: B/D (Night) | E90: 22
A91: Darrius Turner | B91: 930-444-0567 | C91: B/D (Night) | E91: 23
A92: Diego Ramirez | B92: 385-239-9399 | C92: B/D (Night) | E92: 24
A93: Randa Garza | B93: 801-599-9069 | C93: B/D (Night) | E93: 25
A94: Esha Ali | B94: 801-413-6776 | C94: B/D (Night) | E94: 26
A95: Yandira | B95: 801-574-9577 | C95: B/D (Night) | E95: 27
A96: Kelly C Florence | B96: 385-487-2732 | C96: B/D (Night) | E96: 28
A97: CatalinaPaolaMaturana Gomez | B97: 801-680-8178 | C97: B/D (Night) | E97: 29
A98: Jacqueline J Salcedo | B98: 385-775-4941 | C98: B/D (Night) | E98: 30
A99: Diego Castellano | B99: 574-326-9920 | C99: B/D (Night) | E99: 31
A100: Linchinte Linchinte | B100: 801-889-7096 | C100: B/D (Night) | E100: 32
A101: Irene Palacius Santos | B101: 385-328-1559 | C101: B/D (Night) | E101: 33
A102: Phillip Schwenke | B102: 3852991096 | C102: B/D (Night) | E102: 34
A103: Daniel O. Nuttall | B103: 385-549-0977 | C103: B/D (Night) | E103: 35
...

Sheet Ready to Start
A1: Mini Completed Date | B1: Language | C1: Employee Name | D1: Bold ID | E1: Phone | F1: Shift | G1: Position | H1: A.M. | I1: BG | J1: DT | K1: EV | L1: FLEX Doc Sent | M1: Ready to Start | N1: Notes
B2: =IF(PrepList!#REF!="","",PrepList!#REF!) -> #REF! | C2: =_xlfn.XLOOKUP(D2,PrepList!F:F,PrepList!E:E) -> #REF! | D2: =IF(PrepList!#REF!="","",PrepList!#REF!) -> #REF! | E2: =IF(PrepList!#REF!="","",PrepList!#REF!) -> #REF! | F2: =IF(PrepList!#REF!="","",PrepList!#REF!) -> #REF! | G2: =IF(PrepList!#REF!="","",PrepList!#REF!) -> #REF! | H2: =IF(PrepList!#REF!="","",PrepList!#REF!) -> #REF! | I2: =IF(PrepList!#REF!="","",PrepList!#REF!) -> #REF! | J2: =IF(PrepList!#REF!="","",PrepList!#REF!) -> #REF! | L2: =IF(PrepList!#REF!="","",PrepList!#REF!) -> #REF! | N2: =IF(PrepList!#REF!="","",PrepList!#REF!) -> #REF!
B3: =IF(PrepList!#REF!="","",PrepList!#REF!) -> #REF! | C3: =_xlfn.XLOOKUP(D3,PrepList!F:F,PrepList!E:E) -> #REF! | D3: =IF(PrepList!#REF!="","",PrepList!#REF!) -> #REF! | E3: =IF(PrepList!#REF!="","",PrepList!#REF!) -> #REF! | F3: =IF(PrepList!#REF!="","",PrepList!#REF!) -> #REF! | G3: =IF(PrepList!#REF!="","",PrepList!#REF!) -> #REF! | H3: =IF(PrepList!#REF!="","",PrepList!#REF!) -> #REF! | I3: =IF(PrepList!#REF!="","",PrepList!#REF!) -> #REF! | J3: =IF(PrepList!#REF!="","",PrepList!#REF!) -> #REF! | L3: =IF(PrepList!#REF!="","",PrepList!#REF!) -> #REF! | N3: =IF(PrepList!#REF!="","",PrepList!#REF!) -> #REF!
B4: =IF(PrepList!#REF!="","",PrepList!#REF!) -> #REF! | C4: =_xlfn.XLOOKUP(D4,PrepList!F:F,PrepList!E:E) -> #REF! | D4: =IF(PrepList!#REF!="","",PrepList!#REF!) -> #REF! | E4: =IF(PrepList!#REF!="","",PrepList!#REF!) -> #REF! | F4: =IF(PrepList!#REF!="","",PrepList!#REF!) -> #REF! | G4: =IF(PrepList!#REF!="","",PrepList!#REF!) -> #REF! | H4: =IF(PrepList!#REF!="","",PrepList!#REF!) -> #REF! | I4: =IF(PrepList!#REF!="","",PrepList!#REF!) -> #REF! | J4: =IF(PrepList!#REF!="","",PrepList!#REF!) -> #REF! | L4: =IF(PrepList!#REF!="","",PrepList!#REF!) -> #REF! | N4: =IF(PrepList!#REF!="","",PrepList!#REF!) -> #REF!
B5: =IF(PrepList!#REF!="","",PrepList!#REF!) -> #REF! | C5: =_xlfn.XLOOKUP(D5,PrepList!F:F,PrepList!E:E) -> #REF! | D5: =IF(PrepList!#REF!="","",PrepList!#REF!) -> #REF! | E5: =IF(PrepList!#REF!="","",PrepList!#REF!) -> #REF! | F5: =IF(PrepList!#REF!="","",PrepList!#REF!) -> #REF! | G5: =IF(PrepList!#REF!="","",PrepList!#REF!) -> #REF! | H5: =IF(PrepList!#REF!="","",PrepList!#REF!) -> #REF! | I5: =IF(PrepList!#REF!="","",PrepList!#REF!) -> #REF! | J5: =IF(PrepList!#REF!="","",PrepList!#REF!) -> #REF! | L5: =IF(PrepList!#REF!="","",PrepList!#REF!) -> #REF! | N5: =IF(PrepList!#REF!="","",PrepList!#REF!) -> #REF!
B6: =IF(PrepList!#REF!="","",PrepList!#REF!) -> #REF! | C6: =_xlfn.XLOOKUP(D6,PrepList!F:F,PrepList!E:E) -> #REF! | D6: =IF(PrepList!#REF!="","",PrepList!#REF!) -> #REF! | E6: =IF(PrepList!#REF!="","",PrepList!#REF!) -> #REF! | F6: =IF(PrepList!#REF!="","",PrepList!#REF!) -> #REF! | G6: =IF(PrepList!#REF!="","",PrepList!#REF!) -> #REF! | H6: =IF(PrepList!#REF!="","",PrepList!#REF!) -> #REF! | I6: =IF(PrepList!#REF!="","",PrepList!#REF!) -> #REF! | J6: =IF(PrepList!#REF!="","",PrepList!#REF!) -> #REF! | L6: =IF(PrepList!#REF!="","",PrepList!#REF!) -> #REF! | N6: =IF(PrepList!#REF!="","",PrepList!#REF!) -> #REF!
B7: =IF(PrepList!#REF!="","",PrepList!#REF!) -> #REF! | C7: =_xlfn.XLOOKUP(D7,PrepList!F:F,PrepList!E:E) -> #REF! | D7: =IF(PrepList!#REF!="","",PrepList!#REF!) -> #REF! | E7: =IF(PrepList!#REF!="","",PrepList!#REF!) -> #REF! | F7: =IF(PrepList!#REF!="","",PrepList!#REF!) -> #REF! | G7: =IF(PrepList!#REF!="","",PrepList!#REF!) -> #REF! | H7: =IF(PrepList!#REF!="","",PrepList!#REF!) -> #REF! | I7: =IF(PrepList!#REF!="","",PrepList!#REF!) -> #REF! | J7: =IF(PrepList!#REF!="","",PrepList!#REF!) -> #REF! | L7: =IF(PrepList!#REF!="","",PrepList!#REF!) -> #REF! | N7: =IF(PrepList!#REF!="","",PrepList!#REF!) -> #REF!
B8: =IF(PrepList!#REF!="","",PrepList!#REF!) -> #REF! | C8: =_xlfn.XLOOKUP(D8,PrepList!F:F,PrepList!E:E) -> #REF! | D8: =IF(PrepList!#REF!="","",PrepList!#REF!) -> #REF! | E8: =IF(PrepList!#REF!="","",PrepList!#REF!) -> #REF! | F8: =IF(PrepList!#REF!="","",PrepList!#REF!) -> #REF! | G8: =IF(PrepList!#REF!="","",PrepList!#REF!) -> #REF! | H8: =IF(PrepList!#REF!="","",PrepList!#REF!) -> #REF! | I8: =IF(PrepList!#REF!="","",PrepList!#REF!) -> #REF! | J8: =IF(PrepList!#REF!="","",PrepList!#REF!) -> #REF! | L8: =IF(PrepList!#REF!="","",PrepList!#REF!) -> #REF! | N8: =IF(PrepList!#REF!="","",PrepList!#REF!) -> #REF!
B9: =IF(PrepList!#REF!="","",PrepList!#REF!) -> #REF! | C9: =_xlfn.XLOOKUP(D9,PrepList!F:F,PrepList!E:E) -> #REF! | D9: =IF(PrepList!#REF!="","",PrepList!#REF!) -> #REF! | E9: =IF(PrepList!#REF!="","",PrepList!#REF!) -> #REF! | F9: =IF(PrepList!#REF!="","",PrepList!#REF!) -> #REF! | G9: =IF(PrepList!#REF!="","",PrepList!#REF!) -> #REF! | H9: =IF(PrepList!#REF!="","",PrepList!#REF!) -> #REF! | I9: =IF(PrepList!#REF!="","",PrepList!#REF!) -> #REF! | J9: =IF(PrepList!#REF!="","",PrepList!#REF!) -> #REF! | L9: =IF(PrepList!#REF!="","",PrepList!#REF!) -> #REF! | N9: =IF(PrepList!#REF!="","",PrepList!#REF!) -> #REF!
B10: =IF(PrepList!#REF!="","",PrepList!#REF!) -> #REF! | C10: =_xlfn.XLOOKUP(D10,PrepList!F:F,PrepList!E:E) -> #REF! | D10: =IF(PrepList!#REF!="","",PrepList!#REF!) -> #REF! | E10: =IF(PrepList!#REF!="","",PrepList!#REF!) -> #REF! | F10: =IF(PrepList!#REF!="","",PrepList!#REF!) -> #REF! | G10: =IF(PrepList!#REF!="","",PrepList!#REF!) -> #REF! | H10: =IF(PrepList!#REF!="","",PrepList!#REF!) -> #REF! | I10: =IF(PrepList!#REF!="","",PrepList!#REF!) -> #REF! | J10: =IF(PrepList!#REF!="","",PrepList!#REF!) -> #REF! | L10: =IF(PrepList!#REF!="","",PrepList!#REF!) -> #REF! | N10: =IF(PrepList!#REF!="","",PrepList!#REF!) -> #REF!
B11: =IF(PrepList!#REF!="","",PrepList!#REF!) -> #REF! | C11: =_xlfn.XLOOKUP(D11,PrepList!F:F,PrepList!E:E) -> #REF! | D11: =IF(PrepList!#REF!="","",PrepList!#REF!) -> #REF! | E11: =IF(PrepList!#REF!="","",PrepList!#REF!) -> #REF! | F11: =IF(PrepList!#REF!="","",PrepList!#REF!) -> #REF! | G11: =IF(PrepList!#REF!="","",PrepList!#REF!) -> #REF! | H11: =IF(PrepList!#REF!="","",PrepList!#REF!) -> #REF! | I11: =IF(PrepList!#REF!="","",PrepList!#REF!) -> #REF! | J11: =IF(PrepList!#REF!="","",PrepList!#REF!) -> #REF! | L11: =IF(PrepList!#REF!="","",PrepList!#REF!) -> #REF! | N11: =IF(PrepList!#REF!="","",PrepList!#REF!) -> #REF!
B12: =IF(PrepList!#REF!="","",PrepList!#REF!) -> #REF! | C12: =_xlfn.XLOOKUP(D12,PrepList!F:F,PrepList!E:E) -> #REF! | D12: =IF(PrepList!#REF!="","",PrepList!#REF!) -> #REF! | E12: =IF(PrepList!#REF!="","",PrepList!#REF!) -> #REF! | F12: =IF(PrepList!#REF!="","",PrepList!#REF!) -> #REF! | G12: =IF(PrepList!#REF!="","",PrepList!#REF!) -> #REF! | H12: =IF(PrepList!#REF!="","",PrepList!#REF!) -> #REF! | I12: =IF(PrepList!#REF!="","",PrepList!#REF!) -> #REF! | J12: =IF(PrepList!#REF!="","",PrepList!#REF!) -> #REF! | L12: =IF(PrepList!#REF!="","",PrepList!#REF!) -> #REF! | N12: =IF(PrepList!#REF!="","",PrepList!#REF!) -> #REF!
B13: =IF(PrepList!#REF!="","",PrepList!#REF!) -> #REF! | C13: =_xlfn.XLOOKUP(D13,PrepList!F:F,PrepList!E:E) -> #REF! | D13: =IF(PrepList!#REF!="","",PrepList!#REF!) -> #REF! | E13: =IF(PrepList!#REF!="","",PrepList!#REF!) -> #REF! | F13: =IF(PrepList!#REF!="","",PrepList!#REF!) -> #REF! | G13: =IF(PrepList!#REF!="","",PrepList!#REF!) -> #REF! | H13: =IF(PrepList!#REF!="","",PrepList!#REF!) -> #REF! | I13: =IF(PrepList!#REF!="","",PrepList!#REF!) -> #REF! | J13: =IF(PrepList!#REF!="","",PrepList!#REF!) -> #REF! | L13: =IF(PrepList!#REF!="","",PrepList!#REF!) -> #REF! | N13: =IF(PrepList!#REF!="","",PrepList!#REF!) -> #REF!
... B170: =IF(PrepList!#REF!="","",PrepList!#REF!) -> #REF! | C170: =_xlfn.XLOOKUP(D170,PrepList!F:F,PrepList!E:E) -> #REF! | D170: =IF(PrepList!#REF!="","",PrepList!#REF!) -> #REF! | E170: =IF(PrepList!#REF!="","",PrepList!#REF!) -> #REF! | F170: =IF(PrepList!#REF!="","",PrepList!#REF!) -> #REF! | G170: =IF(PrepList!#REF!="","",PrepList!#REF!) -> #REF! | H170: =IF(PrepList!#REF!="","",PrepList!#REF!) -> #REF! | I170: =IF(PrepList!#REF!="","",PrepList!#REF!) -> #REF! | J170: =IF(PrepList!#REF!="","",PrepList!#REF!) -> #REF! | L170: =IF(PrepList!#REF!="","",PrepList!#REF!) -> #REF! | N170: =IF(PrepList!#REF!="","",PrepList!#REF!) -> #REF!
B171: =IF(PrepList!D2="","",PrepList!D2) -> Spanish | C171: =_xlfn.XLOOKUP(D171,PrepList!F:F,PrepList!E:E) -> Doraxci Gonzalez | D171: =IF(PrepList!F2="","",PrepList!F2) -> 177671254 | E171: =IF(PrepList!G2="","",PrepList!G2) -> 3856289600 | F171: =IF(PrepList!H2="","",PrepList!H2) -> Day Shift | G171: =IF(PrepList!I2="","",PrepList!I2) -> Mechanical Assembly | H171: =IF(PrepList!K2="","",PrepList!K2) -> FZ | I171: =IF(PrepList!L2="","",PrepList!L2) -> Pending | J171: =IF(PrepList!M2="","",PrepList!M2) | L171: =IF(PrepList!N2="","",PrepList!N2) -> Passed | N171: =IF(PrepList!P2="","",PrepList!P2) -> Confirmed on 8/26 she is still interested
B172: =IF(PrepList!D3="","",PrepList!D3) -> Spanish | C172: =_xlfn.XLOOKUP(D172,PrepList!F:F,PrepList!E:E) -> Maralis Mendoza | D172: =IF(PrepList!F3="","",PrepList!F3) -> 198173510 | E172: =IF(PrepList!G3="","",PrepList!G3) -> 3852164295 | F172: =IF(PrepList!H3="","",PrepList!H3) -> Day Shift | G172: =IF(PrepList!I3="","",PrepList!I3) -> Mechanical Assembly | H172: =IF(PrepList!K3="","",PrepList!K3) -> BL | I172: =IF(PrepList!L3="","",PrepList!L3) -> Passed | J172: =IF(PrepList!M3="","",PrepList!M3) -> Passed | L172: =IF(PrepList!N3="","",PrepList!N3) -> Passed | N172: =IF(PrepList!P3="","",PrepList!P3) -> Confirmed on 8/26 she is still interested
B173: =IF(PrepList!#REF!="","",PrepList!#REF!) -> #REF! | C173: =_xlfn.XLOOKUP(D173,PrepList!F:F,PrepList!E:E) -> #REF! | D173: =IF(PrepList!#REF!="","",PrepList!#REF!) -> #REF! | E173: =IF(PrepList!#REF!="","",PrepList!#REF!) -> #REF! | F173: =IF(PrepList!#REF!="","",PrepList!#REF!) -> #REF! | G173: =IF(PrepList!#REF!="","",PrepList!#REF!) -> #REF! | H173: =IF(PrepList!#REF!="","",PrepList!#REF!) -> #REF! | I173: =IF(PrepList!#REF!="","",PrepList!#REF!) -> #REF! | J173: =IF(PrepList!#REF!="","",PrepList!#REF!) -> #REF! | L173: =IF(PrepList!#REF!="","",PrepList!#REF!) -> #REF! | N173: =IF(PrepList!#REF!="","",PrepList!#REF!) -> #REF!
B174: =IF(PrepList!D4="","",PrepList!D4) -> Spanish | C174: =_xlfn.XLOOKUP(D174,PrepList!F:F,PrepList!E:E) -> Edna Dominguez | D174: =IF(PrepList!F4="","",PrepList!F4) -> 148926496 | E174: =IF(PrepList!G4="","",PrepList!G4) -> 8019185846 | F174: =IF(PrepList!H4="","",PrepList!H4) -> Night Shift | G174: =IF(PrepList!I4="","",PrepList!I4) -> Mechanical Assembly | H174: =IF(PrepList!K4="","",PrepList!K4) -> CE | I174: =IF(PrepList!L4="","",PrepList!L4) -> Passed | J174: =IF(PrepList!M4="","",PrepList!M4) -> Passed | L174: =IF(PrepList!N4="","",PrepList!N4) -> Passed | N174: =IF(PrepList!P4="","",PrepList!P4) -> She stated she wont be in Utah for a few months?
B175: =IF(PrepList!D5="","",PrepList!D5) -> Spanish | C175: =_xlfn.XLOOKUP(D175,PrepList!F:F,PrepList!E:E) -> Amayrany Hernandez | D175: =IF(PrepList!F5="","",PrepList!F5) -> 198303055 | E175: =IF(PrepList!G5="","",PrepList!G5) -> 3855410937 | F175: =IF(PrepList!H5="","",PrepList!H5) -> Night Shift | G175: =IF(PrepList!I5="","",PrepList!I5) -> Mechanical Assembly | H175: =IF(PrepList!K5="","",PrepList!K5) -> CE | I175: =IF(PrepList!L5="","",PrepList!L5) -> Passed | J175: =IF(PrepList!M5="","",PrepList!M5) -> Passed | L175: =IF(PrepList!N5="","",PrepList!N5) -> Passed | N175: =IF(PrepList!P5="","",PrepList!P5) -> Confirmed on 8/26 she is still interested
B176: =IF(PrepList!#REF!="","",PrepList!#REF!) -> #REF! | C176: =_xlfn.XLOOKUP(D176,PrepList!F:F,PrepList!E:E) -> #REF! | D176: =IF(PrepList!#REF!="","",PrepList!#REF!) -> #REF! | E176: =IF(PrepList!#REF!="","",PrepList!#REF!) -> #REF! | F176: =IF(PrepList!#REF!="","",PrepList!#REF!) -> #REF! | G176: =IF(PrepList!#REF!="","",PrepList!#REF!) -> #REF! | H176: =IF(PrepList!#REF!="","",PrepList!#REF!) -> #REF! | I176: =IF(PrepList!#REF!="","",PrepList!#REF!) -> #REF! | J176: =IF(PrepList!#REF!="","",PrepList!#REF!) -> #REF! | L176: =IF(PrepList!#REF!="","",PrepList!#REF!) -> #REF! | N176: =IF(PrepList!#REF!="","",PrepList!#REF!) -> #REF!
B177: =IF(PrepList!#REF!="","",PrepList!#REF!) -> #REF! | C177: =_xlfn.XLOOKUP(D177,PrepList!F:F,PrepList!E:E) -> #REF! | D177: =IF(PrepList!#REF!="","",PrepList!#REF!) -> #REF! | E177: =IF(PrepList!#REF!="","",PrepList!#REF!) -> #REF! | F177: =IF(PrepList!#REF!="","",PrepList!#REF!) -> #REF! | G177: =IF(PrepList!#REF!="","",PrepList!#REF!) -> #REF! | H177: =IF(PrepList!#REF!="","",PrepList!#REF!) -> #REF! | I177: =IF(PrepList!#REF!="","",PrepList!#REF!) -> #REF! | J177: =IF(PrepList!#REF!="","",PrepList!#REF!) -> #REF! | L177: =IF(PrepList!#REF!="","",PrepList!#REF!) -> #REF! | N177: =IF(PrepList!#REF!="","",PrepList!#REF!) -> #REF!
B178: =IF(PrepList!#REF!="","",PrepList!#REF!) -> #REF! | C178: =_xlfn.XLOOKUP(D178,PrepList!F:F,PrepList!E:E) -> #REF! | D178: =IF(PrepList!#REF!="","",PrepList!#REF!) -> #REF! | E178: =IF(PrepList!#REF!="","",PrepList!#REF!) -> #REF! | F178: =IF(PrepList!#REF!="","",PrepList!#REF!) -> #REF! | G178: =IF(PrepList!#REF!="","",PrepList!#REF!) -> #REF! | H178: =IF(PrepList!#REF!="","",PrepList!#REF!) -> #REF! | I178: =IF(PrepList!#REF!="","",PrepList!#REF!) -> #REF! | J178: =IF(PrepList!#REF!="","",PrepList!#REF!) -> #REF! | L178: =IF(PrepList!#REF!="","",PrepList!#REF!) -> #REF! | N178: =IF(PrepList!#REF!="","",PrepList!#REF!) -> #REF!
B179: =IF(PrepList!#REF!="","",PrepList!#REF!) -> #REF! | C179: =_xlfn.XLOOKUP(D179,PrepList!F:F,PrepList!E:E) -> #REF! | D179: =IF(PrepList!#REF!="","",PrepList!#REF!) -> #REF! | E179: =IF(PrepList!#REF!="","",PrepList!#REF!) -> #REF! | F179: =IF(PrepList!#REF!="","",PrepList!#REF!) -> #REF! | G179: =IF(PrepList!#REF!="","",PrepList!#REF!) -> #REF! | H179: =IF(PrepList!#REF!="","",PrepList!#REF!) -> #REF! | I179: =IF(PrepList!#REF!="","",PrepList!#REF!) -> #REF! | J179: =IF(PrepList!#REF!="","",PrepList!#REF!) -> #REF! | L179: =IF(PrepList!#REF!="","",PrepList!#REF!) -> #REF! | N179: =IF(PrepList!#REF!="","",PrepList!#REF!) -> #REF!
B180: =IF(PrepList!D6="","",PrepList!D6) -> Spanish | C180: =_xlfn.XLOOKUP(D180,PrepList!F:F,PrepList!E:E) -> Aracely Hernandez | D180: =IF(PrepList!F6="","",PrepList!F6) -> 198318924 | E180: =IF(PrepList!G6="","",PrepList!G6) -> 4357141187 | F180: =IF(PrepList!H6="","",PrepList!H6) -> Night Shift | G180: =IF(PrepList!I6="","",PrepList!I6) -> Mechanical Assembly | H180: =IF(PrepList!K6="","",PrepList!K6) -> CE | I180: =IF(PrepList!L6="","",PrepList!L6) -> Passed | J180: =IF(PrepList!M6="","",PrepList!M6) -> Passed | L180: =IF(PrepList!N6="","",PrepList!N6) -> Passed | N180: =IF(PrepList!P6="","",PrepList!P6)
B181: =IF(PrepList!D7="","",PrepList!D7) -> Spanish | C181: =_xlfn.XLOOKUP(D181,PrepList!F:F,PrepList!E:E) -> Snayder Pongo | D181: =IF(PrepList!F7="","",PrepList!F7) -> 198237668 | E181: =IF(PrepList!G7="","",PrepList!G7) -> 3854883070 | F181: =IF(PrepList!H7="","",PrepList!H7) -> Day Shift | G181: =IF(PrepList!I7="","",PrepList!I7) -> Mechanical Assembly | H181: =IF(PrepList!K7="","",PrepList!K7) -> NM | I181: =IF(PrepList!L7="","",PrepList!L7) -> Passed | J181: =IF(PrepList!M7="","",PrepList!M7) -> Passed | L181: =IF(PrepList!N7="","",PrepList!N7) -> Passed | N181: =IF(PrepList!P7="","",PrepList!P7)
B182: =IF(PrepList!D8="","",PrepList!D8) -> Spanish | C182: =_xlfn.XLOOKUP(D182,PrepList!F:F,PrepList!E:E) -> Yennifer Hernandez | D182: =IF(PrepList!F8="","",PrepList!F8) -> 186325204 | E182: =IF(PrepList!G8="","",PrepList!G8) -> 8015094766 | F182: =IF(PrepList!H8="","",PrepList!H8) -> Day Shift | G182: =IF(PrepList!I8="","",PrepList!I8) -> Mechanical Assembly | H182: =IF(PrepList!K8="","",PrepList!K8) -> BL | I182: =IF(PrepList!L8="","",PrepList!L8) -> Passed | J182: =IF(PrepList!M8="","",PrepList!M8) -> Passed | L182: =IF(PrepList!N8="","",PrepList!N8) -> Passed | N182: =IF(PrepList!P8="","",PrepList!P8)
B183: =IF(PrepList!#REF!="","",PrepList!#REF!) -> #REF! | C183: =_xlfn.XLOOKUP(D183,PrepList!F:F,PrepList!E:E) -> #REF! | D183: =IF(PrepList!#REF!="","",PrepList!#REF!) -> #REF! | E183: =IF(PrepList!#REF!="","",PrepList!#REF!) -> #REF! | F183: =IF(PrepList!#REF!="","",PrepList!#REF!) -> #REF! | G183: =IF(PrepList!#REF!="","",PrepList!#REF!) -> #REF! | H183: =IF(PrepList!#REF!="","",PrepList!#REF!) -> #REF! | I183: =IF(PrepList!#REF!="","",PrepList!#REF!) -> #REF! | J183: =IF(PrepList!#REF!="","",PrepList!#REF!) -> #REF! | L183: =IF(PrepList!#REF!="","",PrepList!#REF!) -> #REF! | N183: =IF(PrepList!#REF!="","",PrepList!#REF!) -> #REF!
B184: =IF(PrepList!#REF!="","",PrepList!#REF!) -> #REF! | C184: =_xlfn.XLOOKUP(D184,PrepList!F:F,PrepList!E:E) -> #REF! | D184: =IF(PrepList!#REF!="","",PrepList!#REF!) -> #REF! | E184: =IF(PrepList!#REF!="","",PrepList!#REF!) -> #REF! | F184: =IF(PrepList!#REF!="","",PrepList!#REF!) -> #REF! | G184: =IF(PrepList!#REF!="","",PrepList!#REF!) -> #REF! | H184: =IF(PrepList!#REF!="","",PrepList!#REF!) -> #REF! | I184: =IF(PrepList!#REF!="","",PrepList!#REF!) -> #REF! | J184: =IF(PrepList!#REF!="","",PrepList!#REF!) -> #REF! | L184: =IF(PrepList!#REF!="","",PrepList!#REF!) -> #REF! | N184: =IF(PrepList!#REF!="","",PrepList!#REF!) -> #REF!
B185: =IF(PrepList!#REF!="","",PrepList!#REF!) -> #REF! | C185: =_xlfn.XLOOKUP(D185,PrepList!F:F,PrepList!E:E) -> #REF! | D185: =IF(PrepList!#REF!="","",PrepList!#REF!) -> #REF! | E185: =IF(PrepList!#REF!="","",PrepList!#REF!) -> #REF! | F185: =IF(PrepList!#REF!="","",PrepList!#REF!) -> #REF! | G185: =IF(PrepList!#REF!="","",PrepList!#REF!) -> #REF! | H185: =IF(PrepList!K9="","",PrepList!K9) -> BL | I185: =IF(PrepList!L9="","",PrepList!L9) -> Passed | J185: =IF(PrepList!M9="","",PrepList!M9) -> Passed | L185: =IF(PrepList!#REF!="","",PrepList!#REF!) -> #REF! | N185: =IF(PrepList!#REF!="","",PrepList!#REF!) -> #REF!
B186: =IF(PrepList!D9="","",PrepList!D9) -> Spanish | C186: =_xlfn.XLOOKUP(D186,PrepList!F:F,PrepList!E:E) -> Norelkys Gallardo | D186: =IF(PrepList!F9="","",PrepList!F9) -> 185565315 | E186: =IF(PrepList!G9="","",PrepList!G9) -> 3855907316 | F186: =IF(PrepList!H9="","",PrepList!H9) -> Day Shift | G186: =IF(PrepList!I9="","",PrepList!I9) -> Mechanical Assembly | H186: =IF(PrepList!#REF!="","",PrepList!#REF!) -> #REF! | I186: =IF(PrepList!#REF!="","",PrepList!#REF!) -> #REF! | J186: =IF(PrepList!#REF!="","",PrepList!#REF!) -> #REF! | L186: =IF(PrepList!N9="","",PrepList!N9) -> Passed | N186: =IF(PrepList!P9="","",PrepList!P9)
B187: =IF(PrepList!#REF!="","",PrepList!#REF!) -> #REF! | C187: =_xlfn.XLOOKUP(D187,PrepList!F:F,PrepList!E:E) -> #REF! | D187: =IF(PrepList!#REF!="","",PrepList!#REF!) -> #REF! | E187: =IF(PrepList!#REF!="","",PrepList!#REF!) -> #REF! | F187: =IF(PrepList!#REF!="","",PrepList!#REF!) -> #REF! | G187: =IF(PrepList!#REF!="","",PrepList!#REF!) -> #REF! | H187: =IF(PrepList!#REF!="","",PrepList!#REF!) -> #REF! | I187: =IF(PrepList!#REF!="","",PrepList!#REF!) -> #REF! | J187: =IF(PrepList!#REF!="","",PrepList!#REF!) -> #REF! | L187: =IF(PrepList!#REF!="","",PrepList!#REF!) -> #REF! | N187: =IF(PrepList!#REF!="","",PrepList!#REF!) -> #REF!
B188: =IF(PrepList!#REF!="","",PrepList!#REF!) -> #REF! | C188: =_xlfn.XLOOKUP(D188,PrepList!F:F,PrepList!E:E) -> #REF! | D188: =IF(PrepList!#REF!="","",PrepList!#REF!) -> #REF! | E188: =IF(PrepList!#REF!="","",PrepList!#REF!) -> #REF! | F188: =IF(PrepList!#REF!="","",PrepList!#REF!) -> #REF! | G188: =IF(PrepList!#REF!="","",PrepList!#REF!) -> #REF! | H188: =IF(PrepList!#REF!="","",PrepList!#REF!) -> #REF! | I188: =IF(PrepList!#REF!="","",PrepList!#REF!) -> #REF! | J188: =IF(PrepList!#REF!="","",PrepList!#REF!) -> #REF! | L188: =IF(PrepList!#REF!="","",PrepList!#REF!) -> #REF! | N188: =IF(PrepList!#REF!="","",PrepList!#REF!) -> #REF!
B189: =IF(PrepList!#REF!="","",PrepList!#REF!) -> #REF! | C189: =_xlfn.XLOOKUP(D189,PrepList!F:F,PrepList!E:E) -> #REF! | D189: =IF(PrepList!#REF!="","",PrepList!#REF!) -> #REF! | E189: =IF(PrepList!#REF!="","",PrepList!#REF!) -> #REF! | F189: =IF(PrepList!#REF!="","",PrepList!#REF!) -> #REF! | G189: =IF(PrepList!#REF!="","",PrepList!#REF!) -> #REF! | H189: =IF(PrepList!#REF!="","",PrepList!#REF!) -> #REF! | I189: =IF(PrepList!#REF!="","",PrepList!#REF!) -> #REF! | J189: =IF(PrepList!#REF!="","",PrepList!#REF!) -> #REF! | L189: =IF(PrepList!#REF!="","",PrepList!#REF!) -> #REF! | N189: =IF(PrepList!#REF!="","",PrepList!#REF!) -> #REF!
B190: =IF(PrepList!#REF!="","",PrepList!#REF!) -> #REF! | C190: =_xlfn.XLOOKUP(D190,PrepList!F:F,PrepList!E:E) -> #REF! | D190: =IF(PrepList!#REF!="","",PrepList!#REF!) -> #REF! | E190: =IF(PrepList!#REF!="","",PrepList!#REF!) -> #REF! | F190: =IF(PrepList!#REF!="","",PrepList!#REF!) -> #REF! | G190: =IF(PrepList!#REF!="","",PrepList!#REF!) -> #REF! | H190: =IF(PrepList!#REF!="","",PrepList!#REF!) -> #REF! | I190: =IF(PrepList!#REF!="","",PrepList!#REF!) -> #REF! | J190: =IF(PrepList!#REF!="","",PrepList!#REF!) -> #REF! | L190: =IF(PrepList!#REF!="","",PrepList!#REF!) -> #REF! | N190: =IF(PrepList!#REF!="","",PrepList!#REF!) -> #REF!
B191: =IF(PrepList!#REF!="","",PrepList!#REF!) -> #REF! | C191: =_xlfn.XLOOKUP(D191,PrepList!F:F,PrepList!E:E) -> #REF! | D191: =IF(PrepList!#REF!="","",PrepList!#REF!) -> #REF! | E191: =IF(PrepList!#REF!="","",PrepList!#REF!) -> #REF! | F191: =IF(PrepList!#REF!="","",PrepList!#REF!) -> #REF! | G191: =IF(PrepList!#REF!="","",PrepList!#REF!) -> #REF! | H191: =IF(PrepList!#REF!="","",PrepList!#REF!) -> #REF! | I191: =IF(PrepList!#REF!="","",PrepList!#REF!) -> #REF! | J191: =IF(PrepList!#REF!="","",PrepList!#REF!) -> #REF! | L191: =IF(PrepList!#REF!="","",PrepList!#REF!) -> #REF! | N191: =IF(PrepList!#REF!="","",PrepList!#REF!) -> #REF!
B192: =IF(PrepList!#REF!="","",PrepList!#REF!) -> #REF! | C192: =_xlfn.XLOOKUP(D192,PrepList!F:F,PrepList!E:E) -> #REF! | D192: =IF(PrepList!#REF!="","",PrepList!#REF!) -> #REF! | E192: =IF(PrepList!#REF!="","",PrepList!#REF!) -> #REF! | F192: =IF(PrepList!#REF!="","",PrepList!#REF!) -> #REF! | G192: =IF(PrepList!#REF!="","",PrepList!#REF!) -> #REF! | H192: =IF(PrepList!#REF!="","",PrepList!#REF!) -> #REF! | I192: =IF(PrepList!#REF!="","",PrepList!#REF!) -> #REF! | J192: =IF(PrepList!#REF!="","",PrepList!#REF!) -> #REF! | L192: =IF(PrepList!#REF!="","",PrepList!#REF!) -> #REF! | N192: =IF(PrepList!#REF!="","",PrepList!#REF!) -> #REF!
B193: =IF(PrepList!#REF!="","",PrepList!#REF!) -> #REF! | C193: =_xlfn.XLOOKUP(D193,PrepList!F:F,PrepList!E:E) -> #REF! | D193: =IF(PrepList!#REF!="","",PrepList!#REF!) -> #REF! | E193: =IF(PrepList!#REF!="","",PrepList!#REF!) -> #REF! | F193: =IF(PrepList!#REF!="","",PrepList!#REF!) -> #REF! | G193: =IF(PrepList!#REF!="","",PrepList!#REF!) -> #REF! | H193: =IF(PrepList!#REF!="","",PrepList!#REF!) -> #REF! | I193: =IF(PrepList!#REF!="","",PrepList!#REF!) -> #REF! | J193: =IF(PrepList!#REF!="","",PrepList!#REF!) -> #REF! | L193: =IF(PrepList!#REF!="","",PrepList!#REF!) -> #REF! | N193: =IF(PrepList!#REF!="","",PrepList!#REF!) -> #REF!
B194: =IF(PrepList!#REF!="","",PrepList!#REF!) -> #REF! | C194: =_xlfn.XLOOKUP(D194,PrepList!F:F,PrepList!E:E) -> #REF! | D194: =IF(PrepList!#REF!="","",PrepList!#REF!) -> #REF! | E194: =IF(PrepList!#REF!="","",PrepList!#REF!) -> #REF! | F194: =IF(PrepList!#REF!="","",PrepList!#REF!) -> #REF! | G194: =IF(PrepList!#REF!="","",PrepList!#REF!) -> #REF! | H194: =IF(PrepList!#REF!="","",PrepList!#REF!) -> #REF! | I194: =IF(PrepList!#REF!="","",PrepList!#REF!) -> #REF! | J194: =IF(PrepList!#REF!="","",PrepList!#REF!) -> #REF! | L194: =IF(PrepList!#REF!="","",PrepList!#REF!) -> #REF! | N194: =IF(PrepList!#REF!="","",PrepList!#REF!) -> #REF!
B195: =IF(PrepList!#REF!="","",PrepList!#REF!) -> #REF! | C195: =_xlfn.XLOOKUP(D195,PrepList!F:F,PrepList!E:E) -> #REF! | D195: =IF(PrepList!#REF!="","",PrepList!#REF!) -> #REF! | E195: =IF(PrepList!#REF!="","",PrepList!#REF!) -> #REF! | F195: =IF(PrepList!#REF!="","",PrepList!#REF!) -> #REF! | G195: =IF(PrepList!#REF!="","",PrepList!#REF!) -> #REF! | H195: =IF(PrepList!#REF!="","",PrepList!#REF!) -> #REF! | I195: =IF(PrepList!#REF!="","",PrepList!#REF!) -> #REF! | J195: =IF(PrepList!#REF!="","",PrepList!#REF!) -> #REF! | L195: =IF(PrepList!#REF!="","",PrepList!#REF!) -> #REF! | N195: =IF(PrepList!#REF!="","",PrepList!#REF!) -> #REF!
B196: =IF(PrepList!#REF!="","",PrepList!#REF!) -> #REF! | C196: =_xlfn.XLOOKUP(D196,PrepList!F:F,PrepList!E:E) -> #REF! | D196: =IF(PrepList!#REF!="","",PrepList!#REF!) -> #REF! | E196: =IF(PrepList!#REF!="","",PrepList!#REF!) -> #REF! | F196: =IF(PrepList!#REF!="","",PrepList!#REF!) -> #REF! | G196: =IF(PrepList!#REF!="","",PrepList!#REF!) -> #REF! | H196: =IF(PrepList!K10="","",PrepList!K10) -> NM | I196: =IF(PrepList!L10="","",PrepList!L10) -> Passed | J196: =IF(PrepList!M10="","",PrepList!M10) -> Passed | L196: =IF(PrepList!#REF!="","",PrepList!#REF!) -> #REF! | N196: =IF(PrepList!#REF!="","",PrepList!#REF!) -> #REF!
B197: =IF(PrepList!#REF!="","",PrepList!#REF!) -> #REF! | C197: =_xlfn.XLOOKUP(D197,PrepList!F:F,PrepList!E:E) -> #REF! | D197: =IF(PrepList!#REF!="","",PrepList!#REF!) -> #REF! | E197: =IF(PrepList!#REF!="","",PrepList!#REF!) -> #REF! | F197: =IF(PrepList!#REF!="","",PrepList!#REF!) -> #REF! | G197: =IF(PrepList!#REF!="","",PrepList!#REF!) -> #REF! | H197: =IF(PrepList!K11="","",PrepList!K11) -> DR | I197: =IF(PrepList!L11="","",PrepList!L11) -> Passed | J197: =IF(PrepList!M11="","",PrepList!M11) -> Passed | L197: =IF(PrepList!#REF!="","",PrepList!#REF!) -> #REF! | N197: =IF(PrepList!#REF!="","",PrepList!#REF!) -> #REF!
B198: =IF(PrepList!#REF!="","",PrepList!#REF!) -> #REF! | C198: =_xlfn.XLOOKUP(D198,PrepList!F:F,PrepList!E:E) -> #REF! | D198: =IF(PrepList!#REF!="","",PrepList!#REF!) -> #REF! | E198: =IF(PrepList!#REF!="","",PrepList!#REF!) -> #REF! | F198: =IF(PrepList!#REF!="","",PrepList!#REF!) -> #REF! | G198: =IF(PrepList!#REF!="","",PrepList!#REF!) -> #REF! | H198: =IF(PrepList!#REF!="","",PrepList!#REF!) -> #REF! | I198: =IF(PrepList!#REF!="","",PrepList!#REF!) -> #REF! | J198: =IF(PrepList!#REF!="","",PrepList!#REF!) -> #REF! | L198: =IF(PrepList!#REF!="","",PrepList!#REF!) -> #REF! | N198: =IF(PrepList!#REF!="","",PrepList!#REF!) -> #REF!
B199: =IF(PrepList!D10="","",PrepList!D10) -> Spanish | C199: =_xlfn.XLOOKUP(D199,PrepList!F:F,PrepList!E:E) -> Aura Rivas | D199: =IF(PrepList!F10="","",PrepList!F10) -> 177626645 | E199: =IF(PrepList!G10="","",PrepList!G10) -> 3322563395 | F199: =IF(PrepList!H10="","",PrepList!H10) -> Night Shift | G199: =IF(PrepList!I10="","",PrepList!I10) -> Mechanical Assembly | H199: =IF(PrepList!#REF!="","",PrepList!#REF!) -> #REF! | I199: =IF(PrepList!#REF!="","",PrepList!#REF!) -> #REF! | J199: =IF(PrepList!#REF!="","",PrepList!#REF!) -> #REF! | L199: =IF(PrepList!N10="","",PrepList!N10) -> Passed | N199: =IF(PrepList!P10="","",PrepList!P10) -> Confirmed on 8/26 she is still interested
B200: =IF(PrepList!D11="","",PrepList!D11) -> Spanish | C200: =_xlfn.XLOOKUP(D200,PrepList!F:F,PrepList!E:E) -> Alber Carillo | D200: =IF(PrepList!F11="","",PrepList!F11) -> 182934778 | E200: =IF(PrepList!G11="","",PrepList!G11) -> 4352007063 | F200: =IF(PrepList!H11="","",PrepList!H11) -> Day Shift | G200: =IF(PrepList!I11="","",PrepList!I11) -> Mechanical Assembly | H200: =IF(PrepList!K12="","",PrepList!K12) -> CE | I200: =IF(PrepList!L12="","",PrepList!L12) -> Passed | J200: =IF(PrepList!M12="","",PrepList!M12) -> Passed | L200: =IF(PrepList!N11="","",PrepList!N11) -> Passed | N200: =IF(PrepList!P11="","",PrepList!P11)
B201: =IF(PrepList!#REF!="","",PrepList!#REF!) -> #REF! | C201: =_xlfn.XLOOKUP(D201,PrepList!F:F,PrepList!E:E) -> #REF! | D201: =IF(PrepList!#REF!="","",PrepList!#REF!) -> #REF! | E201: =IF(PrepList!#REF!="","",PrepList!#REF!) -> #REF! | F201: =IF(PrepList!#REF!="","",PrepList!#REF!) -> #REF! | G201: =IF(PrepList!#REF!="","",PrepList!#REF!) -> #REF! | H201: =IF(PrepList!#REF!="","",PrepList!#REF!) -> #REF! | I201: =IF(PrepList!#REF!="","",PrepList!#REF!) -> #REF! | J201: =IF(PrepList!#REF!="","",PrepList!#REF!) -> #REF! | L201: =IF(PrepList!#REF!="","",PrepList!#REF!) -> #REF! | N201: =IF(PrepList!#REF!="","",PrepList!#REF!) -> #REF!
B202: =IF(PrepList!#REF!="","",PrepList!#REF!) -> #REF! | C202: =_xlfn.XLOOKUP(D202,PrepList!F:F,PrepList!E:E) -> #REF! | D202: =IF(PrepList!#REF!="","",PrepList!#REF!) -> #REF! | E202: =IF(PrepList!#REF!="","",PrepList!#REF!) -> #REF! | F202: =IF(PrepList!#REF!="","",PrepList!#REF!) -> #REF! | G202: =IF(PrepList!#REF!="","",PrepList!#REF!) -> #REF! | H202: =IF(PrepList!#REF!="","",PrepList!#REF!) -> #REF! | I202: =IF(PrepList!#REF!="","",PrepList!#REF!) -> #REF! | J202: =IF(PrepList!#REF!="","",PrepList!#REF!) -> #REF! | L202: =IF(PrepList!#REF!="","",PrepList!#REF!) -> #REF! | N202: =IF(PrepList!#REF!="","",PrepList!#REF!) -> #REF!
B203: =IF(PrepList!D12="","",PrepList!D12) -> Spanish | C203: =_xlfn.XLOOKUP(D203,PrepList!F:F,PrepList!E:E) -> Mary Andrade | D203: =IF(PrepList!F12="","",PrepList!F12) -> 198304520 | E203: =IF(PrepList!G12="","",PrepList!G12) -> 3852674145 | F203: =IF(PrepList!H12="","",PrepList!H12) -> Day Shift | G203: =IF(PrepList!I12="","",PrepList!I12) -> Mechanical Assembly | H203: =IF(PrepList!#REF!="","",PrepList!#REF!) -> #REF! | I203: =IF(PrepList!#REF!="","",PrepList!#REF!) -> #REF! | J203: =IF(PrepList!#REF!="","",PrepList!#REF!) -> #REF! | L203: =IF(PrepList!N12="","",PrepList!N12) -> Passed | N203: =IF(PrepList!P12="","",PrepList!P12)
B204: =IF(PrepList!#REF!="","",PrepList!#REF!) -> #REF! | C204: =_xlfn.XLOOKUP(D204,PrepList!F:F,PrepList!E:E) -> #REF! | D204: =IF(PrepList!#REF!="","",PrepList!#REF!) -> #REF! | E204: =IF(PrepList!#REF!="","",PrepList!#REF!) -> #REF! | F204: =IF(PrepList!#REF!="","",PrepList!#REF!) -> #REF! | G204: =IF(PrepList!#REF!="","",PrepList!#REF!) -> #REF! | H204: =IF(PrepList!#REF!="","",PrepList!#REF!) -> #REF! | I204: =IF(PrepList!#REF!="","",PrepList!#REF!) -> #REF! | J204: =IF(PrepList!#REF!="","",PrepList!#REF!) -> #REF! | L204: =IF(PrepList!#REF!="","",PrepList!#REF!) -> #REF! | N204: =IF(PrepList!#REF!="","",PrepList!#REF!) -> #REF!
B205: =IF(PrepList!#REF!="","",PrepList!#REF!) -> #REF! | C205: =_xlfn.XLOOKUP(D205,PrepList!F:F,PrepList!E:E) -> #REF! | D205: =IF(PrepList!#REF!="","",PrepList!#REF!) -> #REF! | E205: =IF(PrepList!#REF!="","",PrepList!#REF!) -> #REF! | F205: =IF(PrepList!#REF!="","",PrepList!#REF!) -> #REF! | G205: =IF(PrepList!#REF!="","",PrepList!#REF!) -> #REF! | H205: =IF(PrepList!#REF!="","",PrepList!#REF!) -> #REF! | I205: =IF(PrepList!#REF!="","",PrepList!#REF!) -> #REF! | J205: =IF(PrepList!#REF!="","",PrepList!#REF!) -> #REF! | L205: =IF(PrepList!#REF!="","",PrepList!#REF!) -> #REF! | N205: =IF(PrepList!#REF!="","",PrepList!#REF!) -> #REF!
B206: =IF(PrepList!#REF!="","",PrepList!#REF!) -> #REF! | C206: =_xlfn.XLOOKUP(D206,PrepList!F:F,PrepList!E:E) -> #REF! | D206: =IF(PrepList!#REF!="","",PrepList!#REF!) -> #REF! | E206: =IF(PrepList!#REF!="","",PrepList!#REF!) -> #REF! | F206: =IF(PrepList!#REF!="","",PrepList!#REF!) -> #REF! | G206: =IF(PrepList!#REF!="","",PrepList!#REF!) -> #REF! | H206: =IF(PrepList!#REF!="","",PrepList!#REF!) -> #REF! | I206: =IF(PrepList!#REF!="","",PrepList!#REF!) -> #REF! | J206: =IF(PrepList!#REF!="","",PrepList!#REF!) -> #REF! | L206: =IF(PrepList!#REF!="","",PrepList!#REF!) -> #REF! | N206: =IF(PrepList!#REF!="","",PrepList!#REF!) -> #REF!
B207: =IF(PrepList!#REF!="","",PrepList!#REF!) -> #REF! | C207: =_xlfn.XLOOKUP(D207,PrepList!F:F,PrepList!E:E) -> #REF! | D207: =IF(PrepList!#REF!="","",PrepList!#REF!) -> #REF! | E207: =IF(PrepList!#REF!="","",PrepList!#REF!) -> #REF! | F207: =IF(PrepList!#REF!="","",PrepList!#REF!) -> #REF! | G207: =IF(PrepList!#REF!="","",PrepList!#REF!) -> #REF! | H207: =IF(PrepList!#REF!="","",PrepList!#REF!) -> #REF! | I207: =IF(PrepList!#REF!="","",PrepList!#REF!) -> #REF! | J207: =IF(PrepList!#REF!="","",PrepList!#REF!) -> #REF! | L207: =IF(PrepList!#REF!="","",PrepList!#REF!) -> #REF! | N207: =IF(PrepList!#REF!="","",PrepList!#REF!) -> #REF!
B208: =IF(PrepList!#REF!="","",PrepList!#REF!) -> #REF! | C208: =_xlfn.XLOOKUP(D208,PrepList!F:F,PrepList!E:E) -> #REF! | D208: =IF(PrepList!#REF!="","",PrepList!#REF!) -> #REF! | E208: =IF(PrepList!#REF!="","",PrepList!#REF!) -> #REF! | F208: =IF(PrepList!#REF!="","",PrepList!#REF!) -> #REF! | G208: =IF(PrepList!#REF!="","",PrepList!#REF!) -> #REF! | H208: =IF(PrepList!K13="","",PrepList!K13) -> CE | I208: =IF(PrepList!L13="","",PrepList!L13) -> Passed | J208: =IF(PrepList!M13="","",PrepList!M13) -> Passed | L208: =IF(PrepList!#REF!="","",PrepList!#REF!) -> #REF! | N208: =IF(PrepList!#REF!="","",PrepList!#REF!) -> #REF!
B209: =IF(PrepList!#REF!="","",PrepList!#REF!) -> #REF! | C209: =_xlfn.XLOOKUP(D209,PrepList!F:F,PrepList!E:E) -> #REF! | D209: =IF(PrepList!#REF!="","",PrepList!#REF!) -> #REF! | E209: =IF(PrepList!#REF!="","",PrepList!#REF!) -> #REF! | F209: =IF(PrepList!#REF!="","",PrepList!#REF!) -> #REF! | G209: =IF(PrepList!#REF!="","",PrepList!#REF!) -> #REF! | H209: =IF(PrepList!#REF!="","",PrepList!#REF!) -> #REF! | I209: =IF(PrepList!#REF!="","",PrepList!#REF!) -> #REF! | J209: =IF(PrepList!#REF!="","",PrepList!#REF!) -> #REF! | L209: =IF(PrepList!#REF!="","",PrepList!#REF!) -> #REF! | N209: =IF(PrepList!#REF!="","",PrepList!#REF!) -> #REF!
B210: =IF(PrepList!#REF!="","",PrepList!#REF!) -> #REF! | C210: =_xlfn.XLOOKUP(D210,PrepList!F:F,PrepList!E:E) -> #REF! | D210: =IF(PrepList!#REF!="","",PrepList!#REF!) -> #REF! | E210: =IF(PrepList!#REF!="","",PrepList!#REF!) -> #REF! | F210: =IF(PrepList!#REF!="","",PrepList!#REF!) -> #REF! | G210: =IF(PrepList!#REF!="","",PrepList!#REF!) -> #REF! | H210: =IF(PrepList!#REF!="","",PrepList!#REF!) -> #REF! | I210: =IF(PrepList!#REF!="","",PrepList!#REF!) -> #REF! | J210: =IF(PrepList!#REF!="","",PrepList!#REF!) -> #REF! | L210: =IF(PrepList!#REF!="","",PrepList!#REF!) -> #REF! | N210: =IF(PrepList!#REF!="","",PrepList!#REF!) -> #REF!
B211: =IF(PrepList!#REF!="","",PrepList!#REF!) -> #REF! | C211: =_xlfn.XLOOKUP(D211,PrepList!F:F,PrepList!E:E) -> #REF! | D211: =IF(PrepList!#REF!="","",PrepList!#REF!) -> #REF! | E211: =IF(PrepList!#REF!="","",PrepList!#REF!) -> #REF! | F211: =IF(PrepList!#REF!="","",PrepList!#REF!) -> #REF! | G211: =IF(PrepList!#REF!="","",PrepList!#REF!) -> #REF! | H211: =IF(PrepList!#REF!="","",PrepList!#REF!) -> #REF! | I211: =IF(PrepList!#REF!="","",PrepList!#REF!) -> #REF! | J211: =IF(PrepList!#REF!="","",PrepList!#REF!) -> #REF! | L211: =IF(PrepList!#REF!="","",PrepList!#REF!) -> #REF! | N211: =IF(PrepList!#REF!="","",PrepList!#REF!) -> #REF!
B212: =IF(PrepList!D13="","",PrepList!D13) -> Spanish | C212: =_xlfn.XLOOKUP(D212,PrepList!F:F,PrepList!E:E) -> Yoseani Contreras | D212: =IF(PrepList!F13="","",PrepList!F13) -> 198457422 | E212: =IF(PrepList!G13="","",PrepList!G13) -> 5517991219 | F212: =IF(PrepList!H13="","",PrepList!H13) -> Night Shift | G212: =IF(PrepList!I13="","",PrepList!I13) -> Mechanical Assembly | H212: =IF(PrepList!#REF!="","",PrepList!#REF!) -> #REF! | I212: =IF(PrepList!#REF!="","",PrepList!#REF!) -> #REF! | J212: =IF(PrepList!#REF!="","",PrepList!#REF!) -> #REF! | L212: =IF(PrepList!N13="","",PrepList!N13) -> Passed | N212: =IF(PrepList!P13="","",PrepList!P13)
B213: =IF(PrepList!#REF!="","",PrepList!#REF!) -> #REF! | C213: =_xlfn.XLOOKUP(D213,PrepList!F:F,PrepList!E:E) -> #REF! | D213: =IF(PrepList!#REF!="","",PrepList!#REF!) -> #REF! | E213: =IF(PrepList!#REF!="","",PrepList!#REF!) -> #REF! | F213: =IF(PrepList!#REF!="","",PrepList!#REF!) -> #REF! | G213: =IF(PrepList!#REF!="","",PrepList!#REF!) -> #REF! | H213: =IF(PrepList!#REF!="","",PrepList!#REF!) -> #REF! | I213: =IF(PrepList!#REF!="","",PrepList!#REF!) -> #REF! | J213: =IF(PrepList!#REF!="","",PrepList!#REF!) -> #REF! | L213: =IF(PrepList!#REF!="","",PrepList!#REF!) -> #REF! | N213: =IF(PrepList!#REF!="","",PrepList!#REF!) -> #REF!
B214: =IF(PrepList!#REF!="","",PrepList!#REF!) -> #REF! | C214: =_xlfn.XLOOKUP(D214,PrepList!F:F,PrepList!E:E) -> #REF! | D214: =IF(PrepList!#REF!="","",PrepList!#REF!) -> #REF! | E214: =IF(PrepList!#REF!="","",PrepList!#REF!) -> #REF! | F214: =IF(PrepList!#REF!="","",PrepList!#REF!) -> #REF! | G214: =IF(PrepList!#REF!="","",PrepList!#REF!) -> #REF! | H214: =IF(PrepList!#REF!="","",PrepList!#REF!) -> #REF! | I214: =IF(PrepList!#REF!="","",PrepList!#REF!) -> #REF! | J214: =IF(PrepList!#REF!="","",PrepList!#REF!) -> #REF! | L214: =IF(PrepList!#REF!="","",PrepList!#REF!) -> #REF! | N214: =IF(PrepList!#REF!="","",PrepList!#REF!) -> #REF!
B215: =IF(PrepList!#REF!="","",PrepList!#REF!) -> #REF! | C215: =_xlfn.XLOOKUP(D215,PrepList!F:F,PrepList!E:E) -> #REF! | D215: =IF(PrepList!#REF!="","",PrepList!#REF!) -> #REF! | E215: =IF(PrepList!#REF!="","",PrepList!#REF!) -> #REF! | F215: =IF(PrepList!#REF!="","",PrepList!#REF!) -> #REF! | G215: =IF(PrepList!#REF!="","",PrepList!#REF!) -> #REF! | H215: =IF(PrepList!#REF!="","",PrepList!#REF!) -> #REF! | I215: =IF(PrepList!#REF!="","",PrepList!#REF!) -> #REF! | J215: =IF(PrepList!#REF!="","",PrepList!#REF!) -> #REF! | L215: =IF(PrepList!#REF!="","",PrepList!#REF!) -> #REF! | N215: =IF(PrepList!#REF!="","",PrepList!#REF!) -> #REF!
B216: =IF(PrepList!#REF!="","",PrepList!#REF!) -> #REF! | C216: =_xlfn.XLOOKUP(D216,PrepList!F:F,PrepList!E:E) -> #REF! | D216: =IF(PrepList!#REF!="","",PrepList!#REF!) -> #REF! | E216: =IF(PrepList!#REF!="","",PrepList!#REF!) -> #REF! | F216: =IF(PrepList!#REF!="","",PrepList!#REF!) -> #REF! | G216: =IF(PrepList!#REF!="","",PrepList!#REF!) -> #REF! | H216: =IF(PrepList!#REF!="","",PrepList!#REF!) -> #REF! | I216: =IF(PrepList!#REF!="","",PrepList!#REF!) -> #REF! | J216: =IF(PrepList!#REF!="","",PrepList!#REF!) -> #REF! | L216: =IF(PrepList!#REF!="","",PrepList!#REF!) -> #REF! | N216: =IF(PrepList!#REF!="","",PrepList!#REF!) -> #REF!
B217: =IF(PrepList!#REF!="","",PrepList!#REF!) -> #REF! | C217: =_xlfn.XLOOKUP(D217,PrepList!F:F,PrepList!E:E) -> #REF! | D217: =IF(PrepList!#REF!="","",PrepList!#REF!) -> #REF! | E217: =IF(PrepList!#REF!="","",PrepList!#REF!) -> #REF! | F217: =IF(PrepList!#REF!="","",PrepList!#REF!) -> #REF! | G217: =IF(PrepList!#REF!="","",PrepList!#REF!) -> #REF! | H217: =IF(PrepList!#REF!="","",PrepList!#REF!) -> #REF! | I217: =IF(PrepList!#REF!="","",PrepList!#REF!) -> #REF! | J217: =IF(PrepList!#REF!="","",PrepList!#REF!) -> #REF! | L217: =IF(PrepList!#REF!="","",PrepList!#REF!) -> #REF! | N217: =IF(PrepList!#REF!="","",PrepList!#REF!) -> #REF!
B218: =IF(PrepList!#REF!="","",PrepList!#REF!) -> #REF! | C218: =_xlfn.XLOOKUP(D218,PrepList!F:F,PrepList!E:E) -> #REF! | D218: =IF(PrepList!#REF!="","",PrepList!#REF!) -> #REF! | E218: =IF(PrepList!#REF!="","",PrepList!#REF!) -> #REF! | F218: =IF(PrepList!#REF!="","",PrepList!#REF!) -> #REF! | G218: =IF(PrepList!#REF!="","",PrepList!#REF!) -> #REF! | H218: =IF(PrepList!#REF!="","",PrepList!#REF!) -> #REF! | I218: =IF(PrepList!#REF!="","",PrepList!#REF!) -> #REF! | J218: =IF(PrepList!#REF!="","",PrepList!#REF!) -> #REF! | L218: =IF(PrepList!#REF!="","",PrepList!#REF!) -> #REF! | N218: =IF(PrepList!#REF!="","",PrepList!#REF!) -> #REF!
B219: =IF(PrepList!#REF!="","",PrepList!#REF!) -> #REF! | C219: =_xlfn.XLOOKUP(D219,PrepList!F:F,PrepList!E:E) -> #REF! | D219: =IF(PrepList!#REF!="","",PrepList!#REF!) -> #REF! | E219: =IF(PrepList!#REF!="","",PrepList!#REF!) -> #REF! | F219: =IF(PrepList!#REF!="","",PrepList!#REF!) -> #REF! | G219: =IF(PrepList!#REF!="","",PrepList!#REF!) -> #REF! | H219: =IF(PrepList!#REF!="","",PrepList!#REF!) -> #REF! | I219: =IF(PrepList!#REF!="","",PrepList!#REF!) -> #REF! | J219: =IF(PrepList!#REF!="","",PrepList!#REF!) -> #REF! | L219: =IF(PrepList!#REF!="","",PrepList!#REF!) -> #REF! | N219: =IF(PrepList!#REF!="","",PrepList!#REF!) -> #REF!
B220: =IF(PrepList!#REF!="","",PrepList!#REF!) -> #REF! | C220: =_xlfn.XLOOKUP(D220,PrepList!F:F,PrepList!E:E) -> #REF! | D220: =IF(PrepList!#REF!="","",PrepList!#REF!) -> #REF! | E220: =IF(PrepList!#REF!="","",PrepList!#REF!) -> #REF! | F220: =IF(PrepList!#REF!="","",PrepList!#REF!) -> #REF! | G220: =IF(PrepList!#REF!="","",PrepList!#REF!) -> #REF! | H220: =IF(PrepList!#REF!="","",PrepList!#REF!) -> #REF! | I220: =IF(PrepList!#REF!="","",PrepList!#REF!) -> #REF! | J220: =IF(PrepList!#REF!="","",PrepList!#REF!) -> #REF! | L220: =IF(PrepList!#REF!="","",PrepList!#REF!) -> #REF! | N220: =IF(PrepList!#REF!="","",PrepList!#REF!) -> #REF!
B221: =IF(PrepList!#REF!="","",PrepList!#REF!) -> #REF! | C221: =_xlfn.XLOOKUP(D221,PrepList!F:F,PrepList!E:E) -> #REF! | D221: =IF(PrepList!#REF!="","",PrepList!#REF!) -> #REF! | E221: =IF(PrepList!#REF!="","",PrepList!#REF!) -> #REF! | F221: =IF(PrepList!#REF!="","",PrepList!#REF!) -> #REF! | G221: =IF(PrepList!#REF!="","",PrepList!#REF!) -> #REF! | H221: =IF(PrepList!#REF!="","",PrepList!#REF!) -> #REF! | I221: =IF(PrepList!#REF!="","",PrepList!#REF!) -> #REF! | J221: =IF(PrepList!#REF!="","",PrepList!#REF!) -> #REF! | L221: =IF(PrepList!#REF!="","",PrepList!#REF!) -> #REF! | N221: =IF(PrepList!#REF!="","",PrepList!#REF!) -> #REF!
B222: =IF(PrepList!#REF!="","",PrepList!#REF!) -> #REF! | C222: =_xlfn.XLOOKUP(D222,PrepList!F:F,PrepList!E:E) -> #REF! | D222: =IF(PrepList!#REF!="","",PrepList!#REF!) -> #REF! | E222: =IF(PrepList!#REF!="","",PrepList!#REF!) -> #REF! | F222: =IF(PrepList!#REF!="","",PrepList!#REF!) -> #REF! | G222: =IF(PrepList!#REF!="","",PrepList!#REF!) -> #REF! | H222: =IF(PrepList!#REF!="","",PrepList!#REF!) -> #REF! | I222: =IF(PrepList!#REF!="","",PrepList!#REF!) -> #REF! | J222: =IF(PrepList!#REF!="","",PrepList!#REF!) -> #REF! | L222: =IF(PrepList!#REF!="","",PrepList!#REF!) -> #REF! | N222: =IF(PrepList!#REF!="","",PrepList!#REF!) -> #REF!
B223: =IF(PrepList!#REF!="","",PrepList!#REF!) -> #REF! | C223: =_xlfn.XLOOKUP(D223,PrepList!F:F,PrepList!E:E) -> #REF! | D223: =IF(PrepList!#REF!="","",PrepList!#REF!) -> #REF! | E223: =IF(PrepList!#REF!="","",PrepList!#REF!) -> #REF! | F223: =IF(PrepList!#REF!="","",PrepList!#REF!) -> #REF! | G223: =IF(PrepList!#REF!="","",PrepList!#REF!) -> #REF! | H223: =IF(PrepList!#REF!="","",PrepList!#REF!) -> #REF! | I223: =IF(PrepList!#REF!="","",PrepList!#REF!) -> #REF! | J223: =IF(PrepList!#REF!="","",PrepList!#REF!) -> #REF! | L223: =IF(PrepList!#REF!="","",PrepList!#REF!) -> #REF! | N223: =IF(PrepList!#REF!="","",PrepList!#REF!) -> #REF!
B224: =IF(PrepList!#REF!="","",PrepList!#REF!) -> #REF! | C224: =_xlfn.XLOOKUP(D224,PrepList!F:F,PrepList!E:E) -> #REF! | D224: =IF(PrepList!#REF!="","",PrepList!#REF!) -> #REF! | E224: =IF(PrepList!#REF!="","",PrepList!#REF!) -> #REF! | F224: =IF(PrepList!#REF!="","",PrepList!#REF!) -> #REF! | G224: =IF(PrepList!#REF!="","",PrepList!#REF!) -> #REF! | H224: =IF(PrepList!#REF!="","",PrepList!#REF!) -> #REF! | I224: =IF(PrepList!#REF!="","",PrepList!#REF!) -> #REF! | J224: =IF(PrepList!#REF!="","",PrepList!#REF!) -> #REF! | L224: =IF(PrepList!#REF!="","",PrepList!#REF!) -> #REF! | N224: =IF(PrepList!#REF!="","",PrepList!#REF!) -> #REF!
... B294: =IF(PrepList!#REF!="","",PrepList!#REF!) -> #REF! | C294: =_xlfn.XLOOKUP(D294,PrepList!F:F,PrepList!E:E) -> #REF! | D294: =IF(PrepList!#REF!="","",PrepList!#REF!) -> #REF! | E294: =IF(PrepList!#REF!="","",PrepList!#REF!) -> #REF! | F294: =IF(PrepList!#REF!="","",PrepList!#REF!) -> #REF! | G294: =IF(PrepList!#REF!="","",PrepList!#REF!) -> #REF! | H294: =IF(PrepList!#REF!="","",PrepList!#REF!) -> #REF! | I294: =IF(PrepList!#REF!="","",PrepList!#REF!) -> #REF! | J294: =IF(PrepList!#REF!="","",PrepList!#REF!) -> #REF! | L294: =IF(PrepList!#REF!="","",PrepList!#REF!) -> #REF! | N294: =IF(PrepList!#REF!="","",PrepList!#REF!) -> #REF!

Sheet Activity Tracker & Pipeline
A1: SLC Activity Tracker 2024 | D1: Applications | F1: Phone Screens | H1: Interviews | J1: Resume Subs | L1: Offers Accepted | M1: Decline Reasons
A2: Office | B2: Date | C2: # of recruiters | D2: Goal | E2: Attn | F2: Goal | G2: Attn | H2: Today | I2: Tomorrow | J2: Goal | K2: Attn | M2: Decline Reasons
A3: NSL | P3: Prepped | Q3: =R4+T4+V4+X4+Z4+AB4+AD4+AF4+AH4+AJ4+AL4+AN4 -> 496 | R3: A/C Mechanical Assembly | S3: BG Cleared | T3: B/D Mechanical Assembly | U3: BG Cleared | V3: A/C Materials | W3: BG Cleared | X3: B/D Materials | Y3: BG Cleared | Z3: A/C Rack Assembly | AA3: BG Cleared | AB3: B/D Rack Assembly | AC3: BG Cleared | AD3: IT Support Technician | AE3: BG Cleared | AF3: Delivery Business Systems Analyst | AG3: BG Cleared | AH3: B/D Quality | AI3: BG Cleared | AJ3: A/C Test Operator | AK3: BG Cleared | AL3: A/C Debug | AM3: BG Cleared | AN3: B/D Debug Tech 4 | AO3: BG Cleared
A4: WVC | P4: Cleared | Q4: =S4+U4+W4+Y4+AA4+AC4+AE4+AG4+AI4+AK4+AM4+AO4 -> 238 | R4: 306 | S4: 149 | T4: 130 | U4: 61 | V4: 15 | W4: 10 | X4: 19 | Y4: 8 | Z4: 12 | AA4: 4 | AB4: 12 | AC4: 4 | AD4: 0 | AE4: 0 | AF4: 0 | AG4: 0 | AH4: 0 | AI4: 0 | AJ4: 0 | AK4: 0 | AL4: 1 | AM4: 1 | AN4: 1 | AO4: 1 | AP4: 3 | AQ4: 1 | AR4: 2 | AS4: 2 | AT4: 0 | AU4: 0 | AV4: 0 | AW4: 0 | AX4: 0 | AY4: 0 | AZ4: 0 | BA4: 0
A5: WJ | P5: Updated | Q5: 46197
A6: TOTAL | C6: =SUM(C2:C5) -> 0 | D6: =SUM(D2:D5) -> 0 | E6: =SUM(E2:E5) -> 0 | F6: =SUM(F2:F5) -> 0 | G6: =SUM(G2:G5) -> 0 | H6: =SUM(H2:H5) -> 0 | I6: =SUM(I2:I5) -> 0 | J6: =SUM(J2:J5) -> 0 | ... L6: =SUM(L2:L5) -> 0
A9: Date Last Posted | C9: WVC | D9: 45985 | E9: 45986 | F9: 45987 | G9: 45988 | H9: 45989 | K9: A Roster Starts
C10: QC Inspector - Days | D10: 5 | K10: B Roster Starts
C11: QC Inspector - Nights | D11: 0
C12: 1st shift assembly | D12: 0
C13: 3rd shift assembly | D13: 0
A14: Date Last Posted | C14: WJ
C15: 3rd shift assembly | D15: 0
A18: Date Last Posted | C18: NSL
B19: Day - Warehouse | D19: 0
B20: Grave - Warehouse | D20: 0
B21: Grave - Quality Control | D21: 0
B22: Day - Quality Control | D22: 0
C24: Applies | D24: =SUM(D10:D23) -> 5 | E24: =SUM(E10:E23) -> 0 | F24: =SUM(F10:F23) -> 0 | G24: =SUM(G10:G23) -> 0 | H24: =SUM(H10:H23) -> 0 | I24: =SUM(I10:I23) -> 0 | J24: =SUM(J10:J23) -> 0
D25: by 5pm

Sheet PrepList
A1: Date | B1: Last Contacted | C1: Contacted | D1: Language | E1: Employee Name (must match Avionte) | F1: Talent ID | G1: Phone | H1: Shift Preference | I1: Position | J1: Office | K1: Recruiter | L1: BG? | M1: DT? | N1: FLEX Doc Sent | O1: Attended Mini Orientation | P1: Notes
A2: 45797 | B2: 46260 | C2: Contacted | D2: Spanish | E2: Doraxci Gonzalez | F2: 177671254 | G2: 3856289600 | H2: Day Shift | I2: Mechanical Assembly | J2: WJ | K2: FZ | L2: Pending | N2: Passed | O2: Yes | P2: Confirmed on 8/26 she is still interested
A3: 45869 | B3: 46260 | C3: Contacted | D3: Spanish | E3: Maralis Mendoza | F3: 198173510 | G3: 3852164295 | H3: Day Shift | I3: Mechanical Assembly | J3: WJ | K3: BL | L3: Passed | M3: Passed | N3: Passed | P3: Confirmed on 8/26 she is still interested
A4: 45876 | B4: 46260 | C4: Contacted | D4: Spanish | E4: Edna Dominguez | F4: 148926496 | G4: 8019185846 | H4: Night Shift | I4: Mechanical Assembly | J4: WVC | K4: CE | L4: Passed | M4: Passed | N4: Passed | P4: She stated she wont be in Utah for a few months?
A5: 45876 | B5: 46260 | C5: Contacted | D5: Spanish | E5: Amayrany Hernandez | F5: 198303055 | G5: 3855410937 | H5: Night Shift | I5: Mechanical Assembly | J5: WVC | K5: CE | L5: Passed | M5: Passed | N5: Passed | P5: Confirmed on 8/26 she is still interested
A6: 45877 | B6: 46260 | C6: Contacted | D6: Spanish | E6: Aracely Hernandez | F6: 198318924 | G6: 4357141187 | H6: Night Shift | I6: Mechanical Assembly | J6: WVC | K6: CE | L6: Passed | M6: Passed | N6: Passed
A7: 45880 | B7: 46260 | C7: Contacted | D7: Spanish | E7: Snayder Pongo | F7: 198237668 | G7: 3854883070 | H7: Day Shift | I7: Mechanical Assembly | J7: WJ | K7: NM | L7: Passed | M7: Passed | N7: Passed
A8: 45881 | B8: 46260 | C8: Contacted | D8: Spanish | E8: Yennifer Hernandez | F8: 186325204 | G8: 8015094766 | H8: Day Shift | I8: Mechanical Assembly | J8: WJ | K8: BL | L8: Passed | M8: Passed | N8: Passed
A9: 45881 | B9: 46260 | C9: Contacted | D9: Spanish | E9: Norelkys Gallardo | F9: 185565315 | G9: 3855907316 | H9: Day Shift | I9: Mechanical Assembly | J9: WJ | K9: BL | L9: Passed | M9: Passed | N9: Passed
A10: 45887 | B10: 46260 | C10: Contacted | D10: Spanish | E10: Aura Rivas | F10: 177626645 | G10: 3322563395 | H10: Night Shift | I10: Mechanical Assembly | J10: WJ | K10: NM | L10: Passed | M10: Passed | N10: Passed | O10: Yes | P10: Confirmed on 8/26 she is still interested
A11: 45888 | B11: 46260 | C11: Contacted | D11: Spanish | E11: Alber Carillo | F11: 182934778 | G11: 4352007063 | H11: Day Shift | I11: Mechanical Assembly | J11: NSL | K11: DR | L11: Passed | M11: Passed | N11: Passed | O11: Pending
A12: 45888 | B12: 46260 | C12: Contacted | D12: Spanish | E12: Mary Andrade | F12: 198304520 | G12: 3852674145 | H12: Day Shift | I12: Mechanical Assembly | J12: WVC | K12: CE | L12: Passed | M12: Passed | N12: Passed
A13: 45889 | B13: 46260 | C13: Contacted | D13: Spanish | E13: Yoseani Contreras | F13: 198457422 | G13: 5517991219 | H13: Night Shift | I13: Mechanical Assembly | J13: WVC | K13: CE | L13: Passed | M13: Passed | N13: Passed | O13: Pending
A14: 01/16/226 | B14: 46260 | C14: Contacted | D14: Spanish | E14: Irene Guerrero | F14: 176593378 | G14: 3855894411 | H14: Day Shift | I14: Mechanical Assembly | J14: WJ | K14: NM | L14: Passed | M14: Passed | N14: Passed | O14: Pending
B15: 46265 | C15: Contacted | D15: Spanish | E15: Diego Gomez | F15: 186547714 | G15: 9283237807 | H15: Day Shift | I15: Mechanical Assembly | J15: NSL | K15: DR | L15: Passed | M15: Passed | N15: Passed | O15: Pending
B16: 46265 | C16: Contacted | D16: Spanish | E16: Genesis Gonzales | F16: 155192157 | G16: 8018312018 | H16: Night Shift | I16: Mechanical Assembly | J16: NSL | K16: DR | L16: Not Ran | M16: Passed | N16: Sent | O16: Pending | P16: Confirmed on 9/1 she is stil interested
B17: 46265 | C17: Contacted | D17: Spanish | E17: Erika Beltran | F17: 215164885 | G17: 3854919576 | H17: Night Shift | I17: Mechanical Assembly | J17: NSL | K17: DR | L17: Not Ran | M17: Passed | N17: Sent | O17: Pending
B18: 46265 | C18: Contacted | D18: Spanish | E18: Adriana Gonzales | F18: 216395703 | G18: 3852964862 | H18: Day Shift | I18: Mechanical Assembly | J18: NSL | K18: DR | L18: Pending | N18: Passed | O18: Pending
B19: 46266 | C19: Contacted | D19: Spanish | E19: Maira Aray | F19: 167482313 | G19: 8014036011 | H19: Day Shift | I19: Mechanical Assembly | J19: NSL | K19: DR | L19: Not Ran | N19: Sent | O19: Pending
B20: 46266 | C20: Contacted | D20: Spanish | E20: Francisca Rodriguez | F20: 216398767 | G20: 8016001096 | H20: Day Shift | I20: Mechanical Assembly | J20: NSL | K20: DR | L20: Pending | N20: Passed | O20: Pending
B21: 46266 | C21: Contacted | D21: Spanish | E21: Edgar Blanco | F21: 198454505 | G21: 3855410257 | H21: Day Shift | I21: Mechanical Assembly | J21: WJ | K21: NM | L21: Passed | M21: Passed | N21: Passed | O21: Yes | P21: Phone# no longer valid
B22: 46266 | C22: Contacted | D22: Spanish | E22: Joaquina mAlvarado | F22: 182803870 | G22: 3855767303 | H22: Day Shift | I22: Mechanical Assembly | J22: WVC | K22: AR | L22: Passed | M22: Passed | N22: Passed
B23: 46266 | C23: Contacted | D23: Spanish | E23: Susana Medina | F23: 95712795 | G23: (385) 775-3179 | H23: Day Shift | I23: Mechanical Assembly | J23: WJ | K23: BL | L23: Passed | M23: Passed | N23: Passed | P23: Confirmed on 9/1 she is still interested
B24: 46266 | C24: Contacted | D24: Spanish | E24: Greisibel Reyes | F24: 187283462 | G24: 3076775835 | H24: Day Shift | I24: Mechanical Assembly | J24: WJ | K24: BL | L24: Passed | M24: Passed | N24: Passed
C25: Contacted | D25: English | E25: Chad Candland | F25: 167453188 | G25: 8015746280 | H25: Night Shift | I25: Mechanical Assembly | J25: NSL | K25: GKW | L25: Passed | M25: Passed | N25: Passed
B26: 46266 | C26: Contacted | D26: Spanish | E26: Fainoly Nino | F26: 198115241 | G26: 8012443795 | H26: Day Shift | I26: Mechanical Assembly | J26: NSL | K26: DG | L26: Pending | M26: Passed | N26: Passed
B27: 46269 | C27: Contacted | D27: Spanish | E27: Jahiro Salas | F27: 198477793 | G27: 8016618133 | H27: Day Shift | I27: Mechanical Assembly | J27: NSL | K27: DG | L27: Passed | M27: Passed | N27: Passed
B28: 46269 | C28: Contacted | D28: Spanish | E28: ELIO PORTILLA | G28: (801) 895-6980 | H28: Day Shift | I28: Mechanical Assembly | J28: NSL | K28: DR | L28: Passed | M28: Passed | N28: Passed
B29: 46269 | C29: Contacted | D29: Bilingual | E29: Martha Salvador Trejo | F29: 199551858 | G29: 3853430317 | H29: Day Shift | I29: Mechanical Assembly | J29: WVC | K29: CE | L29: Passed | M29: Passed | N29: Passed
B30: 46269 | C30: Contacted | D30: Spanish | E30: Luz Ospina | F30: 186544458 | G30: (609) 516-2765 | H30: Day Shift | I30: Mechanical Assembly | J30: WVC | K30: CE
B31: 46269 | C31: Contacted | D31: Bilingual | E31: Rocio Rodriguez | G31: 801-7219587 | H31: Day Shift | J31: NSL
B32: 46269 | C32: Contacted | D32: Spanish | E32: Maria Linares | F32: 155478795 | G32: 3852610893 | H32: Day Shift | I32: Mechanical Assembly | J32: WJ | K32: NM | L32: Passed | M32: Passed | N32: Passed
B33: 46269 | C33: Contacted | D33: Spanish | E33: Dilianny Delsie | F33: 177942733 | G33: 8015849797 | H33: Day Shift | I33: Mechanical Assembly | J33: NSL | K33: DR | L33: Pending | M33: Passed | N33: Passed
B34: 46269 | C34: Contacted | D34: Spanish | E34: Katty Rossell | F34: 216398708 | G34: 5512025893 | H34: Day Shift | I34: Mechanical Assembly | J34: NSL | K34: DR | L34: Not Ran | N34: Passed
B35: 46269 | C35: Contacted | D35: Spanish | E35: Marialex Parajo | F35: 191900159 | G35: 3852522378 | H35: Day Shift | I35: Mechanical Assembly | J35: NSL | K35: DR | L35: Passed | M35: Passed | N35: Sent
B36: 46273 | C36: Contacted | D36: English | E36: Tyrone Scott | F36: 218580424 | G36: 8016669504 | H36: Night Shift | I36: Mechanical Assembly | J36: NSL | K36: GKW | N36: Sent | P36: Interested as of 9/9/26
A37: 46072 | B37: 46273 | C37: Contacted | D37: Spanish | E37: Gabriela Fernandez | F37: 144684733 | G37: 3852377965 | H37: Day Shift | I37: Mechanical Assembly | J37: WJ | K37: BL | L37: Passed | M37: Passed | N37: Passed
A38: 46072 | B38: 46273 | C38: Contacted | D38: Spanish | E38: Anabelis Peraza | F38: 139332894 | G38: 3854572418 | H38: Night Shift | I38: Materials | J38: WJ | K38: FZ | L38: Passed | M38: Passed | N38: Passed
A39: 46072 | B39: 46273 | C39: Contacted | D39: Spanish | E39: Eva Ramirez | F39: 218508261 | G39: 8018280334 | H39: Day Shift | I39: Mechanical Assembly | J39: WJ | K39: BL | L39: Passed | M39: Passed | N39: Passed | P39: Interested as of 9/9
A40: 46072 | B40: 46273 | C40: Contacted | D40: Spanish | E40: Ricardo Perea Vera | F40: 218637517 | G40: 3858314755 | H40: Night Shift | I40: Mechanical Assembly | J40: WVC | K40: SM | L40: Passed | M40: Passed | N40: Passed | P40: Interested as of 9/9
A41: 46072 | B41: 46273 | C41: Contacted | D41: Spanish | E41: Desiyana Perez | F41: 213080292 | G41: 801 6669792 | H41: Day Shift | I41: Mechanical Assembly | J41: WJ | K41: BL | L41: Passed | M41: Passed | N41: Passed
A42: 46072 | B42: 46273 | C42: Contacted | D42: Spanish | E42: Yeudis Palacios | F42: 186520994 | G42: 3855763264 | H42: Day Shift | I42: Mechanical Assembly | J42: WJ | K42: FZ | L42: Passed | M42: Passed | N42: Passed
A43: 46072 | B43: 46273 | C43: Contacted | D43: Spanish | E43: Betina Chica | F43: 218501372 | G43: 3852466291 | H43: Day Shift | I43: Mechanical Assembly | J43: WJ | K43: NM | L43: Pending | M43: Passed | N43: Passed | O43: Yes
A44: 46073 | B44: 46273 | C44: Contacted | D44: Spanish | E44: Marcos Lopez | F44: 218585883 | G44: 7868306940 | H44: Day Shift | I44: Mechanical Assembly | J44: WJ | K44: NM | L44: Pending | M44: Passed | N44: Passed | O44: Yes | P44: Interested as of 9/9
A45: 46073 | B45: 46273 | C45: Contacted | D45: Spanish | E45: Kendrys Semprun | F45: 218587572 | G45: 7866966897 | H45: Day Shift | I45: Mechanical Assembly | J45: WJ | K45: NM | L45: Pending | M45: Passed | N45: Passed | O45: Yes
A46: 46073 | B46: 46273 | C46: Contacted | D46: Spanish | E46: Cristina Sandkli | F46: 218657204 | G46: 3854249583 | H46: Day Shift | I46: Mechanical Assembly | J46: WJ | K46: BL | L46: Passed | M46: Passed | N46: Passed
A47: 46073 | B47: 46273 | C47: Contacted | D47: Spanish | E47: Biannimar Lopez | F47: 215268039 | G47: 7542719045 | H47: Day Shift | I47: Mechanical Assembly | J47: WJ | K47: NM | L47: Pending | M47: Passed | N47: Passed | O47: Yes
A48: 46073 | B48: 46273 | C48: Contacted | D48: Spanish | E48: Marco Lopez | F48: 218585688 | G48: 7866728865 | H48: Day Shift | I48: Mechanical Assembly | J48: WJ | K48: NM | L48: Pending | M48: Passed | N48: Passed | O48: Yes
A49: 46073 | B49: 46273 | C49: Contacted | D49: Spanish | E49: Kattlyn Rivero | F49: 217228380 | G49: 8019700664 | H49: Day Shift | I49: Mechanical Assembly | J49: WJ | K49: NM | L49: Pending | M49: Passed | N49: Passed | O49: Yes
A50: 46073 | B50: 46273 | C50: Contacted | D50: Spanish | E50: Jaime Quintero | F50: 185116206 | G50: 8013010667 | H50: Day Shift | I50: Mechanical Assembly | J50: WJ | K50: NM | L50: Pending | M50: Passed | N50: Passed | O50: Pending
A51: 46073 | B51: 46273 | C51: Contacted | D51: Spanish | E51: Alber Ramos Araque | F51: 218660210 | G51: 3854258170 | H51: Night Shift | I51: Mechanical Assembly | J51: WVC | K51: SM | L51: Passed | M51: Passed | N51: Passed
A52: 45711 | B52: 46273 | C52: Contacted | D52: English | E52: John Ankum | F52: 95709280 | G52: 3854023928 | H52: Night Shift | I52: Mechanical Assembly | J52: NSL | K52: GKW | L52: Passed | M52: Passed | N52: Passed
A53: 46076 | B53: 46274 | C53: Contacted | D53: Spanish | E53: Neibeth Landaeta Garces | F53: 182946693 | G53: 3855298717 | H53: Day Shift | I53: Mechanical Assembly | J53: WVC | K53: SM | L53: Passed | M53: Passed | N53: Passed | O53: Yes
A54: 46076 | B54: 46274 | C54: Contacted | D54: English | E54: Mickey Mangrum | F54: 213042100 | G54: 3853069752 | H54: Day Shift | I54: Mechanical Assembly | J54: WJ | K54: NM | L54: Passed | M54: Passed | N54: Passed | O54: Yes
A55: 46076 | B55: 46274 | C55: Contacted | D55: Spanish | E55: Deisy Tapia | F55: 176565636 | G55: 3855019136 | H55: Day Shift | I55: Mechanical Assembly | J55: WJ | K55: BL | L55: Passed | M55: Passed | N55: Passed
A56: 46076 | B56: 46274 | C56: Contacted | D56: Spanish | E56: Ingrid Tapias | F56: 218606642 | G56: 8014194222 | H56: Day Shift | I56: Mechanical Assembly | J56: WJ | K56: BL | L56: Passed | M56: Passed | N56: Passed
A57: 46076 | B57: 46274 | C57: Contacted | D57: Spanish | E57: Edwing Jaimes | F57: 218770546 | G57: 3855492547 | H57: Day Shift | I57: Mechanical Assembly | J57: WVC | K57: SM | L57: Passed | M57: Passed | N57: Passed
A58: 46077 | B58: 46274 | C58: Contacted | D58: Bilingual | E58: Lluvia Alvarez | F58: 95708133 | G58: (801) 836-2444 | H58: Day Shift | I58: Mechanical Assembly | J58: WJ | K58: NM | L58: Passed | M58: Passed | N58: Passed | O58: Yes
A59: 46077 | B59: 46274 | C59: Contacted | D59: Spanish | E59: Yosneiro Delgado | F59: 186513337 | G59: 3853029701 | H59: Day Shift | I59: Mechanical Assembly | J59: WJ | K59: BL | L59: Fail | M59: Passed | N59: Passed
A60: 46077 | B60: 46274 | C60: Contacted | D60: Bilingual | E60: Erik Cruceno | F60: 146917732 | G60: 8059753875 | H60: Day Shift | I60: Mechanical Assembly | J60: NSL | K60: GKW | L60: Pending | N60: Passed
A61: 46077 | B61: 46274 | C61: Contacted | D61: Spanish | E61: Yorbis Urdaneta | F61: 218032164 | G61: 8632817149 | H61: Day Shift | I61: Mechanical Assembly | J61: WJ | K61: NM | L61: Pending | M61: Passed | N61: Passed | O61: Yes
A62: 46077 | B62: 46274 | C62: Contacted | D62: English | E62: Emmanuel Ngabonziza | F62: 218406993 | G62: 3855487368 | H62: Night Shift | I62: Mechanical Assembly | J62: WJ | K62: BL | L62: Passed | M62: Passed | N62: Passed
A63: 46077 | B63: 46274 | C63: Contacted | D63: Spanish | E63: Marbelis Materan | F63: 181335195 | G63: 4355232270 | H63: Day Shift | I63: Mechanical Assembly | J63: WJ | K63: NM | L63: Pending | M63: Passed | N63: Passed | O63: Yes
A64: 46077 | B64: 46274 | C64: Contacted | D64: Spanish | E64: Yamelis Sanchez | F64: 186522873 | G64: 8017591696 | H64: Night Shift | I64: Mechanical Assembly | J64: WJ | K64: BL | L64: Passed | M64: Passed | N64: Passed
A65: 46077 | B65: 46274 | C65: Contacted | D65: Bilingual | E65: Paola Ramones | F65: 133275822 | G65: 8017933291 | H65: Day Shift | I65: Mechanical Assembly | J65: WJ | K65: NM | L65: Pending | M65: Passed | N65: Passed | O65: Yes
A66: 46078 | B66: 46274 | C66: Contacted | D66: Spanish | E66: Jesus Cortez | F66: 213746676 | G66: 3854570583 | H66: Day Shift | I66: Mechanical Assembly | J66: WJ | K66: NM | L66: Passed | M66: Passed | N66: Passed | O66: Yes
A67: 46078 | B67: 46274 | C67: Contacted | D67: Spanish | E67: Morelis Serrudo | F67: 206142461 | G67: 8016960961 | H67: Day Shift | I67: Mechanical Assembly | J67: WJ | K67: NM | L67: Passed | M67: Passed | N67: Passed | O67: Yes
A68: 46078 | B68: 46274 | C68: Contacted | D68: Bilingual | E68: Pablo Huerta | F68: 218006749 | G68: 3855564196 | H68: Day Shift | I68: Mechanical Assembly | J68: WJ | K68: NM | L68: Pending | M68: Passed | N68: Passed
A69: 46079 | B69: 46274 | C69: Contacted | D69: Spanish | E69: Juan Buscema | F69: 171283470 | G69: 6898672675 | H69: Night Shift | I69: Mechanical Assembly | J69: WJ | K69: NM | L69: Pending | M69: Passed | N69: Passed | O69: Yes
A70: 46079 | B70: 46274 | C70: Contacted | D70: Spanish | E70: Lorena Gonzalez | F70: 120500793 | G70: 3854778315 | H70: Day Shift | I70: Mechanical Assembly | J70: WJ | K70: NM | L70: Pending | M70: Passed | N70: Passed | O70: Pending
A71: 46079 | B71: 46274 | C71: Contacted | D71: Bilingual | E71: Orlando Puerto | F71: 164030615 | G71: 8015126811 | H71: Day Shift | I71: Mechanical Assembly | J71: WJ | K71: NM | L71: Pending | M71: Passed | N71: Passed | O71: Yes
A72: 46079 | B72: 46274 | C72: Contacted | D72: Bilingual | E72: Lauzud Jara-Rincon | F72: 164030478 | G72: 3856094474 | H72: Day Shift | I72: Mechanical Assembly | J72: WJ | K72: NM | L72: Pending | M72: Passed | N72: Passed | O72: Yes
A73: 46079 | B73: 46240 | C73: Contacted | D73: Spanish | E73: Maritza Coronado | F73: 133590433 | G73: 3853136333 | H73: Day Shift | I73: Mechanical Assembly | J73: WJ | K73: BL | L73: Passed | M73: Passed | N73: Passed
A74: 46079 | B74: 46240 | C74: Contacted | D74: English | E74: Howard Aliu | F74: 218481839 | G74: +1 801-634-6157 | H74: Day Shift | I74: Mechanical Assembly | J74: WJ | K74: BL | L74: Passed | M74: Passed | N74: Passed
A75: 46079 | B75: 46240 | C75: Contacted | D75: Spanish | E75: Nathaly Ruiz | F75: 136688729 | G75: 3853369610 | H75: Day Shift | I75: Mechanical Assembly | J75: WJ | K75: BL | L75: Passed | M75: Passed | N75: Passed
A76: 46079 | B76: 46240 | C76: Contacted | D76: Spanish | E76: Karla Soto | F76: 206138560 | G76: 3858813622 | H76: Night Shift | I76: Mechanical Assembly | J76: WJ | K76: FZ | L76: Passed | M76: Passed | N76: Passed
A77: 46075 | B77: 46240 | C77: Contacted | D77: Bilingual | E77: JoseGGalvan | F77: 185956584 | G77: 801 577-0289 | H77: Day Shift | I77: Mechanical Assembly | J77: WVC | K77: SM | L77: Fail | M77: Passed | N77: Passed
A78: 46079 | B78: 46240 | C78: Contacted | D78: Spanish | E78: Rosana Celis | F78: 169029421 | G78: 8014033680 | H78: Day Shift | I78: Mechanical Assembly | J78: WJ | K78: NM | L78: Pending | M78: Passed | N78: Passed
A79: 46080 | B79: 46240 | C79: Contacted | D79: Spanish | E79: Keila Marquez | F79: 142562828 | G79: 3855561925 | H79: Day Shift | I79: Mechanical Assembly | J79: WJ | K79: NM | L79: Pending | M79: Passed | N79: Passed | O79: Pending
A80: 46080 | B80: 46240 | C80: Contacted | D80: English | E80: Jaiden Lehmann | F80: 198492220 | G80: 385 900 3037 | H80: Day Shift | I80: Mechanical Assembly | J80: WJ | K80: NM | L80: Pending | M80: Passed | N80: Passed | O80: Yes
A81: 46080 | B81: 46240 | C81: Contacted | D81: Spanish | E81: Javier Biegas | F81: 218757146 | G81: 3859003037 | H81: Day Shift | I81: Mechanical Assembly | J81: WJ | K81: NM | L81: Passed | M81: Passed | N81: Passed | O81: Pending
A82: 46080 | B82: 46240 | C82: Contacted | D82: Spanish | E82: Silvia Jimenez | F82: 217223012 | G82: 8017160791 | H82: Day Shift | I82: Mechanical Assembly | J82: WJ | K82: BL | L82: Passed | M82: Passed | N82: Passed
A83: 46080 | B83: 46240 | C83: Contacted | D83: Spanish | E83: Hazel Luna | F83: 218869784 | G83: 435 339 4282 | H83: Day Shift | I83: Mechanical Assembly | J83: WJ | K83: BL | L83: Passed | M83: Passed | N83: Passed
A84: 46080 | B84: 46240 | C84: Contacted | D84: English | E84: Amanda Luckey | F84: 215264805 | G84: 8439398617 | H84: Night Shift | I84: Mechanical Assembly | J84: WVC | K84: SM | L84: Pending | M84: Passed | N84: Passed
A85: 46080 | B85: 46240 | C85: Contacted | D85: Spanish | E85: Leny Chacon | F85: 218852536 | G85: 3855361528 | H85: Day Shift | I85: Mechanical Assembly | J85: WJ | K85: BL | L85: Passed | M85: Passed | N85: Passed
A86: 46080 | B86: 46240 | C86: Contacted | D86: Spanish | E86: Fabiola Celedon | F86: 218869828 | G86: 8015488836 | H86: Day Shift | I86: Mechanical Assembly | J86: WJ | K86: NM | L86: Pending | M86: Passed | N86: Passed | O86: Yes
A87: 46083 | B87: 46240 | C87: Contacted | D87: Spanish | E87: Elimar Moreno | F87: 199399153 | G87: 3854575055 | H87: Day Shift | I87: Mechanical Assembly | J87: WJ | K87: NM | L87: Pending | M87: Passed | N87: Passed | O87: Yes
A88: 46083 | B88: 46240 | C88: Contacted | D88: Spanish | E88: Nidia Medina | F88: 182053872 | G88: 3853127782 | H88: Day Shift | I88: Mechanical Assembly | J88: WJ | K88: NM | L88: Pending | M88: Passed | N88: Passed | O88: Yes
A89: 46083 | B89: 46240 | C89: Contacted | D89: Spanish | E89: Genesis Uribe | F89: 217304054 | G89: 8014730897 | H89: Day Shift | I89: Mechanical Assembly | J89: WJ | K89: NM | L89: Pending | M89: Passed | N89: Passed | O89: Yes
A90: 46083 | B90: 46240 | C90: Contacted | D90: Spanish | E90: Heriangel Herrera | F90: 198168768 | G90: 3855070846 | H90: Day Shift | I90: Mechanical Assembly | J90: WJ | K90: BL | L90: Passed | M90: Passed | N90: Passed
A91: 46083 | B91: 46240 | C91: Contacted | D91: Spanish | E91: j | F91: 206201257 | G91: 8014047296 | H91: Day Shift | I91: Mechanical Assembly | J91: WJ | K91: BL | L91: Passed | M91: Passed | N91: Passed
A92: 46084 | B92: 46240 | C92: Contacted | D92: Spanish | E92: Daniela Duarte | F92: 218898855 | G92: +1 385 556-4112 | H92: Day Shift | I92: Mechanical Assembly | J92: WJ | K92: BL | L92: Passed | M92: Passed | N92: Passed
A93: 46084 | B93: 46240 | C93: Contacted | D93: Spanish | E93: Miguel Balabu | F93: 213056878 | G93: 8017353173 | H93: Night Shift | I93: Mechanical Assembly | J93: WJ | K93: NM | L93: Pending | M93: Passed | N93: Passed | O93: Yes
A94: 46084 | B94: 46240 | C94: Contacted | D94: Spanish | E94: Rafael Valbuena | F94: 198515355 | G94: 3855285890 | H94: Night Shift | I94: Mechanical Assembly | J94: WJ | K94: NM | L94: Pending | M94: Passed | N94: Passed | O94: Yes
A95: 46084 | B95: 46240 | C95: Contacted | D95: Spanish | E95: Juan Oliveros | F95: 199505841 | G95: 8013859554 | H95: Night Shift | I95: Mechanical Assembly | J95: WJ | K95: BL | L95: Passed | M95: Passed | N95: Passed
A96: 46084 | B96: 46240 | C96: Contacted | D96: Spanish | E96: Jefferson Suarez | F96: 218791551 | G96: 9014314176 | H96: Day Shift | I96: Mechanical Assembly | J96: WJ | K96: NM | L96: Pending | M96: Passed | N96: Passed | O96: Yes
A97: 46084 | B97: 46240 | C97: Contacted | D97: Spanish | E97: Johana Suarez | F97: 189857069 | G97: 5167260509 | H97: Day Shift | I97: Mechanical Assembly | J97: WJ | K97: NM | L97: Pending | M97: Passed | N97: Passed | O97: Yes
A98: 46084 | B98: 46240 | C98: Contacted | D98: Bilingual | E98: Erika Vargas | F98: 164911705 | G98: 3854199021 | H98: Day Shift | I98: Mechanical Assembly | J98: WVC | K98: SM | L98: Passed | M98: Passed | N98: Passed
A99: 46084 | B99: 46240 | C99: Contacted | D99: Spanish | E99: Angel Escalona | F99: 199714790 | G99: 3855789466 | H99: Day Shift | I99: Mechanical Assembly | J99: WJ | K99: NM | L99: Passed | M99: Passed | N99: Passed | O99: Yes
A100: 46084 | B100: 46240 | C100: Contacted | D100: Spanish | E100: Yajaira Flores | F100: 219021559 | G100: 3854470255 | H100: Day Shift | I100: Mechanical Assembly | J100: WJ | K100: FZ | L100: Passed | M100: Passed | N100: Passed
...

Sheet Mini Orientation
A1: Thursday 8/6/26 @ 4pm | B1: DO NOT ADD EXTRA ROWS!!!!!!!! | C1: SPANISH ONLY | D1: NO MORE THAN 20 PER CLASS
A2: SSN # | B2: Employe Name Must Match Avionte | C2: Bold ID | D2: Phone | E2: Recruiter | F2: Shift Pref | G2: Arrived | H2: Placed | I2: Notes
B3: Massiel Zabala | C3: 112007733 | D3: 801-564-0825 | E3: BL | F3: Days | G3: Yes | I3: C-shift
A4: 892-08-6999 | B4: Jesus Antonio Villareal Blanco | C4: 115655543 | D4: (385) 242-0947 | E4: FZ | F4: Nights | G4: No
B5: Andres Caruci | C5: 226544093 | D5: 3038886330 | E5: BL | F5: Days | G5: Yes | I5: C-shift
B6: Maribeth Castillo | C6: 190427449 | D6: 2678893261 | E6: DR | F6: Days | G6: Yes | I6: C- Shift (mechanical Assembly)
B7: Gabriella Martinez | C7: 95676314 | D7: (801) 815-5063 | E7: DR | F7: Days | G7: Yes
A8: 721-67-3496 | B8: Jhoseiny Gonzalez | C8: 209195517 | D8: 3852821517 | E8: NM | F8: Nights | G8: Yes | H8: Yes
A9: 122-77-9660 | B9: Jossellyne Orellana | C9: 115744726 | D9: 3474758685 | E9: NM | F9: Days | G9: Yes
A11: 288-45-9300 | B11: Richard Rios | C11: 146966394 | D11: 3855569276 | E11: FZ | F11: Days | G11: Yes
A12: 065-21-3194 | B12: Julio Perez Olivar | C12: 139298190 | D12: 801-903-0227 | E12: RP | F12: Days | G12: Yes | I12: C-Shift (Warehouse)
A13: 647-98-4023 | B13: Ilia A Romero | C13: 228805148 | D13: 3853026775 | E13: FZ | F13: Days | G13: Late
A20: Friday 8/7/26 @ 4pm | B20: DO NOT ADD EXTRA ROWS!!!!!!!! | C20: SPANISH ONLY | D20: NO MORE THAN 20 PER CLASS
A21: SSN # | B21: Employe Name Must Match Avionte | C21: Bold ID | D21: Phone | E21: Recruiter | F21: Shift Pref | G21: Arrived | H21: Placed | I21: Notes
A22: 022-13-1925 | B22: Teresa Hernandez Navarro | C22: 121712371 | D22: 8018153036 | E22: GKW | F22: Days | G22: Yes
B23: Alicia S Ruiz | C23: 217675488 | D23: 3855482730 | E23: NM | F23: Days | G23: Yes
A24: 647-76-9145 | B24: Ali M Osman | C24: 95659911 | D24: (801) 953-7958 | E24: GKW | F24: Days | I24: Rescheduled to Wed
A25: 647-98-4023 | B25: Ilia A Romero | C25: 228805148 | D25: 3853026775 | E25: FZ | F25: Days | G25: Yes
B26: Kahirys Maria Melendez | C26: 120736470 | D26: 3854362422 | E26: NM | F26: Days | G26: Yes
A27: 172-02-3958 | B27: Anais Faria | C27: 227227008 | D27: 3854183056 | E27: FZ | F27: Days | G27: Yes
B28: Eubbeidys E Gonzalez | C28: 224736795 | D28: 9294971616 | E28: NM | F28: Days | G28: Yes
B29: Maria Reyes | C29: 225305567 | D29: 3465463544 | E29: NM | F29: Days | G29: Yes
A30: 136-85-9076 | B30: Nayvir Medina | C30: 230183012 | D30: 385 424 2946 | E30: NM | F30: Days | G30: Yes
A31: 670-50-3472 | B31: Estersi Cacciatore | C31: 229512238 | D31: 8019704852 | E31: BL | F31: Days
B32: Brandon Gonzalez | I32: A shift preferably
A33: 388-71-5477 | B33: Valeria Sandoval | C33: 215128480 | D33: 5598714822 | E33: EP | F33: Nights | G33: Yes
B34: Rocio Rodriguez | C34: 199432485 | D34: +1 385 405 5400 | E34: CN | F34: Days | G34: Yes
A35: 318-95-5312 | B35: Gabriela Aguilar | C35: 230399050 | D35: 3855089565 | E35: NM | F35: Days | G35: Yes
B36: Juan Pablo Saenz | C36: 230400373 | D36: 8016046577 | E36: BL | F36: Days
B37: Ivan Diego Chirinos | C37: 230400380 | D37: 3854348866 | E37: BL | F37: Days
B38: Andris Camargo | C38: 230208470 | D38: 8015741147 | E38: NM | F38: Days | G38: Yes
B39: Ybyairy Leon | C39: 145002751 | D39: 3853387095 | E39: NM | F39: Days | G39: Yes
B40: Karianna Melendez | C40: 230401816 | D40: 8016349052 | E40: NM | F40: Days | G40: Yes
A41: 646-82-3613 | B41: Brandon Gonzalez | C41: 228896924 | D41: 385 418 7532 | E41: NM | F41: Nights
B42: Jorge Valdez | C42: 95682428 | D42: (386) 643-9100 | E42: FZ | F42: Days | I42: C shift
A43: Saturday 8/8/26 @ 4pm | B43: DO NOT ADD EXTRA ROWS!!!!!!!! | C43: SPANISH ONLY | D43: NO MORE THAN 20 PER CLASS
A44: SSN # | B44: Employe Name Must Match Avionte | C44: Bold ID | D44: Phone | E44: Recruiter | F44: Shift Pref | G44: Arrived | H44: Placed | I44: Notes
A45: 204734859 | B45: Johny Kourkounian | C45: 223463547 | D45: 8013478780 | E45: JM | F45: Days
A46: 820038147 | B46: Claudia La Rosa Quispe | C46: 185852924 | D46: 3854794854 | E46: JY | F46: B | I46: B Shift
A47: 354-23-8705 | B47: Alejandra C Valdez | C47: 114717224 | D47: 3852967913 | E47: FZ | F47: A | I47: A shift
A48: 818-69-9321 | B48: Renso Bastardo | C48: 112487887 | D48: 3852967573 | E48: FZ | F48: A | I48: A shift
A49: 730120557 | B49: Joddy Bastidas | C49: 230402628 | D49: 3474458703 | E49: HB | F49: Days
B50: Wisleidi Gomez | C50: 176555735 | D50: 8014144233 | E50: CN | F50: Days
B51: Nestor Lopez Carrion | C51: 222929727 | D51: 3853782924 | E51: NM | F51: Days
B52: Sandra Aguilar | C52: 222930709 | D52: 3854857934 | E52: NM | F52: Days
B53: Sergio Alejandro Pinzon | C53: 225938848 | D53: 3856300714 | E53: EP | F53: A | I53: A shift
B54: Urdaneta Miyelis | C54: 142410292 | D54: 3854867281 | E54: EP | F54: A | I54: A shift
B55: Jose Pinzon Barriga | C55: 146845543 | D55: 3856300378 | E55: EP | F55: A | I55: A shift
B56: Lady Valderrama | E56: NM | F56: Nights
B57: Adriana Gonzalez | E57: NM | F57: Days
B58: Dilianny Delse | E58: NM | F58: Days
B59: Santiago Guerrero | E59: NM | F59: A | I59: A shift
B60: Irene Guerrero | E60: NM | F60: A | I60: A shift
B61: Miyelis D Urdaneta | D61: 3854867281 | E61: CN | F61: Days
B62: Oscar Mendoza | C62: 1.9006902e+17 | D62: 3853107722 | E62: DR | F62: Nights
B63: Juan Pablo Saenz | C63: 230400373 | D63: 8016046577 | E63: BL | F63: Days
B64: Ivan Diego Chirinos | C64: 230400380 | D64: 3854348866 | E64: BL | F64: Days
A65: Tuesday 8/11/26 @ 4pm | B65: DO NOT ADD EXTRA ROWS!!!!!!!! | C65: SPANISH ONLY | D65: NO MORE THAN 20 PER CLASS
A66: SSN # | B66: Employe Name Must Match Avionte | C66: Bold ID | D66: Phone | E66: Recruiter | F66: Shift Pref | G66: Arrived | H66: Placed | I66: Notes
A67: 022-13-1925 | B67: Teresa Hernandez Navarro | C67: 121712371 | D67: 8018153036 | E67: GKW | F67: Days
A68: 733036301 | B68: Whang C Walters | C68: 226997062 | D68: 3852662386 | E68: HB | F68: Nights
B69: Brandon Gonzalez | C69: 22889624 | D69: 3854187532 | E69: EP | F69: A | G69: Yes | I69: A - shift Bilingual
A70: 102493872 | B70: Jenny Arbelaez | C70: 222806603 | D70: 8016498875 | E70: JM | F70: Nights
A71: 629758313 | B71: Yanet Oscanoa | C71: 122873279 | D71: 8014037247 | E71: rp | F71: D | I71: D-shift
B72: Ramona Hernandez | C72: 110697383 | D72: 3858673038 | E72: DR | F72: A | G72: Yes | I72: A-shift
B73: Amayrany Hernandez | C73: 198303055 | D73: 3855410937 | E73: DR | F73: Days
B74: Acacely Hernandez Garcia | C74: 198318924 | D74: 4357141187 | E74: DR | F74: Days
B75: Daniela A Rosales Coronado | C75: 230405645 | D75: 8015021788 | E75: JY | F75: Days | G75: Yes
A76: 350633793 | B76: Albenis Gabriel Lopez | C76: 137450108 | D76: 9412416209 | E76: RP | F76: Nights | G76: Yes
B77: Mariangel N Bastidas Rangel | C77: 118877490 | D77: 3854573759 | E77: JY | F77: Days | G77: Yes
A78: 728-44-4200 | B78: Luz Polanco | C78: 220548977 | D78: 8016349542 | E78: BL | F78: Days | G78: Yes | I78: A-shift
B79: Chirly Hernandez | C79: 193735754 | D79: 3853541243 | E79: DR | F79: Days | G79: Yes
A80: 651-92-6411 | B80: Willy Alvarez | C80: 182813001 | D80: 8014140597 | E80: NM | F80: Days | G80: Yes | I80: A-shift
B81: Olvia Hernandez | C81: 167418299 | D81: 3859779848 | E81: DR | F81: Days | G81: Yes
B82: Edwin Lizardo | C82: 147965238 | D82: 8018336023 | E82: DR | F82: Days | G82: Yes
A83: 875-91-3332 | B83: Yuli Jimenez | C83: 230554382 | D83: 3847890329 | E83: NM | F83: Nights | G83: Yes
A84: 743-48-5767 | B84: Maria Elena Camarillo Alvarado | C84: 182863558 | D84: 3852239443 | E84: FZ | F84: Days | G84: Yes
B85: Fernando Razuri | C85: 205051457 | D85: 8189165469 | E85: NM | F85: Days
A86: 818165068 | B86: Rubeizy A Dominguez Miranda | C86: 228685650 | D86: 3857753267 | E86: HB | F86: Nights | G86: Yes
A87: 149893674 | B87: Oswaldo Quintero | C87: 230557237 | D87: 3855233259 | E87: JM | F87: Nights | G87: Yes
A88: Tuesday 8/11/26 @ 1pm | B88: DO NOT ADD EXTRA ROWS!!!!!!!! | C88: English/Bilingual | D88: NO MORE THAN 20 PER CLASS
A89: SSN # | B89: Employe Name Must Match Avionte | C89: Bold ID | D89: Phone | E89: Recruiter | F89: Shift Pref | G89: Arrived | H89: Placed | I89: Notes
A90: 647987139 | B90: Joseph R Hurtado | C90: 227754054 | D90: 8014034364 | E90: JY | F90: Days | G90: Yes | I90: A shift
A91: 835296844 | B91: Willian Piccone | C91: 217233983 | D91: 3853541676 | E91: RP | F91: Days | I91: late
B92: Dao Cao | C92: 201701566 | D92: 3854445090 | E92: DR | F92: Nights | G92: Yes | I92: B shift
B93: Thavone Noavongsak | C93: 177934156 | D93: 801-680-7310 | E93: DR | F93: Nights | G93: Yes
B94: Lucas Norris | C94: 225274848 | D94: +1 435 277-9202 | E94: DR | F94: Nights | G94: Yes
A95: 646-56-2851 | B95: Eliud Vargas | C95: 230549728 | D95: 3854999817 | E95: NM | F95: Nights | G95: Yes
A96: 528-49-7146 | B96: Chad Cadland | C96: 167453188 | D96: 8015746280 | E96: NM | F96: Nights | G96: Yes
A97: 863-17-9098 | B97: Santos E Rodriguez Torres | C97: 95711490 | D97: 8019413095 | E97: FZ | F97: Days
A98: 647-76-9145 | B98: Ali M Osman | C98: 95659911 | D98: (801) 953-7958 | E98: GKW | F98: Days | G98: Late
B99: Fernando Razuri | C99: 205051457 | D99: 8189165469 | E99: BL | F99: Days | G99: Yes | I99: Can start 8/20. Came late on the 13th.
A100: 093-49-5184 | B100: Diego Garcia | C100: 155276815 | D100: 8018670654 | E100: FZ | F100: Days | G100: Yes | I100: A - shift
A101: 278-47-0771 | B101: Karel Mota | C101: 225339373 | D101: 3852522735 | E101: BL | F101: Days
A102: 575-93-5629 | B102: Telmer Emos | C102: 95673500 | D102: 385 432 9812 | E102: GKW | F102: Nights | I102: Out of town this weekend (8/15)
A103: 528-61-6777 | B103: Molonai Muamoholeva | C103: 227168732 | D103: 385 210-6656 | E103: GKW | F103: Nights | G103: Yes
A104: 575-89-6601 | B104: Saloula Siliva | C104: 230202685 | D104: 3853369802 | E104: JM | F104: Days | G104: Yes | I104: Needs bg ran
B105: Jesse Ren | C105: 119451955 | D105: 8019000047 | E105: NM | F105: Nights
B106: Aidan Perez | C106: 228927969 | D106: 2816704894 | E106: BL | F106: Days | G106: Yes | I106: C-shift cold room. completed everything.
B107: Jameson Lomax | C107: 95649182 | D107: 3852663176 | E107: RP | F107: Nights | G107: Yes | I107: D shift
...

Sheet Orientations Old
B1: Tuesday 7/29/25 @2pm | C1: SPANISH | D1: NO MORE THAN 20 | F1: Nights | G1: Arrived | H1: Offer | I1: Notes - A Roster or B Roster (A = English/Bilingual and 1+ year exp) (B = Spanish and no exp.)
B2: Employe Name | C2: Employee # | D2: Phone | E2: Recruiter | F2: Shift Pref
B3: Joraima Soto | C3: 186324826 | D3: 3854904410 | E3: FZ | F3: Materials | G3: Yes | H3: Yes
B4: Maria Rodriguez | C4: 176583998 | D4: (385) 280-6295 | E4: DG | F4: A/C (Day) | G4: Yes | H4: Yes
B5: Fatima Briceno | C5: 187997721 | D5: 8019150994 | E5: NM | F5: B/D (Night | G5: Yes | H5: Yes
B6: Anyela Blanco | C6: 190324150 | D6: 8013309103 | E6: NM | F6: B/D (Night | G6: Yes | H6: Yes
B7: Leomaris Guzman | C7: 194816575 | D7: 3854361573 | E7: NM | F7: B/D (Night | G7: Yes | H7: Yes
B8: Badrolilia Peraza | C8: 101885257 | D8: 8014256308 | E8: NM | F8: B/D (Night | G8: Yes | H8: no | I8: Unable to contact
B9: Jonathan Arellanes | C9: 194528743 | D9: 3854238506 | E9: NM | F9: B/D (Night | G9: No
B10: Tairy Angulo | C10: 181369439 | D10: 3855065808 | E10: NM | F10: A/C (Day) | G10: Yes | H10: Yes
B11: Neis Pirela | C11: 176962718 | D11: 8012054460 | E11: NM | F11: A/C (Day) | G11: Yes | H11: Yes
B12: SimonRomero | C12: 117084972 | D12: 3852273302 | E12: DG | F12: A/C (Day) | G12: Yes | H12: Yes
B13: Lilibeth Roman | C13: 168124100 | D13: 3852295061 | E13: NM | F13: B/D (Night | G13: yes | H13: Yes
B14: Luis Garcia | C14: 194760398 | D14: 3853147960 | E14: NM | F14: A/C (Day) | G14: Rescheduled | I14: 7 mins late
B15: Romer Magdaniel | C15: 146674951 | D15: 9294247309 | E15: NM | F15: A/C (Day) | G15: yes | H15: Yes
B16: Enyaj Garcia | C16: 193856840 | D16: 8018094198 | E16: NM | F16: A/C (Day) | G16: yes | H16: Yes
B17: Yarelis Delgado | C17: 194501314 | D17: 3462439741 | E17: NM | F17: A/C (Day) | G17: yes | H17: Yes
B18: Jarol Martinez | C18: 193852264 | D18: 8016349786 | E18: FZ | F18: B/D (Night | G18: yes | H18: Yes
B19: Yorleny Luna | C19: 197892151 | D19: 3855735944 | E19: NM | F19: B/D (Night | G19: yes | H19: Yes
B20: Javier Calderon | C20: 193880878 | D20: 8013817589 | E20: BL | F20: A/C (Day) | G20: yes | H20: Yes
B21: Leticia Lopez | C21: 197900170 | D21: 385 484 2641 | E21: DG | F21: A/C (Day) | G21: yes | H21: No | I21: Not enough english
B22: Alma Hernandez | C22: 193852260 | D22: 8018757583 | E22: NM | F22: A/C (Day) | G22: yes | H22: Yes
B23: Joel Martinez | C23: 186524512 | D23: 3854908227 | E23: NM | F23: B/D (Night | G23: yes | H23: Yes
B24: Marvin Delgado | C24: 186627342 | D24: 3854566241 | E24: NM | F24: B/D (Night | G24: yes | H24: Yes
B25: Wednesday 7/30/25 @1 pm | C25: SPANISH | D25: NO MORE THAN 20 | G25: Arrived | H25: Offer | I25: Notes - A Roster or B Roster (A = English/Bilingual and 1+ year exp) (B = Spanish and no exp.)
B26: Employe Name | C26: Employee # | D26: Phone | E26: Recruiter | F26: Shift Pref
B27: Maira Querales | C27: 152806550 | D27: 3856958686 | E27: NM | F27: A/C (Day) | G27: yes | H27: Yes | I27: B
B28: Maria Martinez | C28: 198091228 | D28: 4698940779 | E28: DG | F28: B/D (Night | G28: yes | H28: Yes
B29: William Marrufo | C29: 198091268 | D29: 8016445290 | E29: DG | F29: B/D (Night | G29: yes | H29: Yes
B30: Liduvina Aguilera | C30: 194519751 | D30: 3854650569 | E30: FZ | F30: A/C (Day) | G30: yes | H30: Yes
B31: Maria Lorena Mendez | C31: 194519834 | D31: 3854650569 | E31: FZ | F31: A/C (Day) | G31: yes | H31: Yes
B32: Erwin Pinzon | C32: 198098739 | D32: 3852859222 | E32: NM | F32: A/C (Day) | G32: yes | H32: No | I32: B unable to contact
B33: Ana Rivero | C33: 198038100 | D33: 7578312339 | E33: DG | F33: A/C (Day) | G33: yes | H33: Yes
B34: Liz Ascencio | C34: 177677124 | D34: 8012055313 | E34: CE | F34: A/C (Day) | G34: yes | H34: Yes
B35: Priscilla Salgado | C35: 198119474 | D35: 3852680226 | E35: DG | F35: B/D (Night
B36: Alexander Molina | C36: 198115158 | D36: 3853145049 | E36: FZ | F36: A/C (Day) | G36: yes | H36: Yes | I36: B
B37: Joselyn Rivas | C37: 177664785 | D37: 3852165535 | E37: FZ | F37: A/C (Day) | G37: yes | H37: No | I37: B
B38: Porfirio Magana Diaz | C38: 95708871 | D38: (801) 935-7631 | E38: FZ | F38: A/C (Day) | G38: yes | H38: Yes | I38: A
B39: Sharedt Alfaro | C39: 198119624 | D39: 9145254472 | E39: NM | F39: B/D (Night | G39: yes | H39: Yes
B40: Oscar Sanchez | C40: 198085680 | D40: 8017555395 | E40: BL | F40: B/D (Night | G40: yes | H40: Yes | I40: B
B41: William Cruz | C41: 198085671 | D41: 3855199552 | E41: BL | F41: B/D (Night | G41: yes
B42: Miguel Valera | C42: 160748288 | D42: 9514199934 | E42: DG | F42: B/D (Night | G42: yes
B43: Rubelia Ramirez | C43: 182061710 | D43: 3856229075 | E43: NM | F43: A/C (Day) | G43: yes
B44: Daniela Campos | C44: 180373513 | D44: 3855805959 | E44: DG | F44: B/D (Night | G44: yes | H44: Yes
B45: Jorge Arenales | C45: 190032407 | D45: 3857462807 | E45: NM | F45: B/D (Night | G45: yes | H45: Yes | I45: B
B46: Jamilton Infante | C46: 198046933 | D46: 8014035358 | E46: DG | F46: B/D (Night | G46: yes | H46: Yes
B47: Luis Garcia | C47: 194760398 | D47: 3853147960 | E47: NM | F47: A/C (Day) | G47: yes | H47: Yes | I47: B
B48: Wednesday 7/30/25 2pm | C48: ENGLISH
B49: Employe Name | C49: Employee # | D49: Phone | E49: Recruiter | F49: Shift Pref | G49: Arrived | H49: Offer | I49: Notes
B50: Changchi Hsu | C50: 100303209 | D50: 3855569079 | E50: DR | F50: B/D (Night | G50: No | H50: No
B51: Jean de Dieu Bonane | C51: 95684520 | D51: 801 462 9752 | E51: EW | F51: A/C (Day) | G51: No | H51: No | I51: rescheduled
B52: Elizabeth Ocaranza | C52: 186523967 | D52: 8016381015 | E52: CE | F52: A/C (Day) | G52: Yes | H52: Yes
B53: Jennifer Leon | C53: 95620738 | D53: 6196493412 | E53: CE | F53: A/C (Day) | G53: Yes | H53: YEs | I53: A
B54: Estefanie Nolasco | C54: 95620925 | D54: 6195913177 | E54: CE | F54: A/C (Day) | G54: Yes | H54: No
B55: Yohanna Goss | C55: 137909958 | D55: 513878477 | E55: GKW | F55: A/C (Day) | G55: Yes | H55: No | I55: A Not interested
B56: Sarah Makuach | C56: 198024130 | D56: 801 859 6217 | E56: NM | F56: B/D (Night | G56: Yes | H56: Yes | I56: A
B57: Racheal Atem | C57: 194769517 | D57: 8018143783 | E57: NM | F57: B/D (Night | G57: Yes | I57: A
B58: Josue Hernandez Pacheco | C58: 198010479 | D58: 801-430-6940 | E58: SR | F58: B/D (Night | G58: Yes | H58: Yes
B59: Alex Martinez | C59: 194484159 | D59: +1 408 612 2093 | E59: BL | F59: A/C (Day) | G59: No | H59: no | I59: Canceled - not interested
B60: Jesus Avila | C60: 188004500 | D60: 3852531583 | E60: FZ | F60: B/D (Night | G60: Yes | H60: Yes | I60: A
B61: Nazaire Nsanzimana | C61: 194834882 | D61: 3854159274 | E61: GKW | F61: A/C (Day) | G61: Yes | H61: Yes | I61: A
B62: Jordan Jensen | C62: 194817607 | D62: 8016080266 | E62: BL | F62: A/C (Day) | G62: No | H62: no
B63: Alexandra Silva | C63: 133250817 | D63: 801 941 4042 | E63: NM | F63: A/C (Day) | G63: Yes | H63: No | I63: Was unable to contact
B64: Arianna Ewell | C64: 102139980 | D64: 385-313-2200 | E64: GKW | F64: A/C (Day) | G64: Yes | H64: Yes | I64: A
B65: Noah Brown | C65: 194590577 | D65: +1 801 674-5345 | E65: BL | F65: A/C (Day) | G65: Yes | H65: No | I65: Other work
B66: Elizabeth Malespin | C66: 146827454 | D66: 8016916642 | E66: CE | F66: A/C (Day) | G66: Yes | H66: Yes
B68: THURSDAY 7/31/25 @2pm | C68: SPANISH | D68: NO MORE THAN 20 | G68: Arrived | H68: Offer | I68: Notes - A Roster or B Roster (A = English/Bilingual and 1+ year exp) (B = Spanish and no exp.)
B69: Employe Name | C69: Employee # | D69: Phone | E69: Recruiter | F69: Shift Pref
B70: Jhlonny Herman | C70: 134345849 | D70: 385-227-4448 | E70: NM | F70: B/D (Night | G70: Yes | H70: Yes
B71: Naileth Ortiz | C71: 172194973 | D71: 8014030974 | E71: NM | F71: B/D (Night | G71: Yes | H71: Yes
B72: Juan Tovar | C72: 198023747 | D72: 3855987482 | E72: DR | F72: B/D (Night | G72: No | H72: no
B73: Jamilton Infante | C73: 198046933 | D73: 8014035358 | E73: DG | F73: B/D (Night | G73: No | H73: no
B74: Elizabeth Malespin | C74: 146827454 | D74: 8016916642 | E74: CE | F74: A/C (Day) | G74: Yes | H74: yes
B75: Sandy Mera | C75: 198059304 | D75: 3857753555 | E75: DG | F75: B/D (Night | G75: Yes | H75: Yes
B76: Yhon Lobo | C76: 188005074 | D76: 3855410272 | E76: BL | F76: B/D (Night | G76: Yes | H76: Yes
B77: Ana Saucedo | C77: 115286455 | D77: 3076771941 | E77: FZ | F77: A/C (Day) | G77: Yes | H77: No | I77: A
B78: Angelica Fajardo | C78: 161355464 | D78: 161355464 | E78: FZ | F78: A/C (Day) | G78: Yes | H78: No | I78: B
B79: Juan Ferrer | C79: 198100593 | D79: 8015094077 | E79: NM | F79: B/D (Night | G79: No | H79: no
B80: Massiel Zabala | C80: 112007733 | D80: 4078135547 | E80: FZ | F80: A/C (Day) | G80: Yes | H80: Yes | I80: B Unable to contact. no working #
B81: Silvia Gavidia | C81: 197902597 | D81: 8015580472 | E81: DG | F81: A/C (Day) | G81: Yes | H81: Yes
B82: Carlos faria | C82: 160716568 | D82: 3855831907 | E82: BL | F82: A/C (Day) | G82: No | H82: no
B83: Genie Diaz | C83: 197902590 | D83: 8018641915 | E83: CE | F83: B/D (Night | G83: No | H83: no
B84: Kelly Maldonado | C84: 198143623 | D84: 3474443908 | E84: BL | F84: B/D (Night | G84: Yes | H84: Yes
B85: Juan Gomez | C85: 133848992 | D85: (801) 661-7329 | E85: BL | F85: A/C (Day) | G85: Yes | H85: No | I85: B unable to contact
B86: Juan Ferrer | C86: 198100593 | D86: 8015094077 | E86: NM | F86: B/D (Night | G86: Yes | H86: Yes
B87: Gabriela Arrieta | C87: 95666006 | D87: 3852689033 | E87: NM | F87: A/C (Day) | G87: Yes | H87: Yes
B88: Lisbeth Montanez | C88: 198115176 | D88: 3854618303 | E88: CE | F88: B/D (Night | G88: yes | H88: Yes
B89: Jessica Serna | C89: 145758103 | D89: 3852964715 | E89: NM | F89: B/D (Night | G89: yes
B91: Monday 8/04/25 @2pm | C91: SPANISH | D91: NO MORE THAN 20 | G91: Arrived | H91: Offer | I91: Notes - A Roster or B Roster (A = English/Bilingual and 1+ year exp) (B = Spanish and no exp.)
B92: Employe Name | C92: Employee # | D92: Phone | E92: Recruiter | F92: Shift Pref
B93: Jorge Cantos | C93: 198127607 | D93: 3856229777 | E93: NM | F93: B/D (Night | G93: Yes | H93: Yes
B94: Greykely Calderon | C94: 149727452 | D94: 3856229781 | E94: NM | F94: B/D (Night | G94: Yes | H94: Yes
B95: Kevin Gutierrez | C95: 198148107 | D95: 8014338440 | E95: FZ | F95: A/C (Day) | G95: Yes
B96: Millangelis Salazar | C96: 197829347 | D96: 801-403-4293 | E96: BL | F96: A/C (Day) | G96: Yes | H96: Yes
B97: Mariela Cespedes | C97: 198047354 | D97: 385-461-8051 | E97: BL | F97: A/C (Day) | G97: Yes
B98: Luz Bedoya | C98: 198126205 | D98: 3854903571 | E98: BL | F98: A/C (Day) | G98: Yes | H98: Yes
B99: Jose Antonio Morales | C99: 194612385 | D99: 3854187901 | E99: DR | F99: A/C (Day) | G99: Yes | H99: Yes
B100: Genesis Rodriguez | C100: 194612391 | D100: 3854187898 | E100: DR | F100: A/C (Day) | G100: Yes | H100: Yes
B101: Yormen Rubiano | C101: 129912902 | D101: 3238678685 | E101: DR | F101: B/D (Night | G101: Yes
B102: Sonia Bastidas | C102: 119672550 | D102: 3854180123 | E102: NM | F102: A/C (Day) | G102: Yes | H102: Yes
...

Sheet Hired
A1: Date | B1: Last Contacted | C1: Status | D1: Language | E1: Employee Name (must match Avionte) | F1: Talent ID | G1: Phone | H1: Shift Preference | I1: Position | J1: Office | K1: Recruiter | L1: BG? | M1: DT? | N1: FLEX Doc Sent | O1: Attended Mini Orientation | P1: Notes
A2: 46128 | D2: Spanish | E2: Joanna Munoz | F2: 216559414 | G2: 3854439875 | H2: Night Shift | I2: Mechanical Assembly | J2: WVC | K2: JY | L2: Passed | M2: Passed | N2: Passed | O2: Yes
A3: 46125 | D3: Spanish | E3: Laura Ambriz | F3: 96619838 | G3: 3853370012 | H3: Day Shift | I3: Mechanical Assembly | J3: WVC | K3: JY | L3: Passed | M3: Passed | N3: Passed
A4: 46125 | D4: Spanish | E4: Hildemaro Vargas | F4: 221840574 | G4: 3854050571 | H4: Night Shift | I4: Mechanical Assembly | J4: WJ | K4: NM | L4: Pending | M4: Passed | N4: Passed | O4: Yes
A5: 46122 | D5: Spanish | E5: Desiree Roa | F5: 199708572 | G5: 3854363656 | H5: Night Shift | I5: Mechanical Assembly | J5: WVC | K5: JY | L5: Pending | M5: Passed | N5: Passed | O5: Yes
A6: 46112 | D6: Bilingual | E6: Alondra Portillo | F6: 134090007 | G6: 801 205-1714 | H6: Night Shift | I6: Mechanical Assembly | J6: WJ | K6: NM | L6: Passed | M6: Passed | N6: Passed | O6: Yes
A7: 46112 | D7: Spanish | E7: Franklin Marroquin | F7: 221153634 | G7: 8016697856 | H7: Night Shift | I7: Mechanical Assembly | J7: WJ | K7: NM | L7: Passed | M7: Passed | N7: Passed | O7: Yes
A8: 46112 | D8: Spanish | E8: Lina Mendoza Mantilla | F8: 129270240 | G8: 7153106810 | H8: Night Shift | I8: Mechanical Assembly | J8: WVC | K8: HB | L8: Pending | M8: Passed | N8: Passed
A9: 46111 | D9: Spanish | E9: Orlando Herrera | F9: 146893715 | G9: 3854143049 | H9: Night Shift | I9: Mechanical Assembly | J9: WJ | K9: NM | L9: Pending | M9: Passed | N9: Passed | O9: Yes
A10: 46105 | D10: Spanish | E10: Cesar Paredes | F10: 220962745 | G10: (385) 445-0455 | H10: Night Shift | I10: Mechanical Assembly | J10: WJ | K10: NM | L10: Passed | M10: Passed | N10: Passed | O10: Yes
A11: 46022 | D11: Spanish | E11: Maira Colmenarez | F11: 182102784 | G11: 8529853652 | H11: Night Shift | I11: Mechanical Assembly | J11: WJ | K11: NM | L11: Passed | M11: Passed | N11: Passed | O11: Yes
A12: 46097 | D12: Spanish | E12: Robinson Portillo | F12: 220528859 | G12: 3855036486 | H12: Night Shift | I12: Mechanical Assembly | J12: WJ | K12: NM | L12: Pending | M12: Passed | N12: Passed | O12: Yes
A13: 46091 | D13: Spanish | E13: Eric Ahumada | F13: 219148124 | G13: 4359383183 | H13: Day Shift | I13: Mechanical Assembly | J13: WJ | K13: NM | L13: Pending | M13: Passed | N13: Passed
A14: 46090 | D14: Spanish | E14: Karla Saras | F14: 194460546 | G14: 8019008532 | H14: Night Shift | I14: Mechanical Assembly | J14: WJ | K14: NM | L14: Passed | M14: Passed | N14: Passed | O14: Yes
A15: 46085 | D15: Spanish | E15: Glencis Pacheco | F15: 219091840 | G15: 3853790835 | H15: Day Shift | I15: Mechanical Assembly | J15: WJ | K15: NM | L15: Pending | M15: Passed | N15: Passed | O15: Yes
A16: 46084 | D16: Spanish | E16: Aurora Lamas Arellano | F16: 219012962 | G16: 3852965337 | H16: Day Shift | I16: Mechanical Assembly | J16: WJ | K16: FZ | L16: Pending | M16: Passed | N16: Passed
A17: 46083 | D17: Spanish | E17: Jorge Villarreal | F17: 218763933 | G17: 8013016176 | H17: Night Shift | I17: Mechanical Assembly | J17: WJ | K17: NM | L17: Pending | M17: Passed | N17: Passed | O17: Yes
A18: 46080 | D18: Bilingual | E18: Dulce Lopez | F18: 198189443 | G18: 3852950100 | H18: Day Shift | I18: Mechanical Assembly | J18: WVC | K18: JY | L18: Passed | M18: Passed | N18: Passed | O18: Pending
A19: 46080 | D19: Spanish | E19: Yoselin Castillo | F19: 164911604 | G19: 8013853512 | H19: Day Shift | I19: Mechanical Assembly | J19: WJ | K19: BL | L19: Passed | M19: Passed | N19: Passed
A20: 46078 | D20: Spanish | E20: Roderlys Quiche | F20: 218825186 | G20: 8013810242 | H20: Night Shift | I20: Mechanical Assembly | J20: WJ | K20: BL | L20: Passed | M20: Passed | N20: Passed
A21: 46078 | D21: Spanish | E21: Luis Ferrer | F21: 185242799 | G21: 3855838763 | H21: Night Shift | I21: Mechanical Assembly | J21: WJ | K21: NM | L21: Pending | M21: Passed | N21: Passed | O21: Yes
A22: 46076 | D22: Spanish | E22: Sandra Ruiz | F22: 182082642 | G22: 3855367759 | H22: Night Shift | I22: Mechanical Assembly | J22: WJ | K22: NM | L22: Pending | M22: Passed | N22: Passed | O22: Yes
A23: 46076 | D23: Spanish | E23: Adalmiro Martinez | F23: 201730403 | G23: 3854309136 | H23: Day Shift | I23: Mechanical Assembly | J23: WJ | K23: NM | L23: Pending | M23: Passed | N23: Passed | O23: Yes
D24: Spanish | E24: Eduard Gil | F24: 217569760 | G24: 8015740260 | H24: Night Shift | I24: Mechanical Assembly | J24: WJ | K24: NM | L24: Passed | M24: Passed | N24: Passed | O24: Yes
D25: Spanish | E25: Vanessa Palma | F25: 216548342 | G25: 3854728364 | H25: Day Shift | I25: Mechanical Assembly | J25: WJ | K25: NM | L25: Pending | M25: Passed | N25: Passed | O25: Yes
C26: Wait List | D26: Spanish | E26: Marian Mendez | F26: 180458712 | G26: 8014405907 | H26: Day Shift | I26: Mechanical Assembly | J26: WJ | K26: NM | L26: Passed | M26: Passed | N26: Passed
A27: 46066 | D27: Spanish | E27: Priscilla Castillo | F27: 218038437 | G27: 8016083151 | H27: Night Shift | I27: Mechanical Assembly | J27: WVC | K27: HB | L27: Passed | M27: Passed | N27: Passed
A28: 46065 | D28: Spanish | E28: Gabriela Martinez | F28: 218486983 | G28: 9564496694 | H28: Night Shift | I28: Mechanical Assembly | J28: WJ | K28: NM | L28: Pending | M28: Passed | N28: Passed | O28: Yes
A29: 46065 | D29: Spanish | E29: Jorcer Chirinos | F29: 218487075 | G29: 3473688551 | H29: Night Shift | I29: Mechanical Assembly | J29: WJ | K29: NM | L29: Pending | M29: Passed | N29: Passed | O29: Yes
A30: 46065 | D30: English | E30: Christopher Mok | F30: 133343283 | G30: 3855293558 | H30: Night Shift | I30: Mechanical Assembly | J30: WJ | K30: NM | L30: Passed | M30: Passed | N30: Passed | O30: Yes
A31: 46065 | D31: Bilingual | E31: Stephanie Pimentel | F31: 209054687 | G31: 714 657-0986 | H31: Day Shift | I31: Mechanical Assembly | J31: WJ | K31: NM | L31: Pending | M31: Passed | N31: Passed | O31: Yes
A32: 46065 | D32: Spanish | E32: Idel Silva | F32: 218432819 | G32: 8013014999 | H32: Night Shift | I32: Mechanical Assembly | J32: WJ | K32: NM | L32: Passed | M32: Passed | N32: Passed | O32: Yes
A33: 46064 | D33: Spanish | E33: Tony Jovo | F33: 218446551 | G33: 4072886356 | H33: Night Shift | I33: Mechanical Assembly | J33: WJ | K33: NM | L33: Passed | M33: Passed | N33: Passed | O33: Yes
A34: 46063 | D34: Spanish | E34: Luiseni Gonzalez | F34: 164355124 | G34: 3855021965 | H34: Day Shift | I34: Mechanical Assembly | J34: WJ | K34: NM | L34: Passed | M34: Passed | N34: Passed | O34: Yes
A35: 46059 | D35: English | E35: Maddox Trinh | F35: 203395747 | G35: 385 630-7207 | H35: Night Shift | I35: Mechanical Assembly | J35: NSL | K35: GKW | L35: Pending | M35: Passed | N35: Passed
A36: 46059 | D36: Spanish | E36: Maria Hernandez | F36: 177591908 | G36: 385 549 4599 | H36: Day Shift | I36: Mechanical Assembly | J36: WVC | K36: SM | L36: Passed | M36: Passed | N36: Passed | O36: Yes
A37: 46059 | D37: Spanish | E37: Sharis Luna | F37: 213034437 | G37: 8014031625 | H37: Day Shift | I37: Mechanical Assembly | J37: WVC | K37: SM | L37: Passed | M37: Passed | N37: Passed | O37: Yes
A38: 46059 | D38: Spanish | E38: Niurka Solares | F38: 218237562 | G38: 8013179423 | H38: Day Shift | I38: Mechanical Assembly | J38: WJ | K38: BL | L38: Passed | M38: Passed | N38: Passed
A39: 46058 | D39: Spanish | E39: María Ibarra | F39: 168121931 | G39: 8015849577 | H39: Day Shift | I39: Mechanical Assembly | J39: WJ | K39: BL | L39: Passed | M39: Passed | N39: Passed
A40: 46057 | D40: Spanish | E40: Jaidy Jimenez | F40: 218032291 | G40: 3855261356 | H40: Night Shift | I40: Mechanical Assembly | J40: WJ | K40: NM | L40: Passed | M40: Passed | N40: Passed | O40: Yes
A41: 46056 | D41: Spanish | E41: Ruth Cuicapuza | F41: 181401512 | G41: 3855630085 | H41: Day Shift | I41: Mechanical Assembly | J41: WJ | K41: NM | L41: Pending | M41: Passed | N41: Passed | O41: Yes
A42: 46056 | D42: Spanish | E42: Melina Marin | F42: 217981646 | G42: 8329102422 | H42: Night Shift | I42: Mechanical Assembly | J42: WJ | K42: NM | L42: Pending | M42: Passed | N42: Passed | O42: Yes
A43: 46056 | D43: Spanish | E43: Gledis Salave | F43: 217581295 | G43: 7065377975 | H43: Day Shift | I43: Mechanical Assembly | J43: WJ | K43: NM | L43: Pending | M43: Passed | N43: Passed | O43: Yes
A44: 46056 | D44: Spanish | E44: Roxana Concha | F44: 217966053 | G44: 8019499263 | H44: Day Shift | I44: Mechanical Assembly | J44: WVC | K44: SM | L44: Passed | M44: Passed | N44: Passed
A45: 46056 | D45: Spanish | E45: Katherine Urribarri | F45: 173080631 | G45: 3855623691 | H45: Day Shift | I45: Mechanical Assembly | J45: WJ | K45: NM | L45: Pending | M45: Passed | N45: Passed | O45: Yes
A46: 46055 | D46: Spanish | E46: Richard Hugle | F46: 201781659 | G46: 404 2075364 | H46: Night Shift | I46: Mechanical Assembly | J46: WVC | K46: SM | L46: Passed | M46: Passed | N46: Passed
A47: 46052 | D47: English | E47: Alexander Chavez | F47: 217276724 | G47: 8018336531 | H47: Night Shift | I47: Mechanical Assembly | J47: NSL | K47: GKW | L47: Passed | M47: Passed | N47: Passed
A48: 46050 | D48: Spanish | E48: Wilmery Molina | F48: 157842478 | G48: 385 212 5764 | H48: Day Shift | I48: Mechanical Assembly | J48: WJ | K48: NM | L48: Passed | M48: Passed | N48: Passed | O48: Yes
A49: 46049 | D49: Spanish | E49: Norbys Carbonell | F49: 167320320 | G49: 8017026930 | H49: Day Shift | I49: Mechanical Assembly | J49: WJ | K49: NM | L49: Passed | M49: Passed | N49: Passed | O49: Yes
A50: 46043 | D50: Bilingual | E50: Maria Garcia | F50: 216600348 | G50: 801 819-8446 | H50: Night Shift | I50: Mechanical Assembly | J50: WJ | K50: NM | L50: Passed | M50: Passed | N50: Passed | O50: Yes
A51: 46043 | D51: Spanish | E51: Ana Melano | F51: 144109866 | G51: 3852143309 | H51: Day Shift | I51: Mechanical Assembly | J51: WJ | K51: NM | L51: Passed | M51: Passed | N51: Passed | O51: Pending
A52: 46043 | D52: Spanish | E52: Aliyoli Primera | F52: 115255112 | G52: 8013019019 | H52: Day Shift | I52: Mechanical Assembly | J52: WJ | K52: NM | L52: Passed | M52: Passed | N52: Passed | O52: Pending
A53: 46038 | D53: Spanish | E53: Jose Hernandez | F53: 216886382 | G53: 3855767818 | H53: Day Shift | I53: Mechanical Assembly | J53: WVC | K53: SM | L53: Passed | M53: Passed | N53: Passed | O53: Pending
A54: 46036 | D54: Spanish | E54: Ruth Ricaurte | F54: 199219797 | G54: 8016349048 | H54: Night Shift | I54: Mechanical Assembly | J54: WJ | K54: NM | L54: Passed | M54: Passed | N54: Passed | O54: Yes
A55: 46035 | D55: Spanish | E55: Humberto Ferrer | F55: 215489766 | G55: 8015052710 | H55: Day Shift | I55: Mechanical Assembly | J55: WJ | K55: BL | M55: Not Ran | N55: Passed
A56: 46035 | D56: English | E56: Francisco Saena | F56: 199234585 | G56: 8019994508 | H56: Night Shift | I56: Mechanical Assembly | J56: WJ | K56: BL | L56: Pending | M56: Passed | N56: Passed
A57: 46031 | D57: Spanish | E57: Yeimar Hernandez | F57: 176567281 | G57: 3854842488 | H57: Day Shift | I57: Mechanical Assembly | J57: WJ | K57: NM | L57: Passed | M57: Passed | N57: Passed | O57: Pending
A58: 46031 | D58: Spanish | E58: Roberto Rodriguez | F58: 173080626 | G58: 3854574485 | H58: Day Shift | I58: Mechanical Assembly | J58: WJ | K58: NM | L58: Pending | M58: Passed | N58: Passed | O58: Pending
A59: 46030 | D59: Spanish | E59: Greeni Moreno | F59: 215434837 | G59: 8015145115 | H59: Day Shift | I59: Mechanical Assembly | J59: WJ | K59: BL | L59: Passed | M59: Passed | N59: Passed
A60: 46029 | D60: Spanish | E60: Karelys Pina | F60: 203432515 | G60: 8016619661 | H60: Day Shift | I60: Mechanical Assembly | J60: WJ | K60: NM | L60: Passed | M60: Passed | N60: Passed | O60: Yes
A61: 46028 | D61: Spanish | E61: Maria Ferrer | F61: 213096672 | G61: 3853387356 | H61: Day Shift | I61: Mechanical Assembly | J61: WJ | K61: NM | L61: Passed | M61: Passed | N61: Passed
A62: 46028 | D62: Spanish | E62: Betzaida henriquez | F62: 185189753 | G62: 8014102119 | H62: Day Shift | I62: Mechanical Assembly | J62: WJ | K62: NM | L62: Passed | M62: Passed | N62: Passed | O62: Yes
A63: 46020 | D63: Spanish | E63: Bilianny Arocha | F63: 193871827 | G63: 3852252327 | H63: Day Shift | I63: Mechanical Assembly | J63: WJ | K63: BL | L63: Passed | M63: Passed | N63: Passed
A64: 46014 | D64: Spanish | E64: Yaneiri Bianchi | F64: 193850499 | G64: 8015028685 | H64: Night Shift | I64: Mechanical Assembly | J64: WVC | K64: SCG | L64: Pending | M64: Passed | N64: Passed | O64: No
A65: 45894 | D65: Spanish | E65: Damaris Gutierrez | F65: 198514018 | G65: 3855849513 | H65: Night Shift | I65: Mechanical Assembly | J65: WJ | K65: NM | L65: Passed | M65: Passed | N65: Passed
A66: 45889 | B66: 45981 | D66: Bilingual | E66: Nelfrailis Gonzales | F66: 168037863 | G66: 3855807947 | H66: Night Shift | I66: Mechanical Assembly | J66: NSL | K66: DR | L66: Passed | M66: Passed | N66: Passed
A67: 45889 | D67: Spanish | E67: Javierio Hernandez | F67: 198012857 | G67: 3855807953 | H67: Night Shift | I67: Mechanical Assembly | J67: NSL | K67: DR | L67: Passed | M67: Passed | N67: Passed

Sheet TBD
A1: DO NOT SORT. ONCE NAME IS ADDED IT CANNOT BE REMOVED OR MOVED. EVERYTHING MUST BE DONE BEFORE ADDING TO SHEET.
A2: Spanish and bilingual only starts Deadline is 1pm day before start date
A3: Req # | B3: Supervisor | C3: P CODE | D3: SSN | E3: Employee Name (must match Bold) | F3: Bold ID | G3: Phone # | H3: Recruiter | I3: Shirt Size | J3: Title | K3: Schedule | L3: C-Number | M3: BG | N3: I-9 | O3: E-Verify | P3: Flex AA | Q3: Onboarding Tasks | R3: Offer Letter | S3: NOTES
C4: P2743607 | D4: 135-65-9603 | E4: Cesar Perez | F4: 218431336 | G4: 4352996802 | H4: BL | I4: M | K4: B Shift: Salt Lake City - P - 600pm-600a Rotating Tues,Wed,Sat/Sun,Mon,Thurs,Fri (15% Diff)
C5: P2743602 | D5: 275-67-2850 | E5: Sandra Melendez | F5: 230680035 | G5: 3852722316 | H5: BL | I5: M | K5: D Shift: Salt Lake City - N - 600pm-600a Rotating Sun,Mon,Thurs, Fri/Tues,Wed,Sat (15% Diff)
C6: P2743391 | D6: 782804150 | E6: Luis palmar | F6: 191017674 | G6: 4044355328 | H6: RP | I6: XL | K6: D Shift: Salt Lake City - N - 600pm-600a Rotating Sun,Mon,Thurs, Fri/Tues,Wed,Sat (15% Diff)
C7: P2744693 | D7: 728-44-4200 | E7: Luz Polanco | F7: 220548977 | G7: 8016349542 | H7: BL | K7: A Shift: Salt Lake City - Q - 600am-600pm Rotating Tues,Wed,Sat/Sun,Mon, Thurs,Fri
C8: P2744745 | D8: 015-96-0816 | E8: Karen Rodriguez Monroy | F8: 127763315 | G8: 3854889389 | H8: BL | I8: M | K8: D Shift: Salt Lake City - N - 600pm-600a Rotating Sun,Mon,Thurs, Fri/Tues,Wed,Sat (15% Diff)

Sheet 8.24.26
A1: DO NOT SORT. ONCE NAME IS ADDED IT CANNOT BE REMOVED OR MOVED. EVERYTHING MUST BE DONE BEFORE ADDING TO SHEET.
A2: Spanish and bilingual only starts Deadline is 1pm day before start date
A3: Req # | B3: Supervisor | C3: P CODE | D3: SSN | E3: Employee Name (must match Bold) | F3: Bold ID | G3: Phone # | H3: Recruiter | I3: Shirt Size | J3: Title | K3: Schedule | L3: C-Number | M3: BG | N3: I-9 | O3: E-Verify | P3: Flex AA | Q3: Onboarding Tasks | R3: Offer Letter | S3: NOTES
A4: FLX0630 | B4: Jennifer Prudente (1168431) | C4: P2743630 | D4: 818-01-0139 | E4: Jean Ramos Lopez | F4: 109345141 | G4: 9013375802 | H4: BL | I4: M | J4: Production Specialist 1 - Dekit | K4: C Shift: Salt Lake City - O - 600am-600pm Rotating Sun,Mon,Thurs, Fri/Tues,Wed,Sat | L4: C125977
A5: FLX0633 | B5: Jennifer Prudente (1168431) | C5: P2743627 | D5: 064-15-3565 | E5: Miyelis Urdaneta | F5: 142410292 | G5: 3854867281 | H5: EP | J5: Production Specialist 1 - Dekit | K5: C Shift: Salt Lake City - O - 600am-600pm Rotating Sun,Mon,Thurs, Fri/Tues,Wed,Sat | L5: C125978
A6: FLX0634 | B6: Jennifer Prudente (1168431) | C6: P2743631 | D6: 856-86-3425 | E6: Ivan Chirinos | F6: 230400380 | G6: 3854348866 | H6: BL | I6: M | J6: Production Specialist 1 - Dekit | K6: C Shift: Salt Lake City - O - 600am-600pm Rotating Sun,Mon,Thurs, Fri/Tues,Wed,Sat | L6: C126095
A7: FLX0635 | B7: Jennifer Prudente (1168431) | C7: P2743625 | D7: 199-77-8338 | E7: Yisel Marquez | F7: 161284558 | G7: 7867992591 | H7: NM | I7: M | J7: Production Specialist 1 - Dekit | K7: C Shift: Salt Lake City - O - 600am-600pm Rotating Sun,Mon,Thurs, Fri/Tues,Wed,Sat | L7: C126096
A8: FLX0647 | B8: Jennifer Paz (1166697) | C8: P2743613 | D8: 899-88-1555 | E8: Dieneddys Navarro | F8: 133759259 | G8: 8017501509 | H8: NM | I8: M | J8: Production Specialist - L10 Repair (Bonepile) | K8: A Shift: Salt Lake City - Q - 600am-600pm Rotating Tues,Wed,Sat/Sun,Mon, Thurs,Fri | L8: C125979
A9: FLX0653 | B9: Alexis Rullan | C9: P2743607 | D9: 135-65-9603 | F9: 218431336 | G9: 4352996802 | H9: BL | I9: M | J9: Production Specialist - L10 Repair (Bonepile) | K9: B Shift: Salt Lake City - P - 600pm-600a Rotating Tues,Wed,Sat/Sun,Mon,Thurs,Fri (15% Diff)
A10: FLX0656 | B10: Alexis Rullan | C10: P2743604 | D10: 102493872 | E10: JennyMercedesArbelaez Pena | F10: 222806603 | G10: 8016498875 | H10: JY | I10: M | J10: Production Specialist - L10 Repair (Bonepile) | K10: B Shift: Salt Lake City - P - 600pm-600a Rotating Tues,Wed,Sat/Sun,Mon,Thurs,Fri (15% Diff) | L10: C125980
A11: FLX0658 | B11: Yalia Driggers (1153165) | C11: P2743602 | D11: 275-67-2850 | F11: 230680035 | G11: 3852722316 | H11: BL | I11: M | J11: Production Specialist - L10 Repair (Bonepile) | K11: D Shift: Salt Lake City - N - 600pm-600a Rotating Sun,Mon,Thurs, Fri/Tues,Wed,Sat (15% Diff)
A12: FLX0662 | B12: Alondra Landin | C12: Jose Manuel Marquina / P2689830 | D12: 822442612 | E12: Walter Lesmes | F12: 230689870 | G12: 3852522460 | H12: JM | I12: L | J12: Production Specialist 1 - Mechanical Assembly | K12: A Shift: Salt Lake City - Q - 600am-600pm Rotating Tues,Wed,Sat/Sun,Mon, Thurs,Fri | L12: C125981
A13: FLX0664 | B13: Jose Gonzalez | C13: Zuleima Del Carmen Pereira / P2689186 | D13: 302-57-4156 | E13: Kahirys Maria Melendez | F13: 120736470 | G13: 3854362422 | H13: NM | I13: M | J13: Production Specialist 1 - Mechanical Assembly | K13: A Shift: Salt Lake City - Q - 600am-600pm Rotating Tues,Wed,Sat/Sun,Mon, Thurs,Fri | L13: C125982
A14: FLX0671 | B14: Yaritza Garza | C14: Hector Flores Gonzalez / P2720902 | D14: 814-34-9834 | E14: Juan Pablo Saenz | F14: 230400373 | G14: 8016046577 | H14: BL | J14: Production Specialist 1 - Cold Room | K14: C Shift: Salt Lake City - O - 600am-600pm Rotating Sun,Mon,Thurs, Fri/Tues,Wed,Sat | L14: C125983
A15: FLX0554 | B15: Avigail Zamora | C15: P2743391 | D15: 782804150 | F15: 191017674 | G15: 4044355328 | H15: RP | I15: XL | J15: Production Specialist 1 - Rack level Assembly | K15: D Shift: Salt Lake City - N - 600pm-600a Rotating Sun,Mon,Thurs, Fri/Tues,Wed,Sat (15% Diff)
A16: FLX0675 | B16: Castalia Marino | C16: P2744693 | D16: 728-44-4200 | F16: 220548977 | G16: 8016349542 | H16: BL | J16: Production Specialist 1 - Materials | K16: A Shift: Salt Lake City - Q - 600am-600pm Rotating Tues,Wed,Sat/Sun,Mon, Thurs,Fri
A17: FLX0679 | B17: Alondra Landin | C17: P2744691 | D17: 660-38-2991 | E17: Nelly Parra Lucena | F17: 230684067 | G17: 3857874254 | H17: NM | J17: Production Specialist 1 - Mechanical Assembly | K17: A Shift: Salt Lake City - Q - 600am-600pm Rotating Tues,Wed,Sat/Sun,Mon, Thurs,Fri | L17: C126002
A18: FLX0680 | B18: Alondra Landin | C18: P2744764 | D18: 870-09-1608 | E18: Ghileny Garces Parra | F18: 230683960 | G18: 3855568744 | H18: NM | J18: Production Specialist 1 - Mechanical Assembly | K18: A Shift: Salt Lake City - Q - 600am-600pm Rotating Tues,Wed,Sat/Sun,Mon, Thurs,Fri | L18: C126009
A19: FLX0681 | B19: Barbara Garcia (1137177) | C19: P2744763 | D19: 813-25-1704 | E19: Loinny Avila | F19: 235368222 | G19: 3855363844 | H19: NM | J19: Production Specialist 1 - Cold Room | K19: A Shift: Salt Lake City - Q - 600am-600pm Rotating Tues,Wed,Sat/Sun,Mon, Thurs,Fri | L19: C126025
A20: FLX0687 | B20: Mariana Ballesteros (1174672) | C20: P2744760 | D20: 511-57-4050 | E20: Miguel Penuela Sequera | F20: 222950954 | G20: 3854007870 | H20: DR | J20: Production Specialist 1 - Materials | K20: C Shift: Salt Lake City - O - 600am-600pm Rotating Sun,Mon,Thurs, Fri/Tues,Wed,Sat | L20: C126015
A21: FLX0688 | B21: Mariana Ballesteros (1174672) | C21: P2744759 | D21: 027-13-9140 | E21: Stefani Rios | F21: 198483034 | G21: 3857709785 | H21: BL | J21: Production Specialist 1 - Materials | K21: C Shift: Salt Lake City - O - 600am-600pm Rotating Sun,Mon,Thurs, Fri/Tues,Wed,Sat | L21: C126018
A22: FLX0690 | B22: Dario Mendez Toyo (1174155) | C22: P2744690 | D22: 850-72-2546 | E22: Ricardo Merril | F22: 204831061 | G22: 9176758255 | H22: BL | J22: Production Specialist 1 - Materials | K22: C Shift: Salt Lake City - O - 600am-600pm Rotating Sun,Mon,Thurs, Fri/Tues,Wed,Sat | L22: C126023
A23: FLX0691 | B23: Valeria Mendez (1181800) | C23: P2744689 | D23: 653-25-1441 | E23: Maria Cruz | F23: 221335274 | G23: 8016513104 | H23: BL | J23: Production Specialist 1 - Mechanical Assembly | K23: C Shift: Salt Lake City - O - 600am-600pm Rotating Sun,Mon,Thurs, Fri/Tues,Wed,Sat | L23: C126021
A24: FLX0700 | B24: Sanel Kudic | C24: P2744755 | D24: 710-99-8300 | E24: Jorge Aldana | F24: 152251119 | G24: 3855766809 | H24: NM | J24: Production Specialist 1 - Materials | K24: B Shift: Salt Lake City - P - 600pm-600a Rotating Tues,Wed,Sat/Sun,Mon,Thurs,Fri (15% Diff) | L24: C126044
A25: FLX0702 | B25: Paola Guzman | C25: P2744753 | D25: 617-84-8265 | E25: Elias Dobieksi | F25: 235381721 | G25: 3107291724 | H25: NM | J25: Production Specialist 1 - Materials | K25: B Shift: Salt Lake City - P - 600pm-600a Rotating Tues,Wed,Sat/Sun,Mon,Thurs,Fri (15% Diff) | L25: C126045
A26: FLX0703 | B26: Paola Guzman | C26: P2744752 | D26: 761-78-1497 | E26: Pedro Ruis Medina | F26: 191017640 | G26: 6783149281 | H26: RP | I26: M | J26: Production Specialist 1 - Materials | K26: B Shift: Salt Lake City - P - 600pm-600a Rotating Tues,Wed,Sat/Sun,Mon,Thurs,Fri (15% Diff) | L26: C126014
A27: FLX0711 | B27: Gaige Snow | C27: P2744751 | D27: 648-84-8675 | E27: Gabriel Alviarez | F27: 221039863 | G27: 8016743906 | H27: NM | J27: Production Specialist 1 - Materials | K27: D Shift: Salt Lake City - N - 600pm-600a Rotating Sun,Mon,Thurs, Fri/Tues,Wed,Sat (15% Diff) | L27: C126013
A28: FLX0712 | B28: Gaige Snow | C28: P2744750 | D28: 772-53-1232 | E28: Yorman Yanez | F28: 119129137 | G28: 385-505-0694 | H28: BL | I28: M | J28: Production Specialist 1 - Materials | K28: D Shift: Salt Lake City - N - 600pm-600a Rotating Sun,Mon,Thurs, Fri/Tues,Wed,Sat (15% Diff) | L28: C126012
A29: FLX0714 | B29: Mel Kellar (1142020) | C29: P2744748 | D29: 688-84-1615 | E29: Kimberly Martinez | F29: 136202294 | G29: 3855626805 | H29: BL | I29: M | J29: Production Specialist 1 - Materials | K29: D Shift: Salt Lake City - N - 600pm-600a Rotating Sun,Mon,Thurs, Fri/Tues,Wed,Sat (15% Diff) | L29: C126010
A30: FLX0722 | B30: Dallas Driggers | C30: P2744745 | D30: 015-96-0816 | F30: 127763315 | G30: 3854889389 | H30: BL | I30: M | J30: Production Specialist 1 - Cold Room | K30: D Shift: Salt Lake City - N - 600pm-600a Rotating Sun,Mon,Thurs, Fri/Tues,Wed,Sat (15% Diff)

Sheet 8.20.26
A1: DO NOT SORT. ONCE NAME IS ADDED IT CANNOT BE REMOVED OR MOVED. EVERYTHING MUST BE DONE BEFORE ADDING TO SHEET.
A2: English/bilingual for 6:30am class and Spanish only for 230pm start
A3: Req # | B3: Supervisor | C3: P CODE | D3: SSN | E3: Employee Name (must match Bold) | F3: Bold ID | G3: Phone # | H3: Recruiter | I3: Shirt Size | J3: Title | K3: Schedule | L3: C-Number | M3: BG | N3: I-9 | O3: E-Verify | P3: Flex AA | Q3: Onboarding Tasks | R3: Offer Letter | S3: NOTES
A4: FLX0674 | B4: Castalia Marino | C4: P2744694 | D4: 616-21-6873 | E4: Fernando S Razuri | F4: 205051457 | G4: 8189165469 | H4: FZ | I4: L | J4: Production Specialist 1 - Materials | K4: A Shift: Salt Lake City - Q - 600am-600pm Rotating Tues,Wed,Sat/Sun,Mon, Thurs,Fri | L4: C125927 | R4: x
A5: FLX0675 | B5: Castalia Marino | C5: FLX0675 | D5: 620-70-1335 | E5: Guadalupe Ruiz | F5: 124766504 | G5: 385-576-9207 | H5: BL | J5: Production Specialist 1 - Materials | K5: A Shift: Salt Lake City - Q - 600am-600pm Rotating Tues,Wed,Sat/Sun,Mon, Thurs,Fri | L5: C125941
A6: FLX0676 | B6: Castalia Marino | C6: P2744692 | D6: 686-26-6198 | E6: Henry Rivero | F6: 235103783 | G6: 4326643931 | H6: NM | J6: Production Specialist 1 - Materials | K6: A Shift: Salt Lake City - Q - 600am-600pm Rotating Tues,Wed,Sat/Sun,Mon, Thurs,Fri | L6: C125942 | R6: x
A7: FLX0679 | B7: Alondra Landin | C7: P2744691 | D7: 590-77-6003 | E7: Mayra Ballistreri | F7: 103409638 | G7: 3853714779 | H7: HB | J7: Production Specialist 1 - Mechanical Assembly | K7: A Shift: Salt Lake City - Q - 600am-600pm Rotating Tues,Wed,Sat/Sun,Mon, Thurs,Fri | L7: C125943
A8: FLX0680 | B8: Alondra Landin | C8: P2744764 | J8: Production Specialist 1 - Mechanical Assembly | K8: A Shift: Salt Lake City - Q - 600am-600pm Rotating Tues,Wed,Sat/Sun,Mon, Thurs,Fri
A9: FLX0681 | B9: Barbara Garcia (1137177) | C9: P2744763 | D9: 835-29-6844 | E9: William A Piccone | F9: 217233983 | G9: 3853541676 | H9: RP | I9: L | J9: Production Specialist 1 - Cold Room | K9: A Shift: Salt Lake City - Q - 600am-600pm Rotating Tues,Wed,Sat/Sun,Mon, Thurs,Fri | L9: C125928
A10: FLX0682 | B10: Barbara Garcia (1137177) | C10: P2744762 | D10: 242-87-6217 | E10: Jenifer Torres Loya | F10: 235113308 | G10: 33661890536 | H10: RP | I10: M | J10: Production Specialist 1 - Cold Room | K10: A Shift: Salt Lake City - Q - 600am-600pm Rotating Tues,Wed,Sat/Sun,Mon, Thurs,Fri | L10: C125929 | R10: x
A11: FLX0683 | B11: Barbara Garcia (1137177) | C11: P2744761 | D11: 073-37-5279 | E11: Aidan A Perez | F11: 228927969 | G11: 2816704894 | H11: BL | I11: XXL | J11: Production Specialist 1 - Cold Room | K11: A Shift: Salt Lake City - Q - 600am-600pm Rotating Tues,Wed,Sat/Sun,Mon, Thurs,Fri | L11: C125939 | R11: x
A12: FLX0687 | B12: Mariana Ballesteros (1174672) | C12: P2744760 | J12: Production Specialist 1 - Materials | K12: C Shift: Salt Lake City - O - 600am-600pm Rotating Sun,Mon,Thurs, Fri/Tues,Wed,Sat
A13: FLX0688 | B13: Mariana Ballesteros (1174672) | C13: P2744759 | J13: Production Specialist 1 - Materials | K13: C Shift: Salt Lake City - O - 600am-600pm Rotating Sun,Mon,Thurs, Fri/Tues,Wed,Sat
A14: FLX0689 | B14: Dario Mendez Toyo (1174155) | C14: P2744758 | D14: 275-78-7148 | E14: Yahanna L Goss | F14: 137909958 | G14: 513 878-5477 | H14: JY | I14: L | J14: Production Specialist 1 - Materials | K14: C Shift: Salt Lake City - O - 600am-600pm Rotating Sun,Mon,Thurs, Fri/Tues,Wed,Sat | L14: C125930 | R14: x
A15: FLX0690 | B15: Dario Mendez Toyo (1174155) | C15: P2744690 | D15: 575-89-6601 | E15: Saoluaga T Siliva | F15: 230202685 | G15: 3853369802 | H15: JM | I15: XL | J15: Production Specialist 1 - Materials | K15: C Shift: Salt Lake City - O - 600am-600pm Rotating Sun,Mon,Thurs, Fri/Tues,Wed,Sat | L15: C125932
A16: FLX0691 | B16: Valeria Mendez (1181800) | C16: P2744689 | J16: Production Specialist 1 - Mechanical Assembly | K16: C Shift: Salt Lake City - O - 600am-600pm Rotating Sun,Mon,Thurs, Fri/Tues,Wed,Sat
A17: FLX0692 | B17: Valeria Mendez (1181800) | C17: P2744757 | D17: 730120557 | E17: Joddy Bastidas | F17: 230402628 | G17: 3474458703 | H17: JM | I17: L | J17: Production Specialist 1 - Mechanical Assembly | K17: C Shift: Salt Lake City - O - 600am-600pm Rotating Sun,Mon,Thurs, Fri/Tues,Wed,Sat | L17: C125934 | R17: x
A18: FLX0699 | B18: Sanel Kudic | C18: P2744756 | D18: 647-98-3583 | E18: Andy C Rodriguez Ruiz | F18: 235337443 | G18: 8013479267 | H18: JY | J18: Production Specialist 1 - Materials | K18: B Shift: Salt Lake City - P - 600pm-600a Rotating Tues,Wed,Sat/Sun,Mon,Thurs,Fri (15% Diff) | L18: C125944 | R18: x
A19: FLX0700 | B19: Sanel Kudic | C19: P2744755 | J19: Production Specialist 1 - Materials | K19: B Shift: Salt Lake City - P - 600pm-600a Rotating Tues,Wed,Sat/Sun,Mon,Thurs,Fri (15% Diff)
A20: FLX0701 | B20: Paola Guzman | C20: P2744754 | D20: 146599684 | E20: Glody M Tumbwa | F20: 149731745 | G20: 2176128184 | H20: JM | I20: XL | J20: Production Specialist 1 - Materials | K20: B Shift: Salt Lake City - P - 600pm-600a Rotating Tues,Wed,Sat/Sun,Mon,Thurs,Fri (15% Diff) | L20: C125935 | R20: x
A21: FLX0702 | B21: Paola Guzman | C21: P2744753 | J21: Production Specialist 1 - Materials | K21: B Shift: Salt Lake City - P - 600pm-600a Rotating Tues,Wed,Sat/Sun,Mon,Thurs,Fri (15% Diff)
A22: FLX0703 | B22: Paola Guzman | C22: P2744752 | J22: Production Specialist 1 - Materials | K22: B Shift: Salt Lake City - P - 600pm-600a Rotating Tues,Wed,Sat/Sun,Mon,Thurs,Fri (15% Diff)
A23: FLX0711 | B23: Gaige Snow | C23: P2744751 | J23: Production Specialist 1 - Materials | K23: D Shift: Salt Lake City - N - 600pm-600a Rotating Sun,Mon,Thurs, Fri/Tues,Wed,Sat (15% Diff)
A24: FLX0712 | B24: Gaige Snow | C24: P2744750 | J24: Production Specialist 1 - Materials | K24: D Shift: Salt Lake City - N - 600pm-600a Rotating Sun,Mon,Thurs, Fri/Tues,Wed,Sat (15% Diff)
A25: FLX0713 | B25: Gaige Snow | C25: P2744749 | D25: 733-03-6301 | E25: Whang C Walters | F25: 226997062 | G25: 3852662386 | H25: HB | I25: XL | J25: Production Specialist 1 - Materials | K25: D Shift: Salt Lake City - N - 600pm-600a Rotating Sun,Mon,Thurs, Fri/Tues,Wed,Sat (15% Diff) | L25: C125936 | R25: x
A26: FLX0714 | B26: Mel Kellar (1142020) | C26: P2744748 | J26: Production Specialist 1 - Materials | K26: D Shift: Salt Lake City - N - 600pm-600a Rotating Sun,Mon,Thurs, Fri/Tues,Wed,Sat (15% Diff)
A27: FLX0715 | B27: Mel Kellar (1142020) | C27: P2744747 | D27: 252-25-6569 | E27: Terance Melton | F27: 230749612 | G27: 7204212565 | H27: JY | J27: Production Specialist 1 - Materials | K27: D Shift: Salt Lake City - N - 600pm-600a Rotating Sun,Mon,Thurs, Fri/Tues,Wed,Sat (15% Diff) | L27: C125945 | R27: x
A28: FLX0721 | B28: Dallas Driggers | C28: P2744746 | D28: 647-07-1154 | E28: Michael L Fabela | F28: 203353201 | G28: 385 536 0473 | H28: BL | J28: Production Specialist 1 - Cold Room | K28: D Shift: Salt Lake City - N - 600pm-600a Rotating Sun,Mon,Thurs, Fri/Tues,Wed,Sat (15% Diff) | L28: C125940 | R28: x
A29: FLX0722 | B29: Dallas Driggers | C29: P2744745 | D29: 575-93-5629 | E29: Telmer Emos | F29: 95673500 | G29: 385 432 9812 | H29: GKW | I29: XL | J29: Production Specialist 1 - Cold Room | K29: D Shift: Salt Lake City - N - 600pm-600a Rotating Sun,Mon,Thurs, Fri/Tues,Wed,Sat (15% Diff) | L29: C125937
A30: FLX0723 | B30: Dallas Driggers | C30: P2744744 | D30: 269-83-3820 | E30: Mary Labrador | F30: 161455496 | G30: 3855073267 | H30: NM | I30: L | J30: Production Specialist 1 - Cold Room | K30: D Shift: Salt Lake City - N - 600pm-600a Rotating Sun,Mon,Thurs, Fri/Tues,Wed,Sat (15% Diff) | L30: C125931 | R30: x
D36: Spanish Only

Sheet 8.17.26
A1: SPANISH ONLY
A2: Req # | B2: Supervisor | C2: P CODE | D2: SSN | E2: Employee Name (must match Bold) | F2: Bold ID | G2: Phone # | H2: Recruiter | I2: Shirt Size | J2: Title | K2: Schedule | L2: C-Number | M2: BG | N2: I-9 | O2: E-Verify | P2: Flex AA | Q2: Onboarding Tasks | R2: Offer Letter | S2: NOTES
A3: FLX0541 | B3: Douglas Camargo (114508) | C3: P2743404 | D3: 026-13-6771 | E3: Frank Linares | F3: 230688754 | G3: 3852466212 | H3: RP | I3: L | J3: Production Specialist 1 - Rack level Assembly | K3: A Shift: Salt Lake City - Q - 600am-600pm Rotating Tues,Wed,Sat/Sun,Mon, Thurs,Fri | L3: C125736 | R3: X
A4: FLX0543 | B4: Douglas Camargo (114508) | C4: P2743402 | D4: 172-02-3958 | E4: Anaias Faria | F4: 227227008 | G4: 3854183056 | H4: FZ | I4: S | J4: Production Specialist 1 - Rack level Assembly | K4: A Shift: Salt Lake City - Q - 600am-600pm Rotating Tues,Wed,Sat/Sun,Mon, Thurs,Fri | L4: C125764 | R4: X
A5: FLX0549 | B5: Julissa Sencion (1154184) | C5: P2743396 | D5: 828-17-0411 | E5: Rocio Rondon Pena | F5: 134612285 | G5: 8012057920 | H5: NM | I5: S | J5: Production Specialist 1 - Rack level Assembly | K5: C Shift: Salt Lake City - O - 600am-600pm Rotating Sun,Mon,Thurs, Fri/Tues,Wed,Sat | L5: C125691 | R5: X
A6: FLX0554 | B6: Avigail Zamora | C6: P2743391 | D6: 767-29-4435 | E6: Eduar Suarez | F6: 218871354 | G6: 3852407252 | H6: BL | I6: L | J6: Production Specialist 1 - Rack level Assembly | K6: D Shift: Salt Lake City - N - 600pm-600a Rotating Sun,Mon,Thurs, Fri/Tues,Wed,Sat (15% Diff) | L6: C125685 | R6: X
A7: FLX0558 | B7: Avigail Zamora | C7: P2743387 | D7: Waiting on EV | E7: Oswaldo Valencia | F7: 198126077 | G7: 8014304770 | H7: RP | I7: L | J7: Production Specialist 1 - Rack level Assembly | K7: D Shift: Salt Lake City - N - 600pm-600a Rotating Sun,Mon,Thurs, Fri/Tues,Wed,Sat (15% Diff) | L7: C125776 | R7: X
A8: FLX0559 | B8: Avigail Zamora | C8: P2743386 | D8: 297-63-8673 | E8: Stephanie Gomez | F8: 103450494 | G8: 8019492079 | H8: GKW | I8: L | J8: Production Specialist 1 - Rack level Assembly | K8: D Shift: Salt Lake City - N - 600pm-600a Rotating Sun,Mon,Thurs, Fri/Tues,Wed,Sat (15% Diff) | L8: C125689 | R8: X
A9: FLX0561 | B9: Avigail Zamora | C9: P2743384 | D9: 721-67-3496 | E9: Jhoseiny Gonzalez | F9: 209195517 | G9: 3852821517 | H9: NM | I9: M | J9: Production Specialist 1 - Rack level Assembly | K9: D Shift: Salt Lake City - N - 600pm-600a Rotating Sun,Mon,Thurs, Fri/Tues,Wed,Sat (15% Diff) | L9: C125693 | R9: X
A10: FLX0563 | B10: Barbara Garcia (1137177) | C10: P2743382 | D10: 875-37-3884 | E10: Jaimi Maquin | F10: 217227570 | G10: 3854857254 | H10: BL | I10: S | J10: Production Specialist 1 - Cold Room | K10: A Shift: Salt Lake City - Q - 600am-600pm Rotating Tues,Wed,Sat/Sun,Mon, Thurs,Fri | S10: Due to P# not working she is okay being moved for 8/24 class [Spanish]
A11: FLX0580 | B11: Paola Guzman | C11: P2743377 | D11: 016-31-8115 | E11: Maria Brea | F11: 215079760 | G11: 215079760 | H11: BL | I11: S | J11: Production Specialist 1 - Materials | K11: B Shift: Salt Lake City - P - 600pm-600a Rotating Tues,Wed,Sat/Sun,Mon,Thurs,Fri (15% Diff) | L11: C125781 | R11: X
A12: FLX0583 | B12: Dallas Driggers (1156397) | C12: P2743374 | D12: 671-24-8940 | E12: Natalif Lopez | F12: 218820032 | G12: 7026194931 | H12: NM | I12: S | J12: Production Specialist 1 - Cold Room | K12: D Shift: Salt Lake City - N - 600pm-600a Rotating Sun,Mon,Thurs, Fri/Tues,Wed,Sat (15% Diff) | L12: C125784 | R12: X
A13: FLX0588 | B13: Avigail Zamora | C13: P2743369 | D13: 149-89-3674 | E13: Oswaldo Quintero | F13: 230557237 | G13: 3855233259 | H13: JM | I13: L | J13: Production Specialist 1 - Rack level Assembly | K13: D Shift: Salt Lake City - N - 600pm-600a Rotating Sun,Mon,Thurs, Fri/Tues,Wed,Sat (15% Diff) | L13: C125697 | R13: X
A14: FLX0589 | B14: Avigail Zamora | C14: P2743368 | D14: 133-71-8260 | E14: Yoshua Mendosa | F14: 193874161 | G14: 3855493205 | H14: RP | I14: L | J14: Production Specialist 1 - Rack level Assembly | K14: D Shift: Salt Lake City - N - 600pm-600a Rotating Sun,Mon,Thurs, Fri/Tues,Wed,Sat (15% Diff) | L14: C125698 | R14: X
A15: FLX0634 | B15: Jennifer Prudente (1168431) | C15: P2743626 | D15: 858-65-0230 | E15: Karianna Melendez | F15: 230401816 | G15: 8016349052 | H15: NM | I15: S | J15: Production Specialist 1 - Dekit | K15: C Shift: Salt Lake City - O - 600am-600pm Rotating Sun,Mon,Thurs, Fri/Tues,Wed,Sat | S15: Needs to be contacted and moved to 8/24 [Spanish]
A16: FLX0635 | B16: Jennifer Prudente (1168431) | C16: P2743625 | D16: 761-33-8004 | E16: Hernando Frias | F16: 223280294 | G16: 4085926936 | H16: FZ | J16: Production Specialist 1 - Dekit | K16: C Shift: Salt Lake City - O - 600am-600pm Rotating Sun,Mon,Thurs, Fri/Tues,Wed,Sat | S16: Needs to be contacted and moved for another day
A17: FLX0648 | B17: Patricia Puche Curiel | C17: P2743612 | D17: 139-33-5589 | E17: Mariangel Bastidas Rangel | F17: 118877490 | G17: 3854573759 | H17: JY | I17: L | J17: Production Specialist - L10 Repair (Bonepile) | K17: C Shift: Salt Lake City - O - 600am-600pm Rotating Sun,Mon,Thurs, Fri/Tues,Wed,Sat | L17: C125692 | R17: X
A18: FLX0649 | B18: Patricia Puche Curiel | C18: P2743611 | D18: 222-45-6013 | E18: Daniela Rosales Coronado | F18: 230405645 | G18: 3855493205 | H18: JY | I18: M | J18: Production Specialist - L10 Repair (Bonepile) | K18: C Shift: Salt Lake City - O - 600am-600pm Rotating Sun,Mon,Thurs, Fri/Tues,Wed,Sat | L18: C125690 | R18: X
A19: FLX0650 | B19: Patricia Puche Curiel | C19: P2743610 | D19: 035-23-4130 | E19: Yesica Saez | F19: 220532407 | G19: 9176758254 | H19: BL | I19: L | J19: Production Specialist - L10 Repair (Bonepile) | K19: C Shift: Salt Lake City - O - 600am-600pm Rotating Sun,Mon,Thurs, Fri/Tues,Wed,Sat | L19: C125688 | R19: X
A20: FLX0651 | B20: Patricia Puche Curiel | C20: P2743609 | D20: 189-06-1409 | E20: Luisa Rondon | F20: 191065852 | G20: 385-301-1016 | H20: NM | I20: M | J20: Production Specialist - L10 Repair (Bonepile) | K20: C Shift: Salt Lake City - O - 600am-600pm Rotating Sun,Mon,Thurs, Fri/Tues,Wed,Sat | L20: C125709 | R20: X
A21: FLX0652 | B21: Patricia Puche Curiel | C21: P2743608 | D21: 645-43-3520 | E21: Mary Mata | F21: 133925448 | G21: 8019494079 | H21: NM | I21: S | J21: Production Specialist - L10 Repair (Bonepile) | K21: C Shift: Salt Lake City - O - 600am-600pm Rotating Sun,Mon,Thurs, Fri/Tues,Wed,Sat | L21: C125789 | R21: X
A22: FLX0654 | B22: Alexis Rullan | C22: P2743606 | D22: 872-07-9192 | E22: Nancy Llontop | F22: 222820479 | G22: 3854238197 | H22: NM | I22: S | J22: Production Specialist - L10 Repair (Bonepile) | K22: B Shift: Salt Lake City - P - 600pm-600a Rotating Tues,Wed,Sat/Sun,Mon,Thurs,Fri (15% Diff) | L22: C125684 | R22: X
A23: FLX0655 | B23: Alexis Rullan | C23: P2743605 | D23: 629-75-8313 | E23: Yanet Oscanoa | F23: 122873279 | G23: 8014037247 | H23: JM | I23: M | J23: Production Specialist - L10 Repair (Bonepile) | K23: B Shift: Salt Lake City - P - 600pm-600a Rotating Tues,Wed,Sat/Sun,Mon,Thurs,Fri (15% Diff) | L23: C125686 | R23: X
A24: FLX0659 | B24: Angel Tirado | C24: Aurora Lamas Arellano / P2716002 | D24: 069-45-4779 | E24: Carmen Gomez | F24: 95698712 | G24: 801-5579623 | H24: RP | I24: M | J24: Production Specialist 1 - Materials | K24: A Shift: Salt Lake City - Q - 600am-600pm Rotating Tues,Wed,Sat/Sun,Mon, Thurs,Fri | L24: C125694 | R24: X
A25: FLX0660 | B25: Jennifer Prudente | C25: Gabriela A Martinez / P2725262 | D25: 852-22-3104 | E25: Junior Zabala | F25: 230568678 | G25: 8018357759 | I25: XL | J25: Production Specialist 1 - Dekit | K25: B Shift: Salt Lake City - P - 600pm-600a Rotating Tues,Wed,Sat/Sun,Mon,Thurs,Fri (15% Diff) | L25: C125695 | R25: X
A26: FLX0661 | B26: Yaritza Garza | C26: Johnathan Van Dusen / P2687532 | D26: 743-48-5767 | E26: Maria Elena Camarillo Alvarado | F26: 182863558 | G26: 3852239443 | H26: FZ | I26: M | J26: Production Specialist 1 - Cold Room | K26: C Shift: Salt Lake City - O - 600am-600pm Rotating Sun,Mon,Thurs, Fri/Tues,Wed,Sat | L26: C125713 | R26: X
A27: FLX0662 | B27: Alondra Landin | C27: Jose Manuel Marquina / P2689830 | D27: 187-06-3703 | E27: Rosmar Perale | F27: 176312644 | G27: 3854636039 | H27: RP | I27: M | J27: Production Specialist 1 - Mechanical Assembly | K27: A Shift: Salt Lake City - Q - 600am-600pm Rotating Tues,Wed,Sat/Sun,Mon, Thurs,Fri | L27: C125696
A28: FLX0663 | B28: Angel Tirado | C28: Josue Salgado / P2687202 | D28: 651-92-6411 | E28: Willy Alvarez | F28: 182813001 | G28: 3855499424 | H28: NM | I28: XL | J28: Production Specialist 1 - Materials | K28: A Shift: Salt Lake City - Q - 600am-600pm Rotating Tues,Wed,Sat/Sun,Mon, Thurs,Fri | L28: C125699 | R28: x
A29: FLX0664 | B29: Jose Gonzalez | C29: Zuleima Del Carmen Pereira / P2689186 | D29: 689-45-1561 | E29: Glenda Pilay | F29: 176269991 | G29: 385-573-8074 | H29: SR | I29: L | J29: Production Specialist 1 - Mechanical Assembly | K29: A Shift: Salt Lake City - Q - 600am-600pm Rotating Tues,Wed,Sat/Sun,Mon, Thurs,Fri | L29: C125700 | R29: x
A30: FLX0665 | B30: Beatriz Hernandez | C30: Selena Morales / P2654581 | D30: 761-33-8004 | E30: Maribeth Castilla | F30: 190427449 | G30: 2678893261 | H30: DR | I30: L | J30: Production Specialist 1 - Mechanical Assembly | K30: C Shift: Salt Lake City - O - 600am-600pm Rotating Sun,Mon,Thurs, Fri/Tues,Wed,Sat | L30: C125701 | R30: x
A31: FLX0666 | B31: Dallas Driggers | C31: Nguyen T Nguyen / P2658703 | D31: 388-71-5477 | E31: Valeria Sandoval | F31: 215128480 | G31: 5598714822 | H31: EP | J31: Production Specialist 1 - Cold Room | K31: D Shift: Salt Lake City - N - 600pm-600a Rotating Sun,Mon,Thurs, Fri/Tues,Wed,Sat (15% Diff) | L31: C125791 | R31: x
A32: FLX0667 | B32: DANIEL FUENTES | C32: Leydi Sanchez / P5001520 | D32: 342-13-5382 | E32: Edith Plancarte | F32: 95897214 | G32: 4159372742 | H32: JM | I32: M | J32: Production Specialist 1 - Mechanical Assembly | K32: D Shift: Salt Lake City - N - 600pm-600a Rotating Sun,Mon,Thurs, Fri/Tues,Wed,Sat (15% Diff) | L32: C125703 | R32: x
A33: FLX0668 | B33: Dallas Driggers | C33: Karen A Rodriguez Monroy / P2700719 | D33: 662-51-8652 | E33: Sibel parra | F33: 144425415 | G33: 3855603543 | H33: BL | I33: M | J33: Production Specialist 1 - Cold Room | K33: D Shift: Salt Lake City - N - 600pm-600a Rotating Sun,Mon,Thurs, Fri/Tues,Wed,Sat (15% Diff) | L33: C125792 | R33: x
A34: FLX0669 | B34: Deja Atwood | C34: Yufrecka Bersovine / P2688520 | D34: 275-57-7013 | E34: Liliana Ramirez Ernst | F34: 194664196 | G34: 3853011688 | H34: NM | I34: M | J34: Production Specialist 1 - Mechanical Assembly | K34: A Shift: Salt Lake City - Q - 600am-600pm Rotating Tues,Wed,Sat/Sun,Mon, Thurs,Fri | L34: C125705 | R34: x
A35: FLX0670 | B35: Sanel Kudic | C35: Kary L Carter / P2727312 | D35: 634-46-5650 | E35: Jose Castellano Suarez | F35: 230757142 | G35: 7125094299 | H35: FZ | I35: XL | J35: Production Specialist 1 - Materials | K35: B Shift: Salt Lake City - P - 600pm-600a Rotating Tues,Wed,Sat/Sun,Mon,Thurs,Fri (15% Diff) | L35: C125708 | R35: x
A36: FLX0671 | B36: Yaritza Garza | C36: Hector Flores Gonzalez / P2720902 | D36: 065-21-3194 | E36: Julio Perez Olivar | F36: 139298190 | G36: 8019030227 | H36: RP | I36: L | J36: Production Specialist 1 - Cold Room | K36: C Shift: Salt Lake City - O - 600am-600pm Rotating Sun,Mon,Thurs, Fri/Tues,Wed,Sat | L36: C125710
A37: FLX0672 | B37: Itzayana Maupouje | C37: Milagros Bastardo / P2687512 | D37: 326-39-7550 | E37: Nelson Madueno | F37: 218770711 | G37: (786) 906-3080 | H37: RP | I37: L | J37: Production Specialist 1 - Mechanical Assembly | K37: D Shift: Salt Lake City - N - 600pm-600a Rotating Sun,Mon,Thurs, Fri/Tues,Wed,Sat (15% Diff) | L37: C125711 | R37: x

Sheet 8.13.26
A1: English/Bilingual Starts ONLY
A2: P CODE | B2: Req # | C2: Supervisor | F2: SSN | G2: Employee Name (must match Bold) | H2: Bold ID | I2: Phone # | J2: Recruiter | K2: Shirt Size | L2: Title | M2: Schedule | N2: C-Number | O2: BG | P2: I-9 | Q2: E-Verify | R2: Flex AA | S2: Onboarding Tasks | T2: Offer Letter | U2: NOTES
A4: P2743634 | B4: FLX0626 | C4: Jennifer Prudente (1168431) | F4: 093-49-5184 | G4: Diego Garcia | H4: 155276815 | I4: 8018670654 | J4: FZ | K4: L | L4: Production Specialist 1 - Dekit | M4: A Shift: Salt Lake City - Q - 600am-600pm Rotating Tues,Wed,Sat/Sun,Mon, Thurs,Fri | N4: C125592 | S4: x
A5: P2743633 | B5: FLX0627 | C5: Jennifer Prudente (1168431) | F5: 647-98-7139 | G5: Joseph R Hurtado | H5: 227754054 | I5: 8014034364 | J5: JY | K5: XXL | L5: Production Specialist 1 - Dekit | M5: A Shift: Salt Lake City - Q - 600am-600pm Rotating Tues,Wed,Sat/Sun,Mon, Thurs,Fri | N5: C125596 | S5: x
A6: P2743632 | B6: FLX0628 | C6: Jennifer Prudente (1168431) | F6: 863-17-9098 | G6: Santos E Rodriguez Torres | H6: 95711490 | I6: 8019413095 | J6: FZ | K6: S | L6: Production Specialist 1 - Dekit | M6: A Shift: Salt Lake City - Q - 600am-600pm Rotating Tues,Wed,Sat/Sun,Mon, Thurs,Fri | N6: C125597 | S6: X
A7: P2743631 | B7: FLX0629 | C7: Jennifer Prudente (1168431) | F7: 553-99-6297 | G7: Hector E Mosqueda | H7: 223360986 | I7: (562) 200-3414 | J7: DR | K7: XL | L7: Production Specialist 1 - Dekit | M7: A Shift: Salt Lake City - Q - 600am-600pm Rotating Tues,Wed,Sat/Sun,Mon, Thurs,Fri | N7: C125635 | S7: x
A8: P2743630 | B8: FLX0630 | C8: Jennifer Prudente (1168431) | F8: 835296844 | G8: Willian Piccone | H8: 217233983 | I8: 3853541676 | J8: RP | K8: L | L8: Production Specialist 1 - Dekit | M8: C Shift: Salt Lake City - O - 600am-600pm Rotating Sun,Mon,Thurs, Fri/Tues,Wed,Sat | N8: C125600
A9: P2743629 | B9: FLX0631 | C9: Jennifer Prudente (1168431) | F9: 888-18-4458 | G9: Miguel Rivas | H9: 187557818 | I9: 385-580-4318 | J9: NM | K9: XXXXL | L9: Production Specialist 1 - Dekit | M9: C Shift: Salt Lake City - O - 600am-600pm Rotating Sun,Mon,Thurs, Fri/Tues,Wed,Sat | N9: C125610 | S9: x
A10: P2743628 | B10: FLX0632 | C10: Jennifer Prudente (1168431) | F10: 647-76-9145 | G10: Ali M Osman | H10: 95659911 | I10: (801) 953-7958 | J10: GKW | K10: XL | L10: Production Specialist 1 - Dekit | M10: C Shift: Salt Lake City - O - 600am-600pm Rotating Sun,Mon,Thurs, Fri/Tues,Wed,Sat | N10: C125636 | S10: x
A11: P2743627 | B11: FLX0633 | C11: Jennifer Prudente (1168431) | F11: 835-29-6844 | G11: Willian Piccone | H11: 217233983 | I11: 3853541676 | J11: RP | K11: L | L11: Production Specialist 1 - Dekit | M11: C Shift: Salt Lake City - O - 600am-600pm Rotating Sun,Mon,Thurs, Fri/Tues,Wed,Sat | N11: C125633
A12: P2743626 | B12: FLX0634 | C12: Jennifer Prudente (1168431) | L12: Production Specialist 1 - Dekit | M12: C Shift: Salt Lake City - O - 600am-600pm Rotating Sun,Mon,Thurs, Fri/Tues,Wed,Sat
A13: P2743625 | B13: FLX0635 | C13: Jennifer Prudente (1168431) | L13: Production Specialist 1 - Dekit | M13: C Shift: Salt Lake City - O - 600am-600pm Rotating Sun,Mon,Thurs, Fri/Tues,Wed,Sat
A14: P2743624 | B14: FLX0636 | C14: Jennifer Prudente (1168431) | F14: 758370850 | G14: Umutoni Uwera | H14: 191048914 | I14: 8019703845 | J14: JY | K14: M | L14: Production Specialist 1 - Dekit | M14: B Shift: Salt Lake City - P - 600pm-600a Rotating Tues,Wed,Sat/Sun,Mon,Thurs,Fri (15% Diff) | N14: C125632 | S14: x
A15: P2743623 | B15: FLX0637 | C15: Jennifer Prudente (1168431) | F15: 647-06-3213 | G15: Thavone Noavongsak | H15: 177934156 | I15: 801-680-7310 | J15: DR | K15: L | L15: Production Specialist 1 - Dekit | M15: B Shift: Salt Lake City - P - 600pm-600a Rotating Tues,Wed,Sat/Sun,Mon,Thurs,Fri (15% Diff) | N15: C125629 | S15: x
A16: P2743622 | B16: FLX0638 | C16: Jennifer Prudente (1168431) | F16: 528-61-6777 | G16: Molonai Muamoholeva | H16: 227168732 | I16: 385 210-6656 | J16: GKW | K16: XXL | L16: Production Specialist 1 - Dekit | M16: B Shift: Salt Lake City - P - 600pm-600a Rotating Tues,Wed,Sat/Sun,Mon,Thurs,Fri (15% Diff) | N16: C125631 | S16: x
A17: P2743621 | B17: FLX0639 | C17: Jennifer Prudente (1168431) | F17: 646-82-3613 | G17: Brandon Gonzalez | H17: 228896924 | I17: 3854187532 | J17: EP | K17: XXXL | L17: Production Specialist 1 - Dekit | M17: B Shift: Salt Lake City - P - 600pm-600a Rotating Tues,Wed,Sat/Sun,Mon,Thurs,Fri (15% Diff) | N17: C125634 | S17: x
A18: P2743620 | B18: FLX0640 | C18: Jennifer Prudente (1168431) | F18: 647-50-0764 | G18: Jesse Ren | H18: 119451955 | I18: 8019000047 | J18: NM | K18: L | L18: Production Specialist 1 - Dekit | M18: B Shift: Salt Lake City - P - 600pm-600a Rotating Tues,Wed,Sat/Sun,Mon,Thurs,Fri (15% Diff) | N18: C125611 | S18: x
A19: P2743619 | B19: FLX0641 | C19: Jennifer Prudente (1168431) | F19: 528-49-7146 | G19: Chad Cadland | H19: 167453188 | I19: 8015746280 | J19: NM | K19: L | L19: Production Specialist 1 - Dekit | M19: D Shift: Salt Lake City - N - 600pm-600a Rotating Sun,Mon,Thurs, Fri/Tues,Wed,Sat (15% Diff) | N19: C125612 | S19: x
A20: P2743618 | B20: FLX0642 | C20: Jennifer Prudente (1168431) | F20: 647-94-5480 | G20: Lucas Norris | H20: 225274848 | I20: +1 435 277-9202 | J20: DR | K20: M | L20: Production Specialist 1 - Dekit | M20: D Shift: Salt Lake City - N - 600pm-600a Rotating Sun,Mon,Thurs, Fri/Tues,Wed,Sat (15% Diff) | N20: C125609 | S20: x
A21: P2743617 | B21: FLX0643 | C21: Jennifer Prudente (1168431) | F21: 168872690 | G21: Adut Makuei | H21: 114298261 | I21: 385-267-5635 | J21: RP | K21: S | L21: Production Specialist 1 - Dekit | M21: D Shift: Salt Lake City - N - 600pm-600a Rotating Sun,Mon,Thurs, Fri/Tues,Wed,Sat (15% Diff) | N21: C125607 | S21: x
A22: P2743616 | B22: FLX0644 | C22: Jennifer Prudente (1168431) | F22: 646-66-6521 | G22: Amy Hernandez Flores | H22: 217975979 | I22: 3856016483 | J22: NM | K22: S | L22: Production Specialist 1 - Dekit | M22: D Shift: Salt Lake City - N - 600pm-600a Rotating Sun,Mon,Thurs, Fri/Tues,Wed,Sat (15% Diff) | N22: C125604 | S22: x
A23: P2743615 | B23: FLX0645 | C23: Jennifer Prudente (1168431) | G23: Eliud Vargas | H23: 230549728 | I23: 3854999817 | J23: NM | K23: L | L23: Production Specialist 1 - Dekit | M23: D Shift: Salt Lake City - N - 600pm-600a Rotating Sun,Mon,Thurs, Fri/Tues,Wed,Sat (15% Diff) | N23: C125602 | S23: x
A24: P2743614 | B24: FLX0646 | C24: Jennifer Prudente (1168431) | F24: 820038147 | G24: Claudia La Rosa Quispe | H24: 185852924 | I24: 3854794854 | J24: JY | L24: Production Specialist 1 - Dekit | M24: D Shift: Salt Lake City - N - 600pm-600a Rotating Sun,Mon,Thurs, Fri/Tues,Wed,Sat (15% Diff) | N24: C125601
A25: P2743613 | B25: FLX0647 | C25: Jennifer Paz (1166697) | F25: 646-62-4034 | G25: Tommy Trujillo | H25: 95696069 | I25: 8016381761 | J25: GKW | K25: L | L25: Production Specialist - L10 Repair (Bonepile) | M25: A Shift: Salt Lake City - Q - 600am-600pm Rotating Tues,Wed,Sat/Sun,Mon, Thurs,Fri | N25: C125627
A26: P2743611 | B26: FLX0649 | C26: Patricia Puche Curiel | L26: Production Specialist - L10 Repair (Bonepile) | M26: C Shift: Salt Lake City - O - 600am-600pm Rotating Sun,Mon,Thurs, Fri/Tues,Wed,Sat
A27: P2743610 | B27: FLX0650 | C27: Patricia Puche Curiel | L27: Production Specialist - L10 Repair (Bonepile) | M27: C Shift: Salt Lake City - O - 600am-600pm Rotating Sun,Mon,Thurs, Fri/Tues,Wed,Sat
A28: P2743609 | B28: FLX0651 | C28: Patricia Puche Curiel | L28: Production Specialist - L10 Repair (Bonepile) | M28: C Shift: Salt Lake City - O - 600am-600pm Rotating Sun,Mon,Thurs, Fri/Tues,Wed,Sat
A29: P2743608 | B29: FLX0652 | C29: Patricia Puche Curiel | L29: Production Specialist - L10 Repair (Bonepile) | M29: C Shift: Salt Lake City - O - 600am-600pm Rotating Sun,Mon,Thurs, Fri/Tues,Wed,Sat
A30: P2743607 | B30: FLX0653 | C30: Alexis Rullan | F30: 792-35-1566 | G30: Dao Cao | H30: 201701566 | I30: 3854445090 | J30: DR | K30: M | L30: Production Specialist - L10 Repair (Bonepile) | M30: B Shift: Salt Lake City - P - 600pm-600a Rotating Tues,Wed,Sat/Sun,Mon,Thurs,Fri (15% Diff) | N30: C125603 | S30: x
A31: P2743606 | B31: FLX0654 | C31: Alexis Rullan | L31: Production Specialist - L10 Repair (Bonepile) | M31: B Shift: Salt Lake City - P - 600pm-600a Rotating Tues,Wed,Sat/Sun,Mon,Thurs,Fri (15% Diff)
A32: P2743605 | B32: FLX0655 | C32: Alexis Rullan | L32: Production Specialist - L10 Repair (Bonepile) | M32: B Shift: Salt Lake City - P - 600pm-600a Rotating Tues,Wed,Sat/Sun,Mon,Thurs,Fri (15% Diff)
A33: P2743612 | B33: FLX0648 | C33: Patricia Puche Curiel | L33: Production Specialist - L10 Repair (Bonepile) | M33: C Shift: Salt Lake City - O - 600am-600pm Rotating Sun,Mon,Thurs, Fri/Tues,Wed,Sat
A34: P2743604 | B34: FLX0656 | C34: Alexis Rullan | F34: 146599684 | G34: Glody Tumbwa | H34: 149731745 | I34: 2176128184 | J34: JM | K34: L | L34: Production Specialist - L10 Repair (Bonepile) | M34: B Shift: Salt Lake City - P - 600pm-600a Rotating Tues,Wed,Sat/Sun,Mon,Thurs,Fri (15% Diff) | N34: C125605
A35: P2743603 | B35: FLX0657 | C35: Yalia Driggers (1153165) | F35: 95649182 | G35: Jamoson Lomax | H35: 95649182 | I35: 3852663176 | J35: RP | K35: L | L35: Production Specialist - L10 Repair (Bonepile) | M35: D Shift: Salt Lake City - N - 600pm-600a Rotating Sun,Mon,Thurs, Fri/Tues,Wed,Sat (15% Diff) | N35: C125606 | S35: x
A36: P2743602 | B36: FLX0658 | C36: Yalia Driggers (1153165) | F36: 646-56-2851 | G36: Eliud Vargas | H36: 230549728 | I36: 3854999817 | J36: NM | K36: L | L36: Production Specialist - L10 Repair (Bonepile) | M36: D Shift: Salt Lake City - N - 600pm-600a Rotating Sun,Mon,Thurs, Fri/Tues,Wed,Sat (15% Diff) | N36: C125608 | S36: x

Sheet 8.10.26
A1: SSN | B1: P CODE | C1: Req # | D1: Supervisor | E1: Employee Name (must match Bold) | F1: Bold ID | G1: Phone # | H1: Recruiter | I1: Shirt Size | J1: Title | K1: Schedule | L1: C-Number | M1: BG | N1: I-9 | O1: E-Verify | P1: Flex AA | Q1: Onboarding Tasks | R1: Offer Letter | S1: NOTES
A2: 207-96-3122 | B2: P2743381 | C2: FLX0564 | D2: Barbara Garcia (1137177) | E2: Aminta Perez | F2: 198499602 | G2: 3855494171 | H2: FZ | I2: L | J2: Production Specialist 1 - Cold Room | K2: A Shift: Salt Lake City - Q - 600am-600pm Rotating Tues,Wed,Sat/Sun,Mon, Thurs,Fri | L2: C125542
A3: 029-61-2800 | B3: P2743399 | C3: FLX0546 | D3: Cristian Vega (1135987) | E3: Ana Fernandez | F3: 148985292 | G3: 3855068326 | H3: BL | I3: M | J3: Production Specialist 1 - Rack level Assembly | K3: B Shift: Salt Lake City - P - 600pm-600a Rotating Tues,Wed,Sat/Sun,Mon,Thurs,Fri (15% Diff) | L3: C125515
B4: P2743377 | C4: FLX0580 | D4: Paola Guzman | E4: Anais Faria | F4: 227227008 | G4: 3854183056 | J4: Production Specialist 1 - Materials | K4: B Shift: Salt Lake City - P - 600pm-600a Rotating Tues,Wed,Sat/Sun,Mon,Thurs,Fri (15% Diff)
A5: 861-47-7196 | B5: P2743397 | C5: FLX0548 | D5: Julissa Sencion (1154184) | E5: Andres Caruci | F5: 226544093 | G5: 3038886330 | H5: EP | I5: XL | J5: Production Specialist 1 - Rack level Assembly | K5: C Shift: Salt Lake City - O - 600am-600pm Rotating Sun,Mon,Thurs, Fri/Tues,Wed,Sat | L5: C125518
A6: 710-38-5875 | B6: P2743395 | C6: FLX0550 | D6: Julissa Sencion (1154184) | E6: Calixto Lozada | F6: 222719839 | G6: 3854183265 | H6: FZ | I6: L | J6: Production Specialist 1 - Rack level Assembly | K6: C Shift: Salt Lake City - O - 600am-600pm Rotating Sun,Mon,Thurs, Fri/Tues,Wed,Sat | L6: C125525
A7: 222-73-0641 | B7: P2743376 | C7: FLX0581 | D7: Mel Kellar (1142020) | E7: Cindy P Rosero | F7: 176857111 | G7: 3852275804 | H7: JM | I7: L | J7: Production Specialist 1 - Materials | K7: D Shift: Salt Lake City - N - 600pm-600a Rotating Sun,Mon,Thurs, Fri/Tues,Wed,Sat (15% Diff) | L7: C125551
A8: 097-37-6703 | B8: P2743418 | C8: FLX0526 | D8: Deja Atwood (1153147) | E8: Criz D Luna | F8: 182835613 | G8: 801-205-8158 | H8: FZ | I8: M | J8: Production Specialist 1 - Mechanical Assembly | K8: A Shift: Salt Lake City - Q - 600am-600pm Rotating Tues,Wed,Sat/Sun,Mon, Thurs,Fri | L8: C125459
A9: 646-74-9269 | B9: P2743415 | C9: FLX0529 | D9: Deja Atwood (1153147) | E9: Daniela Guadalupe Barranco | F9: 230396859 | G9: 8014159573 | H9: FZ | I9: L | J9: Production Specialist 1 - Mechanical Assembly | K9: A Shift: Salt Lake City - Q - 600am-600pm Rotating Tues,Wed,Sat/Sun,Mon, Thurs,Fri | L9: C125462
A10: 850-68-1379 | B10: P2743416 | C10: FLX0528 | D10: Deja Atwood (1153147) | E10: Ericka Galeana Lopez | F10: 222819332 | G10: 3852678214 | H10: FZ | I10: S | J10: Production Specialist 1 - Mechanical Assembly | K10: A Shift: Salt Lake City - Q - 600am-600pm Rotating Tues,Wed,Sat/Sun,Mon, Thurs,Fri | L10: C125461
A11: 010-13-0386 | B11: P2743401 | C11: FLX0544 | D11: Douglas Camargo (114508) | E11: Florliluz Barroso | F11: 147463926 | G11: 3857700274 | H11: BL | I11: L | J11: Production Specialist 1 - Rack level Assembly | K11: A Shift: Salt Lake City - Q - 600am-600pm Rotating Tues,Wed,Sat/Sun,Mon, Thurs,Fri | L11: C125506
A12: 116-25-7122 | B12: P2743422 | C12: FLX0522 | D12: Dario Mendez Toyo (1174155) | E12: Francheska Mota | F12: 219100332 | G12: 3852522928 | H12: BL | I12: XL | J12: Production Specialist 1 - Materials | K12: C Shift: Salt Lake City - O - 600am-600pm Rotating Sun,Mon,Thurs, Fri/Tues,Wed,Sat | L12: C125456
A13: 777-20-8015 | B13: P2743406 | C13: FLX0538 | D13: Itzayana Maupouje (1224330) | E13: Gabina Carachure | F13: 217287649 | G13: 8019204459 | H13: FZ | I13: M | J13: Production Specialist 1 - Mechanical Assembly | K13: D Shift: Salt Lake City - N - 600pm-600a Rotating Sun,Mon,Thurs, Fri/Tues,Wed,Sat (15% Diff) | L13: C125479
A14: 318-95-5312 | B14: P2743385 | C14: FLX0560 | D14: Avigail Zamora | E14: Gabriela Aguilar Gentil | F14: 230399050 | G14: 3858817560 | H14: NM | I14: M | J14: Production Specialist 1 - Rack level Assembly | K14: D Shift: Salt Lake City - N - 600pm-600a Rotating Sun,Mon,Thurs, Fri/Tues,Wed,Sat (15% Diff) | L14: C125558
A15: 053-25-4354 | B15: P2743392 | C15: FLX0553 | D15: Avigail Zamora | E15: Gabriela Barrios | F15: 154754659 | G15: 3852668083 | H15: BL | I15: S | J15: Production Specialist 1 - Rack level Assembly | K15: D Shift: Salt Lake City - N - 600pm-600a Rotating Sun,Mon,Thurs, Fri/Tues,Wed,Sat (15% Diff) | L15: C125531
A16: 646-50-2185 | B16: P2743396 | C16: FLX0549 | D16: Julissa Sencion (1154184) | E16: Gabriela Martinez | F16: 95676314 | G16: 8018155063 | H16: DR | I16: XL | J16: Production Specialist 1 - Rack level Assembly | K16: C Shift: Salt Lake City - O - 600am-600pm Rotating Sun,Mon,Thurs, Fri/Tues,Wed,Sat | L16: C125521
A17: 125-49-9271 | B17: P2743417 | C17: FLX0527 | D17: Deja Atwood (1153147) | E17: Gledy J Camcaho Lambrano | F17: 189705387 | G17: 3854367384 | H17: DR | I17: L | J17: Production Specialist 1 - Mechanical Assembly | K17: A Shift: Salt Lake City - Q - 600am-600pm Rotating Tues,Wed,Sat/Sun,Mon, Thurs,Fri | L17: C125460
A18: 647-98-4023 | B18: P2743403 | C18: FLX0542 | D18: Douglas Camargo (114508) | E18: Ilia Romero Linares | F18: 228805148 | G18: 3853026775 | H18: EP | I18: M | J18: Production Specialist 1 - Rack level Assembly | K18: A Shift: Salt Lake City - Q - 600am-600pm Rotating Tues,Wed,Sat/Sun,Mon, Thurs,Fri | L18: C125487
A19: 202-25-8303 | B19: P2743372 | C19: FLX0585 | D19: Dallas Driggers (1156397) | E19: Jaidirys Calderon | F19: 223360858 | G19: 3854363473 | H19: CN | I19: M | J19: Production Specialist 1 - Cold Room | K19: D Shift: Salt Lake City - N - 600pm-600a Rotating Sun,Mon,Thurs, Fri/Tues,Wed,Sat (15% Diff) | L19: C125555
A20: 726-70-9956 | B20: P2743390 | C20: FLX0555 | D20: Avigail Zamora | E20: Jary Pinzon | F20: 218435565 | G20: 8016081065 | H20: BL | I20: XS | J20: Production Specialist 1 - Rack level Assembly | K20: D Shift: Salt Lake City - N - 600pm-600a Rotating Sun,Mon,Thurs, Fri/Tues,Wed,Sat (15% Diff) | L20: C125533
... A22: 273-41-4734 | B22: P2743383 | C22: FLX0562 | D22: Barbara Garcia (1137177) | E22: Jessica Paez | F22: 183109845 | G22: 3855489620 | H22: FZ | I22: S | J22: Production Specialist 1 - Cold Room | K22: A Shift: Salt Lake City - Q - 600am-600pm Rotating Tues,Wed,Sat/Sun,Mon, Thurs,Fri | L22: C125540
A23: 892-08-6999 | B23: P2743410 | C23: FLX0534 | D23: DANIEL FUENTES (1198897) | E23: Jesus Villarreal Blanco | F23: 115655543 | G23: (385) 242-0947 | H23: EP | I23: L | J23: Production Specialist 1 - Mechanical Assembly | K23: D Shift: Salt Lake City - N - 600pm-600a Rotating Sun,Mon,Thurs, Fri/Tues,Wed,Sat (15% Diff) | L23: C125475
A24: 365979882 | B24: P2743394 | C24: FLX0551 | D24: Julissa Sencion (1154184) | E24: Juan A La Rosa | F24: 223901961 | G24: 8016612459 | H24: RP | I24: M | J24: Production Specialist 1 - Rack level Assembly | K24: C Shift: Salt Lake City - O - 600am-600pm Rotating Sun,Mon,Thurs, Fri/Tues,Wed,Sat | L24: C125527
A25: 742-11-7691 | B25: P2743405 | C25: FLX0540 | D25: Douglas Camargo (114508) | E25: Juledwin Quero | F25: 221637295 | G25: 3856257344 | H25: NM | I25: S | J25: Production Specialist 1 - Rack level Assembly | K25: A Shift: Salt Lake City - Q - 600am-600pm Rotating Tues,Wed,Sat/Sun,Mon, Thurs,Fri | L25: C125482
A26: 507-61-4315 | B26: P2743387 | C26: FLX0558 | D26: Avigail Zamora | E26: Juleisy R Gorozabel | F26: 198348610 | G26: 929-331-7372 | H26: FZ | I26: S | J26: Production Specialist 1 - Rack level Assembly | K26: D Shift: Salt Lake City - N - 600pm-600a Rotating Sun,Mon,Thurs, Fri/Tues,Wed,Sat (15% Diff) | L26: C125538
A27: BG Pending | B27: P2743421 | C27: FLX0523 | D27: Dario Mendez Toyo (1174155) | E27: Julio Perez Olivar | F27: 139298190 | G27: 8019030227 | H27: EP | I27: XL | J27: Production Specialist 1 - Materials | K27: C Shift: Salt Lake City - O - 600am-600pm Rotating Sun,Mon,Thurs, Fri/Tues,Wed,Sat | L27: C125445
A28: 646-90-5389 | B28: P2743414 | C28: FLX0530 | D28: Deja Atwood (1153147) | E28: Kimberly Barranco | F28: 230396914 | G28: 8016964110 | H28: FZ | I28: L | J28: Production Specialist 1 - Mechanical Assembly | K28: A Shift: Salt Lake City - Q - 600am-600pm Rotating Tues,Wed,Sat/Sun,Mon, Thurs,Fri | L28: C125463
A29: 322-89-0316 | B29: P2743413 | C29: FLX0531 | D29: Cristian Vega (1135987) | E29: Lorgenis Ramirez | F29: 146757739 | G29: 3855071609 | H29: NM | I29: L | J29: Production Specialist 1 - Mechanical Assembly | K29: B Shift: Salt Lake City - P - 600pm-600a Rotating Tues,Wed,Sat/Sun,Mon,Thurs,Fri (15% Diff) | L29: C125465
A30: 156-53-2151 | B30: P2743402 | C30: FLX0543 | D30: Douglas Camargo (114508) | E30: Luis Suarez | F30: 218766079 | G30: 385-507-0855 | H30: NM | I30: M | J30: Production Specialist 1 - Rack level Assembly | K30: A Shift: Salt Lake City - Q - 600am-600pm Rotating Tues,Wed,Sat/Sun,Mon, Thurs,Fri | L30: C125490
A31: 279-47-6243 | B31: P2743370 | C31: FLX0587 | D31: Dallas Driggers (1156397) | E31: Marco Antonio Leon Cedeno | F31: 225939246 | G31: 385-616-2538 | H31: FZ | I31: XL | J31: Production Specialist 1 - Cold Room | K31: D Shift: Salt Lake City - N - 600pm-600a Rotating Sun,Mon,Thurs, Fri/Tues,Wed,Sat (15% Diff) | L31: C125557
A32: 324-13-2898 | B32: P2743382 | C32: FLX0563 | D32: Barbara Garcia (1137177) | E32: Maria Aray | F32: 167482313 | G32: (385)215-5995 | H32: NM | I32: L | J32: Production Specialist 1 - Cold Room | K32: A Shift: Salt Lake City - Q - 600am-600pm Rotating Tues,Wed,Sat/Sun,Mon, Thurs,Fri | L32: C125541
A33: 018-39-2444 | B33: P2743375 | C33: FLX0582 | D33: Dallas Driggers (1156397) | E33: Maria Nunez | F33: 128702228 | G33: 8018227840 | H33: JM | I33: L | J33: Production Specialist 1 - Cold Room | K33: D Shift: Salt Lake City - N - 600pm-600a Rotating Sun,Mon,Thurs, Fri/Tues,Wed,Sat (15% Diff) | L33: C125552
A34: 299-89-7798 | B34: P2743412 | C34: FLX0532 | D34: Valeria Mendez (1181800) | E34: Massiel Zabala | F34: 112007733 | G34: 801-564-0825 | H34: BL | I34: L | J34: Production Specialist 1 - Mechanical Assembly | K34: C Shift: Salt Lake City - O - 600am-600pm Rotating Sun,Mon,Thurs, Fri/Tues,Wed,Sat | L34: C125466
A35: 647-07-1154 | B35: P2743374 | C35: FLX0583 | D35: Dallas Driggers (1156397) | E35: Michael Fabela | F35: 203353201 | G35: 385 536 0473 | H35: GKW | I35: XL | J35: Production Specialist 1 - Cold Room | K35: D Shift: Salt Lake City - N - 600pm-600a Rotating Sun,Mon,Thurs, Fri/Tues,Wed,Sat (15% Diff) | L35: C125553
A36: 243-87-3618 | B36: P2743409 | C36: FLX0535 | D36: DANIEL FUENTES (1198897) | E36: Miriam Gonzalez Ortega | F36: 213299373 | G36: 3853941867 | H36: NM | I36: M | J36: Production Specialist 1 - Mechanical Assembly | K36: D Shift: Salt Lake City - N - 600pm-600a Rotating Sun,Mon,Thurs, Fri/Tues,Wed,Sat (15% Diff) | L36: C125476
A37: 135-91-1468 | B37: P2743388 | C37: FLX0557 | D37: Avigail Zamora | E37: Nailiceth C Pirela | F37: 142382758 | G37: 3855607900 | H37: CN | I37: L | J37: Production Specialist 1 - Rack level Assembly | K37: D Shift: Salt Lake City - N - 600pm-600a Rotating Sun,Mon,Thurs, Fri/Tues,Wed,Sat (15% Diff) | L37: C125536
A38: 797-48-9157 | B38: P2743393 | C38: FLX0552 | D38: Julissa Sencion (1154184) | E38: Nancy Quispe Idme De La Rosa | F38: 222685657 | G38: 8016611845 | H38: JY | I38: L | J38: Production Specialist 1 - Rack level Assembly | K38: C Shift: Salt Lake City - O - 600am-600pm Rotating Sun,Mon,Thurs, Fri/Tues,Wed,Sat | L38: C125529
A39: 846-77-3813 | B39: P2743400 | C39: FLX0545 | D39: Douglas Camargo (114508) | E39: Nathalia Blanca | F39: 133836166 | G39: 3852556511 | H39: DR | I39: M | J39: Production Specialist 1 - Rack level Assembly | K39: A Shift: Salt Lake City - Q - 600am-600pm Rotating Tues,Wed,Sat/Sun,Mon, Thurs,Fri | L39: C125513
A40: 003-61-0657 | B40: P2743386 | C40: FLX0559 | D40: Avigail Zamora | E40: Nauro Villalobos | F40: 223254823 | G40: 3855429894 | H40: FZ | I40: XXXL | J40: Production Specialist 1 - Rack level Assembly | K40: D Shift: Salt Lake City - N - 600pm-600a Rotating Sun,Mon,Thurs, Fri/Tues,Wed,Sat (15% Diff) | L40: C125547
A41: 876568271 | B41: P2743407 | C41: FLX0537 | D41: Itzayana Maupouje (1224330) | E41: NIcolas Rodriguez Galvis | F41: 221152087 | G41: 801-635-9892 | H41: RP | I41: M | J41: Production Specialist 1 - Mechanical Assembly | K41: D Shift: Salt Lake City - N - 600pm-600a Rotating Sun,Mon,Thurs, Fri/Tues,Wed,Sat (15% Diff) | L41: C125510
A42: 732-30-4764 | B42: P2743423 | C42: FLX0521 | D42: Dario Mendez Toyo (1174155) | E42: Omar Gomez Moreno | F42: 194454010 | G42: 385-588-1278 | H42: FZ | I42: L | J42: Production Specialist 1 - Materials | K42: C Shift: Salt Lake City - O - 600am-600pm Rotating Sun,Mon,Thurs, Fri/Tues,Wed,Sat | L42: C125422
A43: BG Pending | B43: P2743420 | C43: FLX0524 | D43: Deja Atwood (1153147) | E43: Orlando Rivero Perez | F43: 147534789 | G43: 3852423246 | H43: DR | I43: XL | J43: Production Specialist 1 - Mechanical Assembly | K43: A Shift: Salt Lake City - Q - 600am-600pm Rotating Tues,Wed,Sat/Sun,Mon, Thurs,Fri | L43: C125457
A44: 288-45-9300 | B44: P2743411 | C44: FLX0533 | D44: Valeria Mendez (1181800) | E44: Richard Rios | F44: 146966394 | G44: 3855569276 | H44: FZ | I44: L | J44: Production Specialist 1 - Mechanical Assembly | K44: C Shift: Salt Lake City - O - 600am-600pm Rotating Sun,Mon,Thurs, Fri/Tues,Wed,Sat | L44: C125474
A45: 647-82-6059 | B45: P2743379 | C45: FLX0566 | D45: Yaritza Garza (1155856) | E45: Rojelio Facio | F45: 213751471 | G45: 8019199381 | H45: CN | I45: L | J45: Production Specialist 1 - Cold Room | K45: C Shift: Salt Lake City - O - 600am-600pm Rotating Sun,Mon,Thurs, Fri/Tues,Wed,Sat | L45: C125549
A46: 795197855 | B46: P2743389 | C46: FLX0556 | D46: Avigail Zamora | E46: Rosa Oscanoa | F46: 173097452 | G46: 8014037276 | H46: JM | I46: M | J46: Production Specialist 1 - Rack level Assembly | K46: D Shift: Salt Lake City - N - 600pm-600a Rotating Sun,Mon,Thurs, Fri/Tues,Wed,Sat (15% Diff) | L46: C125534
A47: 632912076 | B47: P2743408 | C47: FLX0536 | D47: Itzayana Maupouje (1224330) | E47: Sonia Oscano | F47: 133779635 | G47: 8014034619 | H47: JM | I47: M | J47: Production Specialist 1 - Mechanical Assembly | K47: D Shift: Salt Lake City - N - 600pm-600a Rotating Sun,Mon,Thurs, Fri/Tues,Wed,Sat (15% Diff) | L47: C125477
A48: 125-99-4316 | B48: P2743398 | C48: FLX0547 | D48: Cristian Vega (1135987) | E48: Susan Guedez | F48: 223441667 | G48: 3852458607 | H48: BL | I48: L | J48: Production Specialist 1 - Rack level Assembly | K48: B Shift: Salt Lake City - P - 600pm-600a Rotating Tues,Wed,Sat/Sun,Mon,Thurs,Fri (15% Diff) | L48: C125516
A49: 647-98-1758 | B49: P2743419 | C49: FLX0525 | D49: Deja Atwood (1153147) | E49: Sylvia S Molina | F49: 129454349 | G49: 3852161434 | H49: CN | I49: L | J49: Production Specialist 1 - Mechanical Assembly | K49: A Shift: Salt Lake City - Q - 600am-600pm Rotating Tues,Wed,Sat/Sun,Mon, Thurs,Fri | L49: C125458
A50: 646-62-4034 | B50: P2743404 | C50: FLX0541 | D50: Douglas Camargo (114508) | E50: Tommy Trujillo | F50: 95696069 | G50: 8016381761 | H50: GKW | I50: L | J50: Production Specialist 1 - Rack level Assembly | K50: A Shift: Salt Lake City - Q - 600am-600pm Rotating Tues,Wed,Sat/Sun,Mon, Thurs,Fri | L50: C125486
A51: 852282495 | B51: P2743373 | C51: FLX0584 | D51: Dallas Driggers (1156397) | E51: Xavier Pena | F51: 221407456 | G51: 4706588539 | H51: JM | I51: L | J51: Production Specialist 1 - Cold Room | K51: D Shift: Salt Lake City - N - 600pm-600a Rotating Sun,Mon,Thurs, Fri/Tues,Wed,Sat (15% Diff) | L51: C125554
A52: 657-31-6643 | B52: P2743378 | C52: FLX0579 | D52: Paola Guzman | E52: Yajayra N Chávez Mateo | F52: 218488208 | G52: 3856156852 | H52: BL | I52: M | J52: Production Specialist 1 - Materials | K52: B Shift: Salt Lake City - P - 600pm-600a Rotating Tues,Wed,Sat/Sun,Mon,Thurs,Fri (15% Diff) | L52: C125550
A53: 618-99-2444 | B53: P2743380 | C53: FLX0565 | D53: Yaritza Garza (1155856) | E53: Yeralina Ospino | F53: 146917168 | G53: (551) 323-7110 | H53: NM | I53: M | J53: Production Specialist 1 - Cold Room | K53: C Shift: Salt Lake City - O - 600am-600pm Rotating Sun,Mon,Thurs, Fri/Tues,Wed,Sat | L53: C125545
A54: 368-49-1236 | B54: P2743391 | C54: FLX0554 | D54: Avigail Zamora | J54: Production Specialist 1 - Rack level Assembly | K54: D Shift: Salt Lake City - N - 600pm-600a Rotating Sun,Mon,Thurs, Fri/Tues,Wed,Sat (15% Diff)
B55: P2743384 | C55: FLX0561 | D55: Avigail Zamora | J55: Production Specialist 1 - Rack level Assembly | K55: D Shift: Salt Lake City - N - 600pm-600a Rotating Sun,Mon,Thurs, Fri/Tues,Wed,Sat (15% Diff)
B56: P2743369 | C56: FLX0588 | D56: Avigail Zamora | J56: Production Specialist 1 - Rack level Assembly | K56: D Shift: Salt Lake City - N - 600pm-600a Rotating Sun,Mon,Thurs, Fri/Tues,Wed,Sat (15% Diff)
B57: P2743368 | C57: FLX0589 | D57: Avigail Zamora | J57: Production Specialist 1 - Rack level Assembly | K57: D Shift: Salt Lake City - N - 600pm-600a Rotating Sun,Mon,Thurs, Fri/Tues,Wed,Sat (15% Diff)

Sheet 4.20.26
A1: SSN | B1: P CODE | C1: Req # | D1: Supervisor | E1: Employee Name (must match Bold) | F1: Bold ID | G1: Phone # | H1: Recruiter | I1: Shirt Size | J1: Title | K1: Schedule | L1: C-Number | M1: BG | N1: I-9 | O1: E-Verify | P1: Flex AA | Q1: Onboarding Tasks | R1: Offer Letter | S1: NOTES
A2: 691-74-8336 | B2: P2730497 | C2: FLX0478 | D2: Braulio Antonio Querales Ocando (1154827) | E2: Patricia Avila | F2: 176121295 | G2: 7079087652 | H2: HB | J2: Production Specialist 1 - Cold Room | K2: B Shift: Salt Lake City - P - 600pm-600a Rotating Tues,Wed,Sat/Sun,Mon,Thurs,Fri (15% Diff) | L2: C121621
A3: 825-79-4605 | B3: P2730496 | C3: FLX0479 | D3: Cristian Vega (1135987) | E3: Juan Mejia | F3: 221234205 | G3: 4352689391 | H3: CN | J3: Production Specialist 1 - Rack level Assembly | K3: B Shift: Salt Lake City - P - 600pm-600a Rotating Tues,Wed,Sat/Sun,Mon,Thurs,Fri (15% Diff) | L3: C121622
A4: 730-20-2779 | B4: P2730495 | C4: FLX0480 | D4: Cristian Vega (1135987) | E4: James Lavaka | F4: 216591524 | G4: 3853477871 | H4: GKW | J4: Production Specialist 1 - Rack level Assembly | K4: B Shift: Salt Lake City - P - 600pm-600a Rotating Tues,Wed,Sat/Sun,Mon,Thurs,Fri (15% Diff) | L4: C121708
A5: 469-69-1282 | B5: P2730494 | C5: FLX0481 | D5: Cristian Vega (1135987) | E5: Glencis Pacheco | F5: 219091840 | G5: 3853790835 | H5: NM | I5: M | J5: Production Specialist 1 - Rack level Assembly | K5: B Shift: Salt Lake City - P - 600pm-600a Rotating Tues,Wed,Sat/Sun,Mon,Thurs,Fri (15% Diff) | L5: C121623
A6: 828-82-8605 | B6: P2730493 | C6: FLX0482 | D6: DANIEL FUENTES (1198897) | E6: Eritier Kalimendo | F6: 217220013 | G6: 3853189983 | H6: DR | J6: Production Specialist 1 - Rack level Assembly | K6: D Shift: Salt Lake City - N - 600pm-600a Rotating Sun,Mon,Thurs, Fri/Tues,Wed,Sat (15% Diff) | L6: C121682
A7: 752-54-0638 | B7: P2730488 | C7: FLX0501 | D7: Braulio Antonio Querales Ocando (1154827) | E7: Fabiana de los Angeles Rivas | F7: 215459191 | G7: 3852165410 | H7: HB | I7: M | J7: Production Specialist 1 - Cold Room | K7: B Shift: Salt Lake City - P - 600pm-600a Rotating Tues,Wed,Sat/Sun,Mon,Thurs,Fri (15% Diff) | L7: C121683
A8: 703-27-8143 | B8: P2730487 | C8: FLX0502 | D8: Braulio Antonio Querales Ocando (1154827) | E8: Hildemaro Vargas | F8: 221840574 | G8: 3854050571 | H8: NM | J8: Production Specialist 1 - Cold Room | K8: B Shift: Salt Lake City - P - 600pm-600a Rotating Tues,Wed,Sat/Sun,Mon,Thurs,Fri (15% Diff) | L8: C121680
A9: 758-36-7002 | B9: P2730486 | C9: FLX0503 | D9: Dallas Driggers (1156397) | E9: Lina Mendoza Mantilla | F9: 129270240 | G9: 7153106810 | H9: HB | I9: L | J9: Production Specialist 1 - Cold Room | K9: D Shift: Salt Lake City - N - 600pm-600a Rotating Sun,Mon,Thurs, Fri/Tues,Wed,Sat (15% Diff) | L9: C121699
A10: 645-25-5799 | B10: P2730483 | C10: FLX0512 | D10: Gaige Snow | E10: Dunia Kashama | F10: 95655178 | G10: 3853797801 | H10: DR | I10: L | J10: Production Specialist 1 - Materials | K10: D Shift: Salt Lake City - N - 600pm-600a Rotating Sun,Mon,Thurs, Fri/Tues,Wed,Sat (15% Diff) | L10: C121705
A11: 615-88-7154 | B11: P2730482 | C11: FLX0513 | D11: Francys Gates-Jimenez | E11: Laura Ambriz | F11: 96619838 | G11: 3853370012 | H11: JY | J11: Production Specialist 1 - Mechanical Assembly | K11: B Shift: Salt Lake City - P - 600pm-600a Rotating Tues,Wed,Sat/Sun,Mon,Thurs,Fri (15% Diff) | L11: C121710
A12: 105-77-3863 | B12: P2730481 | C12: FLX0514 | D12: Julissa Sencion (1154184) | E12: Marian Mendez | F12: 180458712 | G12: 8014405907 | H12: NM | J12: Production Specialist 1 - Mechanical Assembly | K12: C Shift: Salt Lake City - O - 600am-600pm Rotating Sun,Mon,Thurs, Fri/Tues,Wed,Sat | L12: C121709
A13: 350-31-8311 | B13: P2730480 | C13: FLX0515 | D13: Alejandro Castro (1213569) | E13: Yoselin Castillo | F13: 164911604 | G13: 8013853512 | H13: BL | I13: L | J13: Production Specialist 1 - Mechanical Assembly | K13: D Shift: Salt Lake City - N - 600pm-600a Rotating Sun,Mon,Thurs, Fri/Tues,Wed,Sat (15% Diff) | L13: C121673
A14: 801-89-1019 | B14: P2730479 | C14: FLX0516 | D14: Braulio Antonio Querales Ocando (1154827) | E14: Roderlys Quiche | F14: 218825186 | G14: 8013810242 | H14: BL | J14: Production Specialist 1 - Cold Room | K14: B Shift: Salt Lake City - P - 600pm-600a Rotating Tues,Wed,Sat/Sun,Mon,Thurs,Fri (15% Diff) | L14: C121703
A15: 803-77-0577 | B15: P2730478 | C15: FLX0517 | D15: Braulio Antonio Querales Ocando (1154827) | E15: Gina Medina | J15: Production Specialist 1 - Cold Room | K15: B Shift: Salt Lake City - P - 600pm-600a Rotating Tues,Wed,Sat/Sun,Mon,Thurs,Fri (15% Diff) | L15: C121695
B16: P2730477 | C16: FLX0518 | D16: Braulio Antonio Querales Ocando (1154827) | E16: Joanna Munoz | F16: 216559414 | G16: 3854439875 | H16: JY | I16: L | J16: Production Specialist 1 - Cold Room | K16: B Shift: Salt Lake City - P - 600pm-600a Rotating Tues,Wed,Sat/Sun,Mon,Thurs,Fri (15% Diff) | L16: C121697
A17: 158-65-4105 | B17: P2730476 | C17: FLX0519 | D17: Braulio Antonio Querales Ocando (1154827) | E17: Desiree Roa | F17: 199708572 | G17: 3854366356 | H17: JY | I17: L | J17: Production Specialist 1 - Cold Room | K17: B Shift: Salt Lake City - P - 600pm-600a Rotating Tues,Wed,Sat/Sun,Mon,Thurs,Fri (15% Diff) | L17: C121692
B18: P2730475 | C18: FLX0520 | D18: Dallas Driggers (1156397) | E18: Orlando Herrera | F18: 146893715 | G18: 3854143049 | H18: NM | J18: Production Specialist 1 - Cold Room | K18: D Shift: Salt Lake City - N - 600pm-600a Rotating Sun,Mon,Thurs, Fri/Tues,Wed,Sat (15% Diff) | L18: C121691

Sheet 4.16.26
A1: SSN | B1: P CODE | C1: Req # | D1: Supervisor | E1: Employee Name (must match Bold) | F1: Bold ID | G1: Phone # | H1: Recruiter | I1: Shirt Size | J1: Title | K1: Schedule | L1: C-Number | M1: BG | N1: I-9 | O1: E-Verify | P1: Flex AA | Q1: Onboarding Tasks | R1: Offer Letter | S1: NOTES
A2: 882-35-4192 | B2: P2730474 | C2: FLX0455 | D2: Christopher Villanueva (1172510) | E2: Genesis Uribe | F2: 217304054 | G2: 8014730897 | H2: NM | J2: Production Specialist 1 - Inventory Control | K2: C Shift: Salt Lake City - O - 600am-600pm Rotating Sun,Mon,Thurs, Fri/Tues,Wed,Sat | L2: C121563
A3: 646-20-1437 | B3: P2730473 | C3: FLX0456 | D3: Gaige Snow | E3: William Palmer | F3: 220925042 | G3: 8012099890 | H3: SCG | I3: XXXL | J3: Production Specialist 1 - Materials | K3: D Shift: Salt Lake City - N - 600pm-600a Rotating Sun,Mon,Thurs, Fri/Tues,Wed,Sat (15% Diff) | L3: C121564
A4: 389-39-1147 | B4: P2730472 | C4: FLX0457 | D4: Gaige Snow | E4: Luis Ferrer | F4: 185242799 | G4: 3855838763 | H4: NM | J4: Production Specialist 1 - Materials | K4: D Shift: Salt Lake City - N - 600pm-600a Rotating Sun,Mon,Thurs, Fri/Tues,Wed,Sat (15% Diff) | L4: C121565
A5: 068-47-4851 | B5: P2730471 | C5: FLX0458 | D5: LUIS LEON CABALLERO (1182844) | E5: Luis Huincho Arango | F5: 217968857 | G5: 3858746002 | H5: SCG | I5: L | J5: Production Specialist 1 - Materials | K5: B Shift: Salt Lake City - P - 600pm-600a Rotating Tues,Wed,Sat/Sun,Mon,Thurs,Fri (15% Diff) | L5: C121580
B6: P2730470 | C6: FLX0459 | D6: LUIS LEON CABALLERO (1182844) | E6: Alondra Portillo | F6: 134090007 | G6: 8012051714 | H6: NM | J6: Production Specialist 1 - Materials | K6: B Shift: Salt Lake City - P - 600pm-600a Rotating Tues,Wed,Sat/Sun,Mon,Thurs,Fri (15% Diff) | L6: C121585
B7: P2730469 | C7: FLX0460 | D7: LUIS LEON CABALLERO (1182844) | E7: Franklin Marroquin | F7: 221153634 | G7: 8016697856 | H7: NM | J7: Production Specialist 1 - Materials | K7: B Shift: Salt Lake City - P - 600pm-600a Rotating Tues,Wed,Sat/Sun,Mon,Thurs,Fri (15% Diff) | L7: C121586
A8: 506-79-6282 | B8: P2730468 | C8: FLX0461 | D8: LUIS LEON CABALLERO (1182844) | E8: Michael Baron Cabezas | F8: 218644588 | G8: 8015143474 | H8: DR | I8: L | J8: Production Specialist 1 - Materials | K8: B Shift: Salt Lake City - P - 600pm-600a Rotating Tues,Wed,Sat/Sun,Mon,Thurs,Fri (15% Diff) | L8: C121587
B9: P2730467 | C9: FLX0462 | D9: Mel Kellar (1142020) | E9: Stockton Chidester | F9: 218584822 | G9: 8017392785 | H9: BL | I9: XXL | J9: Production Specialist 1 - Materials | K9: D Shift: Salt Lake City - N - 600pm-600a Rotating Sun,Mon,Thurs, Fri/Tues,Wed,Sat (15% Diff) | L9: C121588
A10: 828-07-9365 | B10: P2730466 | C10: FLX0463 | D10: Mel Kellar (1142020) | E10: Sandra Ruiz Salgado | F10: 182082642 | G10: 3855367759 | H10: NM | I10: M | J10: Production Specialist 1 - Materials | K10: D Shift: Salt Lake City - N - 600pm-600a Rotating Sun,Mon,Thurs, Fri/Tues,Wed,Sat (15% Diff) | L10: C121589
B11: P2730465 | C11: FLX0464 | D11: Mel Kellar (1142020) | E11: Keily Solorzano Torrealba | F11: 158472406 | G11: 8016340336 | H11: SCG | I11: S | J11: Production Specialist 1 - Materials | K11: D Shift: Salt Lake City - N - 600pm-600a Rotating Sun,Mon,Thurs, Fri/Tues,Wed,Sat (15% Diff) | L11: C121590
A12: 181-35-1192 | B12: P2730464 | C12: FLX0465 | D12: Francys Gates-Jimenez | E12: Maria Cristina Preciado Montana | F12: 218644615 | G12: 8015143518 | H12: DR | I12: M | J12: Production Specialist 1 - Mechanical Assembly | K12: B Shift: Salt Lake City - P - 600pm-600a Rotating Tues,Wed,Sat/Sun,Mon,Thurs,Fri (15% Diff) | L12: C121591
A13: 646-88-4213 | B13: P2730463 | C13: FLX0466 | D13: Francys Gates-Jimenez | E13: Anayelli Diaz Esparza | F13: 221004268 | G13: 8012095874 | H13: FZ | I13: L | J13: Production Specialist 1 - Mechanical Assembly | K13: B Shift: Salt Lake City - P - 600pm-600a Rotating Tues,Wed,Sat/Sun,Mon,Thurs,Fri (15% Diff) | L13: C121592
A14: 695-24-9320 | B14: P2730462 | C14: FLX0467 | D14: Francys Gates-Jimenez | E14: Idel Silva | F14: 218432819 | G14: 8013014999 | H14: NM | I14: XXL | J14: Production Specialist 1 - Mechanical Assembly | K14: B Shift: Salt Lake City - P - 600pm-600a Rotating Tues,Wed,Sat/Sun,Mon,Thurs,Fri (15% Diff) | L14: C121593
A15: 646-16-5884 | B15: P2730461 | C15: FLX0468 | D15: Francys Gates-Jimenez | E15: Marggie Pugh | F15: 119560966 | G15: 8016082769 | H15: SCG | I15: M | J15: Production Specialist 1 - Mechanical Assembly | K15: B Shift: Salt Lake City - P - 600pm-600a Rotating Tues,Wed,Sat/Sun,Mon,Thurs,Fri (15% Diff) | L15: C121594
A16: 612-54-4947 | B16: P2730460 | C16: FLX0469 | D16: Francys Gates-Jimenez | E16: Priscilla Castillo | F16: 218038437 | G16: 8016083151 | H16: HB | I16: M | J16: Production Specialist 1 - Mechanical Assembly | K16: B Shift: Salt Lake City - P - 600pm-600a Rotating Tues,Wed,Sat/Sun,Mon,Thurs,Fri (15% Diff) | L16: C121595
A17: 761-88-3062 | B17: P2730505 | C17: FLX0470 | D17: Francys Gates-Jimenez | E17: Johanna Sierra | F17: 113602446 | G17: 8016805508 | H17: NM | I17: L | J17: Production Specialist 1 - Mechanical Assembly | K17: B Shift: Salt Lake City - P - 600pm-600a Rotating Tues,Wed,Sat/Sun,Mon,Thurs,Fri (15% Diff) | L17: C121596
A18: 726-37-6439 | B18: P2730504 | C18: FLX0471 | D18: Francys Gates-Jimenez | E18: Vahideh Rayeneh | F18: 120136427 | G18: 9495994823 | H18: DR | I18: M | J18: Production Specialist 1 - Mechanical Assembly | K18: B Shift: Salt Lake City - P - 600pm-600a Rotating Tues,Wed,Sat/Sun,Mon,Thurs,Fri (15% Diff) | L18: C121597
A19: 849-56-4258 | B19: P2730503 | C19: FLX0472 | D19: Francys Gates-Jimenez | E19: Jorge Villarreal Lung | F19: 218763933 | G19: 8013016176 | H19: NM | I19: L | J19: Production Specialist 1 - Mechanical Assembly | K19: B Shift: Salt Lake City - P - 600pm-600a Rotating Tues,Wed,Sat/Sun,Mon,Thurs,Fri (15% Diff) | L19: C121598
B20: P2730502 | C20: FLX0473 | D20: Francys Gates-Jimenez | E20: Cesar Obando | F20: 155325318 | G20: 3853159922 | H20: HB | I20: L | J20: Production Specialist 1 - Mechanical Assembly | K20: B Shift: Salt Lake City - P - 600pm-600a Rotating Tues,Wed,Sat/Sun,Mon,Thurs,Fri (15% Diff) | L20: C121599
B21: P2730501 | C21: FLX0474 | D21: Braulio Antonio Querales Ocando (1154827) | E21: Eric Ahumada | F21: 219148124 | G21: 4359383183 | H21: NM | J21: Production Specialist 1 - Cold Room | K21: B Shift: Salt Lake City - P - 600pm-600a Rotating Tues,Wed,Sat/Sun,Mon,Thurs,Fri (15% Diff) | L21: C121600
A22: 394-99-3058 | B22: P2730500 | C22: FLX0475 | D22: Braulio Antonio Querales Ocando (1154827) | E22: Ana Vargas | F22: 220951266 | G22: 3853718847 | H22: NM | J22: Production Specialist 1 - Cold Room | K22: B Shift: Salt Lake City - P - 600pm-600a Rotating Tues,Wed,Sat/Sun,Mon,Thurs,Fri (15% Diff) | L22: C121601
A23: 010-11-4341 | B23: P2730499 | C23: FLX0476 | D23: Braulio Antonio Querales Ocando (1154827) | E23: Cesar Paredes | F23: 220962745 | G23: (385) 445-0455 | H23: NM | I23: L | J23: Production Specialist 1 - Cold Room | K23: B Shift: Salt Lake City - P - 600pm-600a Rotating Tues,Wed,Sat/Sun,Mon,Thurs,Fri (15% Diff) | L23: C121602
B24: P2730498 | C24: FLX0477 | D24: Braulio Antonio Querales Ocando (1154827) | E24: Robinson Portillo | F24: 220528859 | G24: 3855036486 | H24: NM | J24: Production Specialist 1 - Cold Room | K24: B Shift: Salt Lake City - P - 600pm-600a Rotating Tues,Wed,Sat/Sun,Mon,Thurs,Fri (15% Diff) | L24: C121603
A25: 889-68-4289 | B25: P2730492 | C25: FLX0483 | D25: Castalia Marino | E25: Alejandro Ettorre | F25: 218591892 | G25: 8323424113 | H25: NM | I25: XXL | J25: Production Specialist 1 - Materials | K25: A Shift: Salt Lake City - Q - 600am-600pm Rotating Tues,Wed,Sat/Sun,Mon, Thurs,Fri | L25: C121604
A26: 125-49-9271 | B26: P2730491 | C26: FLX0492 | D26: Mariana Ballesteros (1174672) | E26: Gledys Camacho lambrano | F26: 189705387 | G26: 3854367384 | H26: NM | I26: L | J26: Production Specialist 1 - Materials | K26: C Shift: Salt Lake City - O - 600am-600pm Rotating Sun,Mon,Thurs, Fri/Tues,Wed,Sat | L26: C121604
A27: 635-55-4867 | B27: P2730490 | C27: FLX0493 | D27: Barbara Garcia (1137177) | E27: Yusmari Marquez | F27: 218550875 | G27: 3463045262 | H27: NM | J27: Production Specialist 1 - Mechanical Assembly | K27: A Shift: Salt Lake City - Q - 600am-600pm Rotating Tues,Wed,Sat/Sun,Mon, Thurs,Fri | L27: C121605
A28: 289-33-9089 | B28: P2730489 | C28: FLX0500 | D28: Patricia Puche Curiel | E28: Neyda Lacruz | F28: 161215884 | G28: 8013309295 | H28: NM | I28: M | J28: Production Specialist 1 - Debug Cold Room L2 | K28: C Shift: Salt Lake City - O - 600am-600pm Rotating Sun,Mon,Thurs, Fri/Tues,Wed,Sat | L28: C121606
A29: 886-28-5490 | B29: P2730485 | C29: FLX0504 | D29: Alondra Landin (1152847) | E29: Sonia Guerrero Pena | F29: 215485132 | G29: 385 5514290 | H29: NM | I29: XL | J29: Production Specialist 1 - Rack level Assembly | K29: A Shift: Salt Lake City - Q - 600am-600pm Rotating Tues,Wed,Sat/Sun,Mon, Thurs,Fri | L29: C121607
A30: 850-04-6318 | B30: P2730484 | C30: FLX0505 | D30: Alondra Landin (1152847) | E30: Jorsil Vido Tahan | F30: 215485052 | G30: 3855884652 | H30: NM | I30: L | J30: Production Specialist 1 - Rack level Assembly | K30: A Shift: Salt Lake City - Q - 600am-600pm Rotating Tues,Wed,Sat/Sun,Mon, Thurs,Fri | L30: C121608

Sheet 3.23.26
A1: SSN | B1: P CODE | C1: Req # | D1: Supervisor | E1: Employee Name (must match Bold) | F1: Bold ID | G1: Phone # | H1: Recruiter | I1: Shirt Size | J1: Title | K1: Schedule | L1: C-Number | M1: BG | N1: I-9 | O1: E-Verify | P1: Flex AA | Q1: Onboarding Tasks | R1: Offer Letter | S1: NOTES
B2: P2727332 | C2: FLX0365 | D2: Castalia Marino | E2: Betzaida henriquez | F2: 185189753 | G2: 8014102119 | H2: NM | J2: Production Specialist 1 - Materials | K2: A Shift: Salt Lake City - Q - 600am-600pm Rotating Tues,Wed,Sat/Sun,Mon, Thurs,Fri | L2: C121017
B3: P2727331 | C3: FLX0366 | D3: Castalia Marino | E3: Stephanie Pimentel | F3: 209054687 | G3: 714 657-0986 | H3: NM | J3: Production Specialist 1 - Materials | K3: A Shift: Salt Lake City - Q - 600am-600pm Rotating Tues,Wed,Sat/Sun,Mon, Thurs,Fri | L3: C121018

Sheet 3.16.26
A1: SSN | B1: P CODE | C1: Req # | D1: Supervisor | E1: Employee Name (must match Bold) | F1: Bold ID | G1: Phone # | H1: Recruiter | I1: Shirt Size | J1: Title | K1: Schedule | L1: C-Number | M1: BG | N1: I-9 | O1: E-Verify | P1: Flex AA | Q1: Onboarding Tasks | R1: Offer Letter | S1: NOTES
B2: P2721659 | C2: FLX0308 | D2: Alejandro Castro (1213569) | E2: Yorgan Vergara | F2: 185855628 | G2: +1 (385) 252-2185 | H2: BL | J2: Production Specialist 1 - Mechanical Assembly | K2: D Shift: Salt Lake City - N - 600pm-600a Rotating Sun,Mon,Thurs, Fri/Tues,Wed,Sat (15% Diff) | L2: C120700
B3: P5001547 | C3: FLX0333 | D3: Barbara Garcia (1137177) | E3: Gerardo Barboza | F3: 134507919 | G3: 385-471-6153 | H3: FZ | I3: XXL | J3: Production Specialist 1 - Mechanical Assembly | K3: A Shift: Salt Lake City - Q - 600am-600pm Rotating Tues,Wed,Sat/Sun,Mon, Thurs,Fri | L3: C120694

Sheet 3.19.26
A1: SSN | B1: P CODE | C1: Req # | D1: Supervisor | E1: Employee Name (must match Bold) | F1: Bold ID | G1: Phone # | H1: Recruiter | I1: Shirt Size | J1: Title | K1: Schedule | L1: C-Number | M1: BG | N1: I-9 | O1: E-Verify | P1: Flex AA | Q1: Onboarding Tasks | R1: Offer Letter | S1: NOTES
A2: 646963466 | B2: P2727333 | C2: FLX0364 | D2: Castalia Marino | E2: Dulce M Lopez | F2: 198189443 | G2: 3852950100 | H2: JY | I2: L | J2: Production Specialist 1 - Materials | K2: A Shift: Salt Lake City - Q - 600am-600pm Rotating Tues,Wed,Sat/Sun,Mon, Thurs,Fri | L2: C120820
A3: 656-82-2422 | B3: P2727332 | C3: FLX0365 | D3: Castalia Marino | E3: Betzaida henriquez | F3: 185189753 | G3: 8014102119 | H3: NM | J3: Production Specialist 1 - Materials | K3: A Shift: Salt Lake City - Q - 600am-600pm Rotating Tues,Wed,Sat/Sun,Mon, Thurs,Fri | L3: C120821
B4: P2727331 | C4: FLX0366 | D4: Castalia Marino | E4: Rubeilys Chavez Medina | F4: 217621069 | G4: 8016007137 | H4: FZ | J4: Production Specialist 1 - Materials | K4: A Shift: Salt Lake City - Q - 600am-600pm Rotating Tues,Wed,Sat/Sun,Mon, Thurs,Fri | L4: C120822
A5: 655-29-6742 | B5: P2727330 | C5: FLX0383 | D5: Sanel Kudic (1148108) | E5: Tony Jovo | F5: 218446551 | G5: 4072886356 | H5: NM | I5: XL | J5: Production Specialist 1 - Materials | K5: B Shift: Salt Lake City - P - 600pm-600a Rotating Tues,Wed,Sat/Sun,Mon,Thurs,Fri (15% Diff) | L5: C120823
A6: 786-16-8517 | B6: P2727329 | C6: FLX0384 | D6: Sanel Kudic (1148108) | E6: Maira Colmenarez | F6: 182102784 | G6: 8529853652 | H6: NM | I6: L | J6: Production Specialist 1 - Materials | K6: B Shift: Salt Lake City - P - 600pm-600a Rotating Tues,Wed,Sat/Sun,Mon,Thurs,Fri (15% Diff) | L6: C120825
A7: 644-51-4709 | B7: P2727328 | C7: FLX0385 | D7: Sanel Kudic (1148108) | E7: Gledis Salave | F7: 217581295 | G7: 7065377975 | H7: NM | I7: M | J7: Production Specialist 1 - Materials | K7: B Shift: Salt Lake City - P - 600pm-600a Rotating Tues,Wed,Sat/Sun,Mon,Thurs,Fri (15% Diff) | L7: C120826
A8: 286-61-8127 | B8: P2727327 | C8: FLX0386 | D8: Sanel Kudic (1148108) | E8: Adalmiro Martinez | F8: 201730403 | G8: 3854309136 | H8: NM | I8: L | J8: Production Specialist 1 - Materials | K8: B Shift: Salt Lake City - P - 600pm-600a Rotating Tues,Wed,Sat/Sun,Mon,Thurs,Fri (15% Diff) | L8: C120827
A9: 834652716 | B9: P2723364 | C9: FLX0318 | D9: Angel Tirado (1179499) | E9: Roxana Concha | F9: 217966053 | G9: 8019499263 | H9: SM | I9: S | J9: Production Specialist 1 - Materials | K9: A Shift: Salt Lake City - Q - 600am-600pm Rotating Tues,Wed,Sat/Sun,Mon, Thurs,Fri | L9: C120828

Sheet 3.12.26
A1: SSN | B1: P CODE | C1: Req # | D1: Supervisor | E1: Employee Name (must match Bold) | F1: Bold ID | G1: Phone # | H1: Recruiter | I1: Shirt Size | J1: Title | K1: Schedule | L1: C-Number | M1: BG | N1: I-9 | O1: E-Verify | P1: Flex AA | Q1: Onboarding Tasks | R1: Offer Letter | S1: NOTES
A2: 297-98-5702 | B2: P2725272 | C2: FLX0272 | D2: Douglas Camargo (114508) | E2: Julia Babylon | F2: 203107944 | G2: 9375737564 | H2: DG | I2: M | J2: Production Specialist 1 - Cold Room | K2: C Shift: Salt Lake City - O - 600am-600pm Rotating Sun,Mon,Thurs, Fri/Tues,Wed,Sat | L2: C120395
A3: 646-26-8312 | B3: P2725266 | C3: FLX0282 | D3: Dallas Driggers (1156397) | E3: Austin Wheelwright | F3: 187032504 | G3: 385-225-5273 | H3: NR | I3: L | J3: Production Specialist 1 - Cold Room | K3: D Shift: Salt Lake City - N - 600pm-600a Rotating Sun,Mon,Thurs, Fri/Tues,Wed,Sat (15% Diff) | L3: C120396
A4: 899-68-8599 | B4: P2725264 | C4: FLX0284 | D4: Cristian Vega (1135987) | E4: Yudexi Hernandez | F4: 121211456 | G4: 801-671-3971 | H4: SCG | I4: M | J4: Production Specialist 1 - Rack level Assembly | K4: B Shift: Salt Lake City - P - 600pm-600a Rotating Tues,Wed,Sat/Sun,Mon,Thurs,Fri (15% Diff) | L4: C120397
A5: 838-51-6513 | B5: P2720966 | C5: FLX0321 | D5: Alberto Sardi | E5: Ruth Cuicapuza Alfoncio | F5: 181401512 | G5: 3855630085 | H5: NM | I5: M | J5: Production Specialist 1 - Mechanical Assembly | K5: A Shift: Salt Lake City - Q - 600am-600pm Rotating Tues,Wed,Sat/Sun,Mon, Thurs,Fri | L5: C120398
A6: 841-47-7814 | B6: P2692072 | C6: FLX0322 | D6: Alejandro Castro (1213569) | E6: Hernan Reyes | F6: 218899818 | G6: 3855474822 | H6: NM | I6: XXL | J6: Production Specialist 1 - Mechanical Assembly | K6: D Shift: Salt Lake City - N - 600pm-600a Rotating Sun,Mon,Thurs, Fri/Tues,Wed,Sat (15% Diff) | L6: C120399
A7: 737-35-4828 | B7: P2704159 | C7: FLX0323 | D7: Alejandro Castro (1213569) | E7: Roberto Tahan | F7: 121211082 | G7: 8016713944 | H7: SCG | I7: L | J7: Production Specialist 1 - Mechanical Assembly | K7: D Shift: Salt Lake City - N - 600pm-600a Rotating Sun,Mon,Thurs, Fri/Tues,Wed,Sat (15% Diff) | L7: C120400
A8: 218-53-3665 | B8: P2613300 | C8: FLX0324 | D8: Alejandro Castro (1213569) | E8: Damaris Gutierrez | F8: 198514018 | G8: 3855849513 | H8: NM | I8: M | J8: Production Specialist 1 - Mechanical Assembly | K8: D Shift: Salt Lake City - N - 600pm-600a Rotating Sun,Mon,Thurs, Fri/Tues,Wed,Sat (15% Diff) | L8: C120401
A9: 882-96-3874 | B9: P2719507 | C9: FLX0325 | D9: Alejandro Castro (1213569) | E9: Yeimar Hernandez Molina | F9: 176567281 | G9: 3854842488 | H9: NM | I9: XL | J9: Production Specialist 1 - Mechanical Assembly | K9: D Shift: Salt Lake City - N - 600pm-600a Rotating Sun,Mon,Thurs, Fri/Tues,Wed,Sat (15% Diff) | L9: C120402
A10: 750-46-8437 | B10: P2721706 | C10: FLX0326 | D10: Alejandro Castro (1213569) | E10: Ruth Ricaurte | F10: 199219797 | G10: 8016349048 | H10: BL | I10: XXL | J10: Production Specialist 1 - Mechanical Assembly | K10: D Shift: Salt Lake City - N - 600pm-600a Rotating Sun,Mon,Thurs, Fri/Tues,Wed,Sat (15% Diff) | L10: C120403
A11: 346-49-6275 | B11: P2670014 | C11: FLX0329 | D11: Itzayana Maupouje (1224330) | E11: Katherine Urribarri | F11: 173080631 | G11: 3855623691 | H11: NM | I11: S | J11: Production Specialist 1 - Mechanical Assembly | K11: D Shift: Salt Lake City - N - 600pm-600a Rotating Sun,Mon,Thurs, Fri/Tues,Wed,Sat (15% Diff) | L11: C120412
A12: 578-89-6575 | B12: P2722729 | C12: FLX0331 | D12: Alondra Landin (1152847) | E12: Samir Moron | F12: 177706983 | G12: 385-588-9898 | H12: DR | I12: M | J12: Production Specialist 1 - Rack level Assembly | K12: A Shift: Salt Lake City - Q - 600am-600pm Rotating Tues,Wed,Sat/Sun,Mon, Thurs,Fri | L12: C120404
B13: P5001547 | C13: FLX0333 | D13: Barbara Garcia (1137177) | E13: Aysha Romero | F13: 152758106 | G13: 6129980796 | H13: DR | J13: Production Specialist 1 - Mechanical Assembly | K13: A Shift: Salt Lake City - Q - 600am-600pm Rotating Tues,Wed,Sat/Sun,Mon, Thurs,Fri | L13: C120405
A14: 003-71-7801 | B14: P2723350 | C14: FLX0337 | D14: Cristian Vega (1135987) | E14: Claudia Alvarado | F14: 218263391 | G14: 8014046579 | H14: BL | I14: XXL | J14: Production Specialist 1 - Rack level Assembly | K14: B Shift: Salt Lake City - P - 600pm-600a Rotating Tues,Wed,Sat/Sun,Mon,Thurs,Fri (15% Diff) | L14: C120406
